Workbook

Sheet Dashboard
A1: ETE IT PMO — Resource & Project Management Dashboard
B3: TEAM SIZE | E3: WEEKLY CAPACITY | H3: TEAM UTILIZATION | L3: starting / available time | O3: use 10/10/80
B4: =COUNTA('Team Roster'!A4:A26) -> 23 | E4: ='Team Roster'!K27 -> 438.74 | H4: =I15 -> 0.105158 | L4: allocation of available time: allocate 10% allocation for admin, 15% for break/fix, 75% for projects - 40 hour week
B5: Total resources | E5: Net project hrs/wk | H5: Across active weeks
L6: this gives us our model of resource availability; meetings should be focused on the project and project plan
B7: RESOURCE CAPACITY OVERVIEW
B8: Team | C8: Headcount | D8: Weekly Hrs | E8: Support Reserve | F8: Net Capacity | G8: Avg Allocated | H8: Available | I8: Utilization | L8: for ba's / sdlc: 75% of effort on a project (of the 10%) is in discovery and planning
B9: Synnergie (ERP) | C9: =COUNTIF('Team Roster'!$C$4:$C$26,"ERP") -> 8 | D9: =SUMIF('Team Roster'!$C$4:$C$26,"ERP",'Team Roster'!$G$4:$G$26) -> 280 | E9: =SUMIF('Team Roster'!$C$4:$C$26,"ERP",'Team Roster'!$J$4:$J$26) -> 105 | F9: =SUMIF('Team Roster'!$C$4:$C$26,"ERP",'Team Roster'!$K$4:$K$26) -> 175 | G9: {=IFERROR(SUMPRODUCT(('Capacity Heatmap'!$C$5:$C$26="Synnergie")*(MMULT(IF('Capacity Heatmap'!$E$5:$AD$26>0,'Capacity Heatmap'!$E$5:$AD$26,0),_xlfn.SEQUENCE(26,1,1,0))/IF(MMULT(IF('Capacity Heatmap'!$E$5:$AD$26>0,1,0),_xlfn.SEQUENCE(26,1,1,0))>0,MMULT(IF('Capacity Heatmap'!$E$5:$AD$26>0,1,0),_xlfn.SEQUENCE(26,1,1,0)),1))*'Capacity Heatmap'!$D$5:$D$26),0)} -> 13.5 | H9: =F9-G9 -> 161.5 | I9: =IF(F9>0,G9/F9,0) -> 0.077142857 | L9: rest of their time is the other / remainder
B10: Systems Applications | C10: =COUNTIF('Team Roster'!$C$4:$C$26,"Systems Applications") -> 4 | D10: =SUMIF('Team Roster'!$C$4:$C$26,"Systems Applications",'Team Roster'!$G$4:$G$26) -> 100 | E10: =SUMIF('Team Roster'!$C$4:$C$26,"Systems Applications",'Team Roster'!$J$4:$J$26) -> 31.25 | F10: =SUMIF('Team Roster'!$C$4:$C$26,"Systems Applications",'Team Roster'!$K$4:$K$26) -> 68.75 | G10: {=IFERROR(SUMPRODUCT(('Capacity Heatmap'!$C$5:$C$26="Systems Applications")*(MMULT(IF('Capacity Heatmap'!$E$5:$AD$26>0,'Capacity Heatmap'!$E$5:$AD$26,0),_xlfn.SEQUENCE(26,1,1,0))/IF(MMULT(IF('Capacity Heatmap'!$E$5:$AD$26>0,1,0),_xlfn.SEQUENCE(26,1,1,0))>0,MMULT(IF('Capacity Heatmap'!$E$5:$AD$26>0,1,0),_xlfn.SEQUENCE(26,1,1,0)),1))*'Capacity Heatmap'!$D$5:$D$26),0)} -> 20.869565 | H10: =F10-G10 -> 47.880435 | I10: =IF(F10>0,G10/F10,0) -> 0.30355731 | L10: technical side (discovery/ planning) - 5-%, design is 50-75%, build is 75%-80%
B11: Business Analysts | C11: =COUNTIF('Team Roster'!$C$4:$C$26,"Business Analysts") -> 4 | D11: =SUMIF('Team Roster'!$C$4:$C$26,"Business Analysts",'Team Roster'!$G$4:$G$26) -> 145 | E11: =SUMIF('Team Roster'!$C$4:$C$26,"Business Analysts",'Team Roster'!$J$4:$J$26) -> 66 | F11: =SUMIF('Team Roster'!$C$4:$C$26,"Business Analysts",'Team Roster'!$K$4:$K$26) -> 79 | G11: {=IFERROR(SUMPRODUCT(('Capacity Heatmap'!$C$5:$C$26="Business Analysts")*(MMULT(IF('Capacity Heatmap'!$E$5:$AD$26>0,'Capacity Heatmap'!$E$5:$AD$26,0),_xlfn.SEQUENCE(26,1,1,0))/IF(MMULT(IF('Capacity Heatmap'!$E$5:$AD$26>0,1,0),_xlfn.SEQUENCE(26,1,1,0))>0,MMULT(IF('Capacity Heatmap'!$E$5:$AD$26>0,1,0),_xlfn.SEQUENCE(26,1,1,0)),1))*'Capacity Heatmap'!$D$5:$D$26),0)} -> 8.7674572 | H11: =F11-G11 -> 70.232543 | I11: =IF(F11>0,G11/F11,0) -> 0.11098047
B12: Infrastructure | C12: =COUNTIF('Team Roster'!$C$4:$C$26,"Infrastructure") -> 3 | D12: =SUMIF('Team Roster'!$C$4:$C$26,"Infrastructure",'Team Roster'!$G$4:$G$26) -> 120 | E12: =SUMIF('Team Roster'!$C$4:$C$26,"Infrastructure",'Team Roster'!$J$4:$J$26) -> 72 | F12: =SUMIF('Team Roster'!$C$4:$C$26,"Infrastructure",'Team Roster'!$K$4:$K$26) -> 48 | G12: {=IFERROR(SUMPRODUCT(('Capacity Heatmap'!$C$5:$C$26="Infrastructure")*(MMULT(IF('Capacity Heatmap'!$E$5:$AD$26>0,'Capacity Heatmap'!$E$5:$AD$26,0),_xlfn.SEQUENCE(26,1,1,0))/IF(MMULT(IF('Capacity Heatmap'!$E$5:$AD$26>0,1,0),_xlfn.SEQUENCE(26,1,1,0))>0,MMULT(IF('Capacity Heatmap'!$E$5:$AD$26>0,1,0),_xlfn.SEQUENCE(26,1,1,0)),1))*'Capacity Heatmap'!$D$5:$D$26),0)} -> 0 | H12: =F12-G12 -> 48 | I12: =IF(F12>0,G12/F12,0) -> 0 | L12: no more than 3 projects per person at a time
B13: WMS | C13: =COUNTIF('Team Roster'!$C$4:$C$26,"WMS") -> 1 | D13: =SUMIF('Team Roster'!$C$4:$C$26,"WMS",'Team Roster'!$G$4:$G$26) -> 35 | E13: =SUMIF('Team Roster'!$C$4:$C$26,"WMS",'Team Roster'!$J$4:$J$26) -> 21 | F13: =SUMIF('Team Roster'!$C$4:$C$26,"WMS",'Team Roster'!$K$4:$K$26) -> 14 | G13: {=IFERROR(SUMPRODUCT(('Capacity Heatmap'!$C$5:$C$26="WMS")*(MMULT(IF('Capacity Heatmap'!$E$5:$AD$26>0,'Capacity Heatmap'!$E$5:$AD$26,0),_xlfn.SEQUENCE(26,1,1,0))/IF(MMULT(IF('Capacity Heatmap'!$E$5:$AD$26>0,1,0),_xlfn.SEQUENCE(26,1,1,0))>0,MMULT(IF('Capacity Heatmap'!$E$5:$AD$26>0,1,0),_xlfn.SEQUENCE(26,1,1,0)),1))*'Capacity Heatmap'!$D$5:$D$26),0)} -> 0 | H13: =F13-G13 -> 14 | I13: =IF(F13>0,G13/F13,0) -> 0
B14: PMO | C14: =COUNTIF('Team Roster'!$C$4:$C$26,"PMO") -> 3 | D14: =SUMIF('Team Roster'!$C$4:$C$26,"PMO",'Team Roster'!$G$4:$G$26) -> 102 | E14: =SUMIF('Team Roster'!$C$4:$C$26,"PMO",'Team Roster'!$J$4:$J$26) -> 48.01 | F14: =SUMIF('Team Roster'!$C$4:$C$26,"PMO",'Team Roster'!$K$4:$K$26) -> 53.99 | G14: {=IFERROR(SUMPRODUCT(('Capacity Heatmap'!$C$5:$C$26="PMO")*(MMULT(IF('Capacity Heatmap'!$E$5:$AD$26>0,'Capacity Heatmap'!$E$5:$AD$26,0),_xlfn.SEQUENCE(26,1,1,0))/IF(MMULT(IF('Capacity Heatmap'!$E$5:$AD$26>0,1,0),_xlfn.SEQUENCE(26,1,1,0))>0,MMULT(IF('Capacity Heatmap'!$E$5:$AD$26>0,1,0),_xlfn.SEQUENCE(26,1,1,0)),1))*'Capacity Heatmap'!$D$5:$D$26),0)} -> 3 | H14: =F14-G14 -> 50.99 | I14: =IF(F14>0,G14/F14,0) -> 0.055565846 | L14: once developers are done, then ba's go from 10-15% to 25%-30%
B15: TOTAL | C15: =SUM(C9:C14) -> 23 | D15: =SUM(D9:D14) -> 782 | E15: =SUM(E9:E14) -> 343.26 | F15: =SUM(F9:F14) -> 438.74 | G15: =SUM(G9:G14) -> 46.137022 | H15: =SUM(H9:H14) -> 392.60298 | I15: =IF(F15>0,G15/F15,0) -> 0.105158
L16: need multiple dimensions in the model for how we visualize the projects - some might be businer in some phases
B17: PROJECT STATUS SUMMARY
B18: Category | C18: Total | D18: Complete | E18: In Progress | F18: Not Started | G18: Needs Help | H18: Needs Spec | I18: Postponed | J18: % Complete | L18: 32 hours, divide by 2, 16 hours free for something else - gives availability of who's red and and not; assign people to rosters
B19: Project Portfolio | C19: =COUNTA('Project Portfolio'!A4:A42)-COUNTBLANK('Project Portfolio'!A4:A42) -> 37 | D19: =COUNTIF('Project Portfolio'!F4:F42,"✅ COMPLETE") -> 16 | E19: =COUNTIF('Project Portfolio'!F4:F42,"🟢 ON TRACK")+COUNTIF('Project Portfolio'!F4:F42,"🔵 ON HOLD") -> 4 | F19: =COUNTIF('Project Portfolio'!F4:F42,"⚪ NOT STARTED") -> 2 | G19: =COUNTIF('Project Portfolio'!F4:F42,"🟡 AT RISK")+COUNTIF('Project Portfolio'!F4:F42,"🔴 NEEDS ATTENTION") -> 0 | H19: =COUNTIF('Project Portfolio'!F4:F42,"📋 NEEDS TECHNICAL SPEC")+COUNTIF('Project Portfolio'!F4:F42,"📋 NEEDS FUNCTIONAL SPEC") -> 7 | I19: =COUNTIF('Project Portfolio'!F4:F42,"⏸️ POSTPONED")+COUNTIF('Project Portfolio'!F4:F42,"⏳ AWAITING APPROVAL") -> 9 | J19: =IF(C19>0,D19/C19,0) -> 0.43243243
L20: can be assigned to more than 2-3 projeects start/ end at different times
L21: identify how much work is required per resource type per week; maybe as an ex: 300 per ba: have more demand than supply
G22: must have staggerred start dates based on resource capacity adn avail | L22: heatmap to change when we add an additional person b/c more resources
G23: dates, groups, resource capacity, etc.. amount of work does not change | L23: do we have all the right people or not
G24: but as we move dates it should change heatmap b/c of availability

Sheet Team Roster
A1: ETE IT PMO — Team Roster & Capacity
A3: Resource | B3: Role | C3: Team | D3: Vendor | E3: Resource Classification | F3: Rate/Hour | G3: Weekly Hrs Available | H3: Support Reserve % | I3: Project Capacity % | J3: Support Reserve (hrs/wk) | K3: Project Capacity (hrs/wk)
A4: Ajay Kumar | B4: Functional | C4: ERP | D4: Synnergie | E4: MSA | F4: 65 | G4: 35 | H4: 0.4 | I4: =1-H4 -> 0.6 | J4: =G4*H4 -> 14 | K4: =G4*I4 -> 21
A5: Ravindra Reddy | B5: Technical | C5: ERP | D5: Synnergie | E5: MSA | F5: 65 | G5: 35 | H5: 0.4 | I5: =1-H5 -> 0.6 | J5: =G5*H5 -> 14 | K5: =G5*I5 -> 21
A6: Vishnu Premen | B6: Technical | C6: ERP | D6: Synnergie | E6: =IF(D6="Synnergie","T&M",IF(D6="Watermark","MSA",IF(D6="ETE","Internal",""))) -> T&M | F6: 65 | G6: 35 | H6: 0.4 | I6: =1-H6 -> 0.6 | J6: =G6*H6 -> 14 | K6: =G6*I6 -> 21
A7: Deepak Gudwani | B7: Functional | C7: ERP | D7: Synnergie | E7: =IF(D7="Synnergie","T&M",IF(D7="Watermark","MSA",IF(D7="ETE","Internal",""))) -> T&M | F7: 65 | G7: 35 | H7: 0.4 | I7: =1-H7 -> 0.6 | J7: =G7*H7 -> 14 | K7: =G7*I7 -> 21
A8: Sangamesh Koti | B8: Technical | C8: ERP | D8: Synnergie | E8: T&M | F8: 65 | G8: 35 | H8: 0 | I8: =1-H8 -> 1 | J8: =G8*H8 -> 0 | K8: =G8*I8 -> 35
A9: Bhavya Reddy | B9: Technical | C9: ERP | D9: Synnergie | E9: =IF(D9="Synnergie","T&M",IF(D9="Watermark","MSA",IF(D9="ETE","Internal",""))) -> T&M | F9: 65 | G9: 35 | H9: 0 | I9: =1-H9 -> 1 | J9: =G9*H9 -> 0 | K9: =G9*I9 -> 35
A10: Sarath Yeturu | B10: Technical | C10: ERP | D10: Synnergie | E10: MSA | F10: 65 | G10: 35 | H10: 0.6 | I10: =1-H10 -> 0.4 | J10: =G10*H10 -> 21 | K10: =G10*I10 -> 14
A11: Vinod Bollepally | B11: DBA | C11: ERP | D11: Synnergie | E11: MSA | F11: 65 | G11: 35 | H11: 0.8 | I11: =1-H11 -> 0.2 | J11: =G11*H11 -> 28 | K11: =G11*I11 -> 7
A12: Jim Young | B12: Business Analyst | C12: Business Analysts | D12: ETE | E12: =IF(D12="Synnergie","T&M",IF(D12="Watermark","MSA",IF(D12="ETE","Internal",""))) -> Internal | F12: 65 | G12: 40 | H12: 0.6 | I12: =1-H12 -> 0.4 | J12: =G12*H12 -> 24 | K12: =G12*I12 -> 16
A13: Alex Young | B13: Developer | C13: Systems Applications | D13: ETE | E13: =IF(D13="Synnergie","T&M",IF(D13="Watermark","MSA",IF(D13="ETE","Internal",""))) -> Internal | F13: 65 | G13: 25 | H13: 0.5 | I13: =1-H13 -> 0.5 | J13: =G13*H13 -> 12.5 | K13: =G13*I13 -> 12.5
A14: Nick Smith | B14: Developer | C14: Systems Applications | D14: ETE | E14: =IF(D14="Synnergie","T&M",IF(D14="Watermark","MSA",IF(D14="ETE","Internal",""))) -> Internal | F14: 65 | G14: 25 | H14: 0.4 | I14: =1-H14 -> 0.6 | J14: =G14*H14 -> 10 | K14: =G14*I14 -> 15
A15: Colin Olson | B15: Developer | C15: Systems Applications | D15: ETE | E15: =IF(D15="Synnergie","T&M",IF(D15="Watermark","MSA",IF(D15="ETE","Internal",""))) -> Internal | F15: 65 | G15: 25 | H15: 0.1 | I15: =1-H15 -> 0.9 | J15: =G15*H15 -> 2.5 | K15: =G15*I15 -> 22.5
A16: Jonathon Gonzalez | B16: Developer | C16: Systems Applications | D16: ETE | E16: =IF(D16="Synnergie","T&M",IF(D16="Watermark","MSA",IF(D16="ETE","Internal",""))) -> Internal | F16: 65 | G16: 25 | H16: 0.25 | I16: =1-H16 -> 0.75 | J16: =G16*H16 -> 6.25 | K16: =G16*I16 -> 18.75
A17: Audrey Debaere | B17: Business Analyst | C17: Business Analysts | D17: ETE | E17: =IF(D17="Synnergie","T&M",IF(D17="Watermark","MSA",IF(D17="ETE","Internal",""))) -> Internal | F17: 65 | G17: 35 | H17: 0.5 | I17: =1-H17 -> 0.5 | J17: =G17*H17 -> 17.5 | K17: =G17*I17 -> 17.5
A18: Cristian Varelas | B18: Business Analyst | C18: Business Analysts | D18: ETE | E18: =IF(D18="Synnergie","T&M",IF(D18="Watermark","MSA",IF(D18="ETE","Internal",""))) -> Internal | F18: 65 | G18: 35 | H18: 0.2 | I18: =1-H18 -> 0.8 | J18: =G18*H18 -> 7 | K18: =G18*I18 -> 28
A19: Ryan Picado | B19: Business Analyst | C19: Business Analysts | D19: ETE | E19: =IF(D19="Synnergie","T&M",IF(D19="Watermark","MSA",IF(D19="ETE","Internal",""))) -> Internal | F19: 65 | G19: 35 | H19: 0.5 | I19: =1-H19 -> 0.5 | J19: =G19*H19 -> 17.5 | K19: =G19*I19 -> 17.5
A20: Emily Fridley | B20: Project Manager | C20: PMO | D20: ETE | E20: =IF(D20="Synnergie","T&M",IF(D20="Watermark","MSA",IF(D20="ETE","Internal",""))) -> Internal | F20: 65 | G20: 35 | H20: 0.5 | I20: =1-H20 -> 0.5 | J20: =G20*H20 -> 17.5 | K20: =G20*I20 -> 17.5
A21: Brett Anderson | B21: Project Manager | C21: PMO | D21: ETE | E21: =IF(D21="Synnergie","T&M",IF(D21="Watermark","MSA",IF(D21="ETE","Internal",""))) -> Internal | F21: 65 | G21: 35 | H21: 0.25 | I21: =1-H21 -> 0.75 | J21: =G21*H21 -> 8.75 | K21: =G21*I21 -> 26.25
A22: Bettina Kotico | B22: Project Manager | C22: PMO | D22: Kayana | E22: T&M | F22: 65 | G22: 32 | H22: 0.68 | I22: =1-H22 -> 0.32 | J22: =G22*H22 -> 21.76 | K22: =G22*I22 -> 10.24
A23: Donna Wiedemeier | B23: WMS Consultant | C23: WMS | D23: Watermark | E23: T&M | F23: 65 | G23: 35 | H23: 0.6 | I23: =1-H23 -> 0.4 | J23: =G23*H23 -> 21 | K23: =G23*I23 -> 14
A24: Justin Senour | B24: Infrastructure | C24: Infrastructure | D24: ETE | E24: =IF(D24="Synnergie","T&M",IF(D24="Watermark","MSA",IF(D24="ETE","Internal",""))) -> Internal | F24: 65 | G24: 40 | H24: 0.6 | I24: =1-H24 -> 0.4 | J24: =G24*H24 -> 24 | K24: =G24*I24 -> 16
A25: Michael House | B25: Infrastructure | C25: Infrastructure | D25: ETE | E25: =IF(D25="Synnergie","T&M",IF(D25="Watermark","MSA",IF(D25="ETE","Internal",""))) -> Internal | F25: 65 | G25: 40 | H25: 0.6 | I25: =1-H25 -> 0.4 | J25: =G25*H25 -> 24 | K25: =G25*I25 -> 16
A26: Andrew Shaefer | B26: Infrastructure | C26: Infrastructure | D26: ETE | E26: =IF(D26="Synnergie","T&M",IF(D26="Watermark","MSA",IF(D26="ETE","Internal",""))) -> Internal | F26: 65 | G26: 40 | H26: 0.6 | I26: =1-H26 -> 0.4 | J26: =G26*H26 -> 24 | K26: =G26*I26 -> 16
A27: TOTALS | G27: =SUM(G4:G26) -> 782 | H27: =IF(G27>0,J27/G27,0) -> 0.43895141 | I27: =IF(G27>0,K27/G27,0) -> 0.56104859 | J27: =SUM(J4:J26) -> 343.26 | K27: =SUM(K4:K26) -> 438.74

Sheet Project Portfolio
A1: ETE IT PMO — Project Portfolio
A3: ID | B3: Project Name | C3: Type | D3: Business Portfolio | E3: Sponsor/Leader | F3: Project Health | G3: % Complete | H3: Priority | I3: Start Date | J3: Est. End Date | K3: Actual/Updated End | L3: Team | M3: PM | N3: BA | O3: Functional | P3: Technical | Q3: T-Shirt Size | R3: Est. Hours | S3: Est. Cost Range | T3: BA % | U3: Functional % | V3: Technical % | W3: Developer % | X3: Infrastructure % | Y3: DBA % | Z3: PM % | AA3: WMS % | AB3: Notes | AC3: Sort Order
A4: ETE-83 | B4: Customer Master Data Cleanup | C4: Key Initiative | D4: Sales & Distribution | E4: Tom Vierling | F4: 📋 NEEDS TECHNICAL SPEC | G4: 0.15 | H4: High | I4: 45944 | J4: 46174 | L4: Systems Applications | N4: Jim Young | Q4: XXL: > 640 Hours | R4: 1480 | S4: =$R4*65 -> 96200 | T4: 0.1 | AB4: Completed Q1 | AC4: =IF(OR(ISNUMBER(SEARCH("POSTPONED",$F4)),ISNUMBER(SEARCH("NOT APPROVED",$F4))),2,IF(ISNUMBER(SEARCH("COMPLETE",$F4)),3,1)) -> 1
A5: ETE-48 | B5: System Connection Syteline-VKS | C5: Key Initiative | D5: Engineering | E5: Ray Trumble | F5: 🟢 ON TRACK | G5: 0.1 | H5: High | I5: 46068 | J5: 46203 | L5: Synnergie | M5: Emily Fridley | Q5: L: 160-320 Hours | R5: 240 | S5: =$R5*65 -> 15600 | T5: 0.1 | Z5: 0.25 | AC5: =IF(OR(ISNUMBER(SEARCH("POSTPONED",$F5)),ISNUMBER(SEARCH("NOT APPROVED",$F5))),2,IF(ISNUMBER(SEARCH("COMPLETE",$F5)),3,1)) -> 1
A6: ETE-68 | B6: Catalog API Rust2Python | C6: Key Initiative | D6: Information Technology | E6: Jim Koscielniak | F6: 🟢 ON TRACK | G6: 0.13 | H6: High | I6: 45978 | J6: 46136 | L6: Systems Applications | N6: Cristian Varelas | P6: Colin Olson | Q6: XXL: > 640 Hours | R6: 640 | S6: =$R6*65 -> 41600 | T6: 0.1 | W6: 0.75 | AC6: =IF(OR(ISNUMBER(SEARCH("POSTPONED",$F6)),ISNUMBER(SEARCH("NOT APPROVED",$F6))),2,IF(ISNUMBER(SEARCH("COMPLETE",$F6)),3,1)) -> 1
A7: ETE-43 | B7: Data Security - Microsoft Purview | C7: Key Initiative | D7: Information Technology | E7: Jim Koscielniak | F7: 🟢 ON TRACK | G7: 0 | H7: High | I7: 46055 | J7: 46203 | L7: Infrastructure | R7: 0 | S7: =$R7*65 -> 0 | T7: 0.1 | AC7: =IF(OR(ISNUMBER(SEARCH("POSTPONED",$F7)),ISNUMBER(SEARCH("NOT APPROVED",$F7))),2,IF(ISNUMBER(SEARCH("COMPLETE",$F7)),3,1)) -> 1
A8: ETE-19 | B8: Changes to AR Aging Report | C8: Enhancement | D8: Finance | E8: Tom Newell | F8: 🟢 ON TRACK | G8: 0 | H8: High | I8: 46076 | J8: 46129 | L8: Synnergie | N8: Audrey Debaere | O8: Ajay Kumar | P8: Bhavya Reddy | Q8: M: 80-160 Hours | R8: 120 | S8: =$R8*65 -> 7800 | T8: 0.1 | U8: 0.25 | V8: 0.65 | AC8: =IF(OR(ISNUMBER(SEARCH("POSTPONED",$F8)),ISNUMBER(SEARCH("NOT APPROVED",$F8))),2,IF(ISNUMBER(SEARCH("COMPLETE",$F8)),3,1)) -> 1
A9: ETE-49 | B9: Marketing: STE Rewards Tier | C9: Enhancement | D9: Sales & Distribution | E9: Tom Vierling | F9: 📋 NEEDS TECHNICAL SPEC | G9: 0 | H9: Medium | L9: Systems Applications | N9: Cristian Varelas | Q9: L: 160-320 Hours | R9: 240 | S9: =$R9*65 -> 15600 | T9: 0.1 | U9: 0 | V9: 0 | W9: 0.75 | X9: 0 | Y9: 0 | Z9: 0 | AA9: 0 | AC9: =IF(OR(ISNUMBER(SEARCH("POSTPONED",$F9)),ISNUMBER(SEARCH("NOT APPROVED",$F9))),2,IF(ISNUMBER(SEARCH("COMPLETE",$F9)),3,1)) -> 1
A10: ETE-7 | B10: Outsourced Unit Core Accounting | C10: Enhancement | D10: Finance | E10: Tom Newell | F10: 📋 NEEDS FUNCTIONAL SPEC | G10: 0 | H10: Medium | L10: Synnergie | N10: Audrey Debaere | Q10: XXL: > 640 Hours | R10: 640 | S10: =$R10*65 -> 41600 | T10: 0.1 | U10: 0.25 | V10: 0.65 | W10: 0 | X10: 0 | Y10: 0 | Z10: 0 | AA10: 0 | AB10: 8-9 month project | AC10: =IF(OR(ISNUMBER(SEARCH("POSTPONED",$F10)),ISNUMBER(SEARCH("NOT APPROVED",$F10))),2,IF(ISNUMBER(SEARCH("COMPLETE",$F10)),3,1)) -> 1
A11: ETE-52 | B11: SWIMS/Syteline Reporting | C11: Enhancement | D11: Supply Chain | E11: Jon Besherse | F11: 📋 NEEDS TECHNICAL SPEC | G11: 0 | H11: Medium | L11: Systems Applications | N11: Ryan Picado | Q11: S: < 80 Hours | R11: 40 | S11: =$R11*65 -> 2600 | T11: 0.1 | U11: 0 | V11: 0 | W11: 0.75 | X11: 0 | Y11: 0 | Z11: 0 | AA11: 0 | AC11: =IF(OR(ISNUMBER(SEARCH("POSTPONED",$F11)),ISNUMBER(SEARCH("NOT APPROVED",$F11))),2,IF(ISNUMBER(SEARCH("COMPLETE",$F11)),3,1)) -> 1
A12: ETE-16 | B12: Partial Pay w/ CC from WMERP | C12: Enhancement | D12: Finance | E12: Tom Newell | F12: ⚪ NOT STARTED | G12: 0 | H12: Medium | L12: Synnergie | Q12: M: 80-160 Hours | R12: 120 | S12: =$R12*65 -> 7800 | T12: 0.1 | U12: 0.25 | V12: 0.65 | W12: 0 | X12: 0 | Y12: 0 | Z12: 0 | AA12: 0 | AC12: =IF(OR(ISNUMBER(SEARCH("POSTPONED",$F12)),ISNUMBER(SEARCH("NOT APPROVED",$F12))),2,IF(ISNUMBER(SEARCH("COMPLETE",$F12)),3,1)) -> 1
A13: ETE-37 | B13: Magic Search in BuyETE | C13: Enhancement | D13: Sales & Distribution | E13: Tom Vierling | F13: 📋 NEEDS TECHNICAL SPEC | G13: 0 | H13: Highest | L13: Systems Applications | N13: Cristian Varelas | Q13: S: < 80 Hours | R13: 40 | S13: =$R13*65 -> 2600 | T13: 0.1 | U13: 0.25 | V13: 0 | W13: 0.65 | X13: 0 | Y13: 0 | Z13: 0 | AA13: 0 | AC13: =IF(OR(ISNUMBER(SEARCH("POSTPONED",$F13)),ISNUMBER(SEARCH("NOT APPROVED",$F13))),2,IF(ISNUMBER(SEARCH("COMPLETE",$F13)),3,1)) -> 1
A14: ETE-97 | B14: Standard Order Process Notifications | C14: Enhancement | D14: Sales & Distribution | E14: Tom Vierling | F14: ⚪ NOT STARTED | G14: 0 | H14: Highest | L14: Systems Applications | R14: 200 | S14: =$R14*65 -> 13000 | T14: 0.1 | U14: 0 | V14: 0 | W14: 0.75 | X14: 0 | Y14: 0 | Z14: 0 | AA14: 0 | AC14: =IF(OR(ISNUMBER(SEARCH("POSTPONED",$F14)),ISNUMBER(SEARCH("NOT APPROVED",$F14))),2,IF(ISNUMBER(SEARCH("COMPLETE",$F14)),3,1)) -> 1
A15: ETE-100 | B15: ATSG Expired Members Self-Payment | C15: Enhancement | D15: Sales & Distribution | E15: Tom Vierling | F15: 📋 NEEDS FUNCTIONAL SPEC | G15: 0 | H15: Medium | L15: Systems Applications | R15: 200 | S15: =$R15*65 -> 13000 | T15: 0.1 | U15: 0 | V15: 0 | W15: 0.75 | X15: 0 | Y15: 0 | Z15: 0 | AA15: 0 | AC15: =IF(OR(ISNUMBER(SEARCH("POSTPONED",$F15)),ISNUMBER(SEARCH("NOT APPROVED",$F15))),2,IF(ISNUMBER(SEARCH("COMPLETE",$F15)),3,1)) -> 1
A16: ETE-124 | B16: Clean Up Return Loads | C16: Enhancement | D16: Finance | E16: Tom Newell | F16: 📋 NEEDS TECHNICAL SPEC | G16: 0 | H16: Highest | L16: Synnergie | R16: 200 | S16: =$R16*65 -> 13000 | T16: 0.1 | U16: 0.25 | V16: 0.75 | W16: 0 | X16: 0 | Y16: 0 | Z16: 0 | AA16: 0 | AC16: =IF(OR(ISNUMBER(SEARCH("POSTPONED",$F16)),ISNUMBER(SEARCH("NOT APPROVED",$F16))),2,IF(ISNUMBER(SEARCH("COMPLETE",$F16)),3,1)) -> 1
AC17: =IF(OR(ISNUMBER(SEARCH("POSTPONED",$F17)),ISNUMBER(SEARCH("NOT APPROVED",$F17))),2,IF(ISNUMBER(SEARCH("COMPLETE",$F17)),3,1)) -> 1
A18: ETE-58 | B18: Transfer Order Moved Items to Transit Location | C18: Enhancement | D18: Finance | E18: Jim Young | F18: ⏸️ POSTPONED | G18: 0 | AC18: =IF(OR(ISNUMBER(SEARCH("POSTPONED",$F18)),ISNUMBER(SEARCH("NOT APPROVED",$F18))),2,IF(ISNUMBER(SEARCH("COMPLETE",$F18)),3,1)) -> 2
A19: ETE-51 | B19: RMA Credit Memo on Ghost Check-In | C19: Enhancement | D19: Finance | E19: Tom Newell | F19: ⏸️ POSTPONED | G19: 0 | AC19: =IF(OR(ISNUMBER(SEARCH("POSTPONED",$F19)),ISNUMBER(SEARCH("NOT APPROVED",$F19))),2,IF(ISNUMBER(SEARCH("COMPLETE",$F19)),3,1)) -> 2
A20: ETE-59 | B20: Reconcile BridgePay CC Transactions | C20: Enhancement | D20: Finance | E20: Tom Newell | F20: ⏸️ POSTPONED | G20: 0 | AC20: =IF(OR(ISNUMBER(SEARCH("POSTPONED",$F20)),ISNUMBER(SEARCH("NOT APPROVED",$F20))),2,IF(ISNUMBER(SEARCH("COMPLETE",$F20)),3,1)) -> 2
A21: ETE-60 | B21: EDI Payments Not Posting on Background | C21: Enhancement | D21: Finance | E21: Tom Newell | F21: ⏸️ POSTPONED | G21: 0 | AC21: =IF(OR(ISNUMBER(SEARCH("POSTPONED",$F21)),ISNUMBER(SEARCH("NOT APPROVED",$F21))),2,IF(ISNUMBER(SEARCH("COMPLETE",$F21)),3,1)) -> 2
A22: ETE-61 | B22: Accum Deposits Received Field | C22: Bug | D22: Finance | E22: Tom Newell | F22: ⏸️ POSTPONED | G22: 0 | AC22: =IF(OR(ISNUMBER(SEARCH("POSTPONED",$F22)),ISNUMBER(SEARCH("NOT APPROVED",$F22))),2,IF(ISNUMBER(SEARCH("COMPLETE",$F22)),3,1)) -> 2
A23: ETE-86 | B23: Allow TCM Core Receiving to Post | C23: Enhancement | D23: Engineering | E23: Ray Trumble | F23: ⏸️ POSTPONED | G23: 0 | AC23: =IF(OR(ISNUMBER(SEARCH("POSTPONED",$F23)),ISNUMBER(SEARCH("NOT APPROVED",$F23))),2,IF(ISNUMBER(SEARCH("COMPLETE",$F23)),3,1)) -> 2
A24: ETE-34 | B24: Salesforce BDR Application & Process Implementation | C24: Enhancement | D24: Sales & Distribution | E24: Tom Vierling | F24: ⏸️ POSTPONED | G24: 0 | AC24: =IF(OR(ISNUMBER(SEARCH("POSTPONED",$F24)),ISNUMBER(SEARCH("NOT APPROVED",$F24))),2,IF(ISNUMBER(SEARCH("COMPLETE",$F24)),3,1)) -> 2
A25: ETE-35 | B25: BuyETE Ability for Customers to Save Quotes | C25: Enhancement | D25: Sales & Distribution | E25: Tom Vierling | F25: ⏸️ POSTPONED | G25: 0 | AC25: =IF(OR(ISNUMBER(SEARCH("POSTPONED",$F25)),ISNUMBER(SEARCH("NOT APPROVED",$F25))),2,IF(ISNUMBER(SEARCH("COMPLETE",$F25)),3,1)) -> 2
A26: ETE-33 | B26: EDI 3PL Locations | C26: Enhancement | D26: Sales & Distribution | E26: Tom Vierling | F26: ⏸️ POSTPONED | G26: 0 | H26: High | L26: Systems Applications | N26: Jim Young | Q26: M: 80-160 Hours | R26: 120 | AC26: =IF(OR(ISNUMBER(SEARCH("POSTPONED",$F26)),ISNUMBER(SEARCH("NOT APPROVED",$F26))),2,IF(ISNUMBER(SEARCH("COMPLETE",$F26)),3,1)) -> 2
A27: ETE-67 | B27: Avalara Tax Issues | C27: Enhancement | D27: Finance | E27: Tom Newell | F27: ✅ COMPLETE | G27: 1 | H27: Highest | I27: 46057 | J27: 46080 | L27: Synnergie | N27: Audrey Debaere | O27: Deepak Gudwani | P27: Sangamesh Koti | Q27: M: 80-160 Hours | R27: 120 | S27: =$R27*65 -> 7800 | T27: 0.1 | U27: 0.25 | V27: 0.75 | AC27: =IF(OR(ISNUMBER(SEARCH("POSTPONED",$F27)),ISNUMBER(SEARCH("NOT APPROVED",$F27))),2,IF(ISNUMBER(SEARCH("COMPLETE",$F27)),3,1)) -> 3
A28: ETE-14 | B28: Installed Return RMA Type | C28: Enhancement | D28: Supply Chain | E28: Jon Besherse | F28: ✅ COMPLETE | G28: 1 | H28: Highest | I28: 46083 | J28: 46101 | L28: Synnergie | N28: Audrey Debaere | Q28: M: 80-160 Hours | R28: 120 | S28: =$R28*65 -> 7800 | T28: 0.1 | U28: 0.25 | V28: 0.65 | AC28: =IF(OR(ISNUMBER(SEARCH("POSTPONED",$F28)),ISNUMBER(SEARCH("NOT APPROVED",$F28))),2,IF(ISNUMBER(SEARCH("COMPLETE",$F28)),3,1)) -> 3
A29: ETE-70 | B29: Nutanix (Replace VMware) | C29: Key Initiative | D29: Information Technology | E29: Jim Koscielniak | F29: ✅ COMPLETE | G29: 1 | H29: Highest | I29: 45992 | J29: 46102 | L29: Infrastructure | P29: Michael House | R29: 120 | S29: =$R29*65 -> 7800 | T29: 0.1 | X29: 0.5 | AC29: =IF(OR(ISNUMBER(SEARCH("POSTPONED",$F29)),ISNUMBER(SEARCH("NOT APPROVED",$F29))),2,IF(ISNUMBER(SEARCH("COMPLETE",$F29)),3,1)) -> 3
A30: ETE-65 | B30: Rebuild Vendor Portal | C30: Enhancement | D30: Sales & Distribution | E30: Tom Vierling | F30: ✅ COMPLETE | G30: 1 | H30: High | I30: 45957 | J30: 46031 | K30: 46068 | L30: Systems Applications | N30: Jim Young | P30: Jonathon Gonzalez | Q30: S: < 80 Hours | R30: 60 | S30: 11895 | AC30: =IF(OR(ISNUMBER(SEARCH("POSTPONED",$F30)),ISNUMBER(SEARCH("NOT APPROVED",$F30))),2,IF(ISNUMBER(SEARCH("COMPLETE",$F30)),3,1)) -> 3
A31: ETE-69 | B31: Core Plan Optimization | C31: Key Initiative | D31: Supply Chain | E31: Jon Besherse | F31: ✅ COMPLETE | G31: 1 | H31: High | I31: 45973 | J31: 46045 | K31: 46045 | L31: Synnergie | N31: Audrey Debaere | P31: Ravindra Reddy | Q31: L: 160-320 Hours | R31: 360 | S31: 16120 | AC31: =IF(OR(ISNUMBER(SEARCH("POSTPONED",$F31)),ISNUMBER(SEARCH("NOT APPROVED",$F31))),2,IF(ISNUMBER(SEARCH("COMPLETE",$F31)),3,1)) -> 3
A32: ETE-31 | B32: Restocking Fees Added to RMA Credit Memo | C32: Enhancement | D32: Finance | E32: Tom Newell | F32: ✅ COMPLETE | G32: 1 | H32: High | I32: 45648 | J32: 46059 | K32: 46081 | L32: Synnergie | N32: Audrey Debaere | P32: Bhavya Reddy | Q32: L: 160-320 Hours | R32: 310 | S32: 1625 | AC32: =IF(OR(ISNUMBER(SEARCH("POSTPONED",$F32)),ISNUMBER(SEARCH("NOT APPROVED",$F32))),2,IF(ISNUMBER(SEARCH("COMPLETE",$F32)),3,1)) -> 3
A33: ETE-45 | B33: VB Bin Printer Integration | C33: Enhancement | D33: Engineering | E33: Ray Trumble | F33: ✅ COMPLETE | G33: 1 | H33: High | I33: 45950 | J33: 46073 | K33: 46073 | L33: Synnergie | N33: Cristian Varelas | P33: Sangamesh Koti | Q33: M: 80-160 Hours | R33: 160 | S33: 260 | AC33: =IF(OR(ISNUMBER(SEARCH("POSTPONED",$F33)),ISNUMBER(SEARCH("NOT APPROVED",$F33))),2,IF(ISNUMBER(SEARCH("COMPLETE",$F33)),3,1)) -> 3
A34: ETE-42 | B34: Gear Screen - Improved Production Oversight | C34: Key Initiative | D34: Production | E34: Ari Rosengarten | F34: ✅ COMPLETE | G34: 1 | H34: High | I34: 46034 | J34: 46058 | K34: 46081 | L34: Synnergie | N34: Cristian Varelas | P34: Vishnu Premen | Q34: M: 80-160 Hours | R34: 120 | AB34: NAPA not ready | AC34: =IF(OR(ISNUMBER(SEARCH("POSTPONED",$F34)),ISNUMBER(SEARCH("NOT APPROVED",$F34))),2,IF(ISNUMBER(SEARCH("COMPLETE",$F34)),3,1)) -> 3
A35: ETE-72 | B35: Fortigate ZTNA - EMS Setup | C35: Key Initiative | D35: Information Technology | E35: Jim Koscielniak | F35: ✅ COMPLETE | G35: 1 | H35: High | I35: 46003 | J35: 46022 | K35: 46080 | L35: Infrastructure | P35: Justin Senour | R35: 0 | AC35: =IF(OR(ISNUMBER(SEARCH("POSTPONED",$F35)),ISNUMBER(SEARCH("NOT APPROVED",$F35))),2,IF(ISNUMBER(SEARCH("COMPLETE",$F35)),3,1)) -> 3
A36: ETE-71 | B36: One Drive Migration | C36: Key Initiative | D36: Information Technology | E36: Jim Koscielniak | F36: ✅ COMPLETE | G36: 1 | H36: High | I36: 46013 | J36: 46059 | K36: 46068 | L36: Infrastructure | P36: Michael House | R36: 0 | AC36: =IF(OR(ISNUMBER(SEARCH("POSTPONED",$F36)),ISNUMBER(SEARCH("NOT APPROVED",$F36))),2,IF(ISNUMBER(SEARCH("COMPLETE",$F36)),3,1)) -> 3
A37: ETE-87 | B37: Production Dashboard | C37: Enhancement | D37: Production | E37: Ari Rosengarten | F37: ✅ COMPLETE | G37: 1 | H37: High | L37: Systems Applications | Q37: S: < 80 Hours | R37: 40 | AC37: =IF(OR(ISNUMBER(SEARCH("POSTPONED",$F37)),ISNUMBER(SEARCH("NOT APPROVED",$F37))),2,IF(ISNUMBER(SEARCH("COMPLETE",$F37)),3,1)) -> 3
A38: ETE-88 | B38: Return Load Phase 2 | C38: Key Initiative | D38: Finance | E38: Tom Newell | F38: ✅ COMPLETE | G38: 1 | H38: High | I38: 45957 | J38: 46020 | K38: 46031 | L38: Synnergie | N38: Audrey Debaere | P38: Sangamesh Koti | R38: 320 | AC38: =IF(OR(ISNUMBER(SEARCH("POSTPONED",$F38)),ISNUMBER(SEARCH("NOT APPROVED",$F38))),2,IF(ISNUMBER(SEARCH("COMPLETE",$F38)),3,1)) -> 3
A39: ETE-73 | B39: Teal Parts Daily Inventory Feed | C39: Enhancement | D39: Sales & Distribution | E39: Tom Vierling | F39: ✅ COMPLETE | G39: 1 | H39: Highest | L39: Systems Applications | N39: Cristian Varelas | Q39: S: < 80 Hours | R39: 40 | AC39: =IF(OR(ISNUMBER(SEARCH("POSTPONED",$F39)),ISNUMBER(SEARCH("NOT APPROVED",$F39))),2,IF(ISNUMBER(SEARCH("COMPLETE",$F39)),3,1)) -> 3
A40: ETE-10 | B40: Upload Utility for Planning Fields | C40: Enhancement | D40: Supply Chain | E40: Tom Green | F40: ✅ COMPLETE | G40: 0.1 | H40: Highest | L40: Synnergie | N40: Audrey Debaere | Q40: S: < 80 Hours | R40: 80 | AC40: =IF(OR(ISNUMBER(SEARCH("POSTPONED",$F40)),ISNUMBER(SEARCH("NOT APPROVED",$F40))),2,IF(ISNUMBER(SEARCH("COMPLETE",$F40)),3,1)) -> 3
A41: ETE-32 | B41: Form: Cash App SQL Fix | C41: Enhancement | D41: Finance | E41: Tom Newell | F41: ✅ COMPLETE | G41: 1 | H41: High | L41: Synnergie | N41: Audrey Debaere | Q41: L: 160-320 Hours | R41: 320 | AC41: =IF(OR(ISNUMBER(SEARCH("POSTPONED",$F41)),ISNUMBER(SEARCH("NOT APPROVED",$F41))),2,IF(ISNUMBER(SEARCH("COMPLETE",$F41)),3,1)) -> 3
A42: ETE-76 | B42: FedEx Web Services API | C42: Enhancement | D42: Information Technology | E42: Jim Koscielniak | F42: ✅ COMPLETE | G42: 0 | H42: High | I42: 46084 | J42: 46094 | L42: Systems Applications | N42: Jim Young | P42: Alex Young | Q42: S: < 80 Hours | R42: 40 | AC42: =IF(OR(ISNUMBER(SEARCH("POSTPONED",$F42)),ISNUMBER(SEARCH("NOT APPROVED",$F42))),2,IF(ISNUMBER(SEARCH("COMPLETE",$F42)),3,1)) -> 3

Sheet Project Timeline
A1: ETE IT PMO — Project Timeline (Gantt View)
A2: Auto-populated from Project Portfolio | Non-complete projects only | Red line = current week
G3: January 2026 | K3: February 2026 | O3: March 2026 | T3: April 2026 | X3: May 2026 | AB3: June 2026 | AG3: July 2026 | AK3: August 2026 | AP3: September 2026 | AT3: October 2026 | AX3: November 2026 | BC3: December 2026
A4: # | B4: Project ID | C4: Project Name | D4: Project Health | E4: Start | F4: End | G4: 46027 | H4: 46034 | I4: 46041 | J4: 46048 | K4: 46055 | L4: 46062 | M4: 46069 | N4: 46076 | O4: 46083 | P4: 46090 | Q4: 46097 | R4: 46104 | S4: 46111 | T4: 46118 | U4: 46125 | V4: 46132 | W4: 46139 | X4: 46146 | Y4: 46153 | Z4: 46160 | AA4: 46167 | AB4: 46174 | AC4: 46181 | AD4: 46188 | AE4: 46195 | AF4: 46202 | AG4: 46209 | AH4: 46216 | AI4: 46223 | AJ4: 46230 | AK4: 46237 | AL4: 46244 | AM4: 46251 | AN4: 46258 | AO4: 46265 | AP4: 46272 | AQ4: 46279 | AR4: 46286 | AS4: 46293 | AT4: 46300 | AU4: 46307 | AV4: 46314 | AW4: 46321 | AX4: 46328 | AY4: 46335 | AZ4: 46342 | BA4: 46349 | BB4: 46356 | BC4: 46363 | BD4: 46370 | BE4: 46377 | BF4: 46384
A5: 1 | B5: {=IFERROR(INDEX(_xlfn.SORTBY(_xlfn._xlws.FILTER('Project Portfolio'!A$4:A$43,('Project Portfolio'!F$4:F$43<>"✅ COMPLETE")*('Project Portfolio'!F$4:F$43<>"🚫 NOT APPROVED")*('Project Portfolio'!F$4:F$43<>"⏸️ POSTPONED")*('Project Portfolio'!A$4:A$43<>"")),_xlfn._xlws.FILTER(IF('Project Portfolio'!J$4:J$43=0,99999,'Project Portfolio'!J$4:J$43),('Project Portfolio'!F$4:F$43<>"✅ COMPLETE")*('Project Portfolio'!F$4:F$43<>"🚫 NOT APPROVED")*('Project Portfolio'!F$4:F$43<>"⏸️ POSTPONED")*('Project Portfolio'!A$4:A$43<>"")),1),ROW()-4),"")} -> ETE-19 | C5: {=IFERROR(INDEX(_xlfn.SORTBY(_xlfn._xlws.FILTER('Project Portfolio'!B$4:B$43,('Project Portfolio'!F$4:F$43<>"✅ COMPLETE")*('Project Portfolio'!F$4:F$43<>"🚫 NOT APPROVED")*('Project Portfolio'!F$4:F$43<>"⏸️ POSTPONED")*('Project Portfolio'!A$4:A$43<>"")),_xlfn._xlws.FILTER(IF('Project Portfolio'!J$4:J$43=0,99999,'Project Portfolio'!J$4:J$43),('Project Portfolio'!F$4:F$43<>"✅ COMPLETE")*('Project Portfolio'!F$4:F$43<>"🚫 NOT APPROVED")*('Project Portfolio'!F$4:F$43<>"⏸️ POSTPONED")*('Project Portfolio'!A$4:A$43<>"")),1),ROW()-4),"")} -> Changes to AR Aging Report | D5: {=IFERROR(INDEX(_xlfn.SORTBY(_xlfn._xlws.FILTER('Project Portfolio'!F$4:F$43,('Project Portfolio'!F$4:F$43<>"✅ COMPLETE")*('Project Portfolio'!F$4:F$43<>"🚫 NOT APPROVED")*('Project Portfolio'!F$4:F$43<>"⏸️ POSTPONED")*('Project Portfolio'!A$4:A$43<>"")),_xlfn._xlws.FILTER(IF('Project Portfolio'!J$4:J$43=0,99999,'Project Portfolio'!J$4:J$43),('Project Portfolio'!F$4:F$43<>"✅ COMPLETE")*('Project Portfolio'!F$4:F$43<>"🚫 NOT APPROVED")*('Project Portfolio'!F$4:F$43<>"⏸️ POSTPONED")*('Project Portfolio'!A$4:A$43<>"")),1),ROW()-4),"")} -> 🟢 ON TRACK | E5: {=IFERROR(IF(INDEX(_xlfn.SORTBY(_xlfn._xlws.FILTER('Project Portfolio'!I$4:I$43,('Project Portfolio'!F$4:F$43<>"✅ COMPLETE")*('Project Portfolio'!F$4:F$43<>"🚫 NOT APPROVED")*('Project Portfolio'!F$4:F$43<>"⏸️ POSTPONED")*('Project Portfolio'!A$4:A$43<>"")),_xlfn._xlws.FILTER(IF('Project Portfolio'!J$4:J$43=0,99999,'Project Portfolio'!J$4:J$43),('Project Portfolio'!F$4:F$43<>"✅ COMPLETE")*('Project Portfolio'!F$4:F$43<>"🚫 NOT APPROVED")*('Project Portfolio'!F$4:F$43<>"⏸️ POSTPONED")*('Project Portfolio'!A$4:A$43<>"")),1),ROW()-4)=0,"",INDEX(_xlfn.SORTBY(_xlfn._xlws.FILTER('Project Portfolio'!I$4:I$43,('Project Portfolio'!F$4:F$43<>"✅ COMPLETE")*('Project Portfolio'!F$4:F$43<>"🚫 NOT APPROVED")*('Project Portfolio'!F$4:F$43<>"⏸️ POSTPONED")*('Project Portfolio'!A$4:A$43<>"")),_xlfn._xlws.FILTER(IF('Project Portfolio'!J$4:J$43=0,99999,'Project Portfolio'!J$4:J$43),('Project Portfolio'!F$4:F$43<>"✅ COMPLETE")*('Project Portfolio'!F$4:F$43<>"🚫 NOT APPROVED")*('Project Portfolio'!F$4:F$43<>"⏸️ POSTPONED")*('Project Portfolio'!A$4:A$43<>"")),1),ROW()-4)),"")} -> 46076 | F5: {=IFERROR(IF(INDEX(_xlfn.SORTBY(_xlfn._xlws.FILTER('Project Portfolio'!J$4:J$43,('Project Portfolio'!F$4:F$43<>"✅ COMPLETE")*('Project Portfolio'!F$4:F$43<>"🚫 NOT APPROVED")*('Project Portfolio'!F$4:F$43<>"⏸️ POSTPONED")*('Project Portfolio'!A$4:A$43<>"")),_xlfn._xlws.FILTER(IF('Project Portfolio'!J$4:J$43=0,99999,'Project Portfolio'!J$4:J$43),('Project Portfolio'!F$4:F$43<>"✅ COMPLETE")*('Project Portfolio'!F$4:F$43<>"🚫 NOT APPROVED")*('Project Portfolio'!F$4:F$43<>"⏸️ POSTPONED")*('Project Portfolio'!A$4:A$43<>"")),1),ROW()-4)=0,"",INDEX(_xlfn.SORTBY(_xlfn._xlws.FILTER('Project Portfolio'!J$4:J$43,('Project Portfolio'!F$4:F$43<>"✅ COMPLETE")*('Project Portfolio'!F$4:F$43<>"🚫 NOT APPROVED")*('Project Portfolio'!F$4:F$43<>"⏸️ POSTPONED")*('Project Portfolio'!A$4:A$43<>"")),_xlfn._xlws.FILTER(IF('Project Portfolio'!J$4:J$43=0,99999,'Project Portfolio'!J$4:J$43),('Project Portfolio'!F$4:F$43<>"✅ COMPLETE")*('Project Portfolio'!F$4:F$43<>"🚫 NOT APPROVED")*('Project Portfolio'!F$4:F$43<>"⏸️ POSTPONED")*('Project Portfolio'!A$4:A$43<>"")),1),ROW()-4)),"")} -> 46129 | G5: =IF(AND($E5>0,$F5>0,G$4+6>=$E5,G$4<=$F5),1,"") | H5: =IF(AND($E5>0,$F5>0,H$4+6>=$E5,H$4<=$F5),1,"") | I5: =IF(AND($E5>0,$F5>0,I$4+6>=$E5,I$4<=$F5),1,"") | J5: =IF(AND($E5>0,$F5>0,J$4+6>=$E5,J$4<=$F5),1,"") | K5: =IF(AND($E5>0,$F5>0,K$4+6>=$E5,K$4<=$F5),1,"") | L5: =IF(AND($E5>0,$F5>0,L$4+6>=$E5,L$4<=$F5),1,"") | M5: =IF(AND($E5>0,$F5>0,M$4+6>=$E5,M$4<=$F5),1,"") | N5: =IF(AND($E5>0,$F5>0,N$4+6>=$E5,N$4<=$F5),1,"") -> 1 | ... BF5: =IF(AND($E5>0,$F5>0,BF$4+6>=$E5,BF$4<=$F5),1,"")
A6: 2 | B6: {=IFERROR(INDEX(_xlfn.SORTBY(_xlfn._xlws.FILTER('Project Portfolio'!A$4:A$43,('Project Portfolio'!F$4:F$43<>"✅ COMPLETE")*('Project Portfolio'!F$4:F$43<>"🚫 NOT APPROVED")*('Project Portfolio'!F$4:F$43<>"⏸️ POSTPONED")*('Project Portfolio'!A$4:A$43<>"")),_xlfn._xlws.FILTER(IF('Project Portfolio'!J$4:J$43=0,99999,'Project Portfolio'!J$4:J$43),('Project Portfolio'!F$4:F$43<>"✅ COMPLETE")*('Project Portfolio'!F$4:F$43<>"🚫 NOT APPROVED")*('Project Portfolio'!F$4:F$43<>"⏸️ POSTPONED")*('Project Portfolio'!A$4:A$43<>"")),1),ROW()-4),"")} -> ETE-68 | C6: {=IFERROR(INDEX(_xlfn.SORTBY(_xlfn._xlws.FILTER('Project Portfolio'!B$4:B$43,('Project Portfolio'!F$4:F$43<>"✅ COMPLETE")*('Project Portfolio'!F$4:F$43<>"🚫 NOT APPROVED")*('Project Portfolio'!F$4:F$43<>"⏸️ POSTPONED")*('Project Portfolio'!A$4:A$43<>"")),_xlfn._xlws.FILTER(IF('Project Portfolio'!J$4:J$43=0,99999,'Project Portfolio'!J$4:J$43),('Project Portfolio'!F$4:F$43<>"✅ COMPLETE")*('Project Portfolio'!F$4:F$43<>"🚫 NOT APPROVED")*('Project Portfolio'!F$4:F$43<>"⏸️ POSTPONED")*('Project Portfolio'!A$4:A$43<>"")),1),ROW()-4),"")} -> Catalog API Rust2Python | D6: {=IFERROR(INDEX(_xlfn.SORTBY(_xlfn._xlws.FILTER('Project Portfolio'!F$4:F$43,('Project Portfolio'!F$4:F$43<>"✅ COMPLETE")*('Project Portfolio'!F$4:F$43<>"🚫 NOT APPROVED")*('Project Portfolio'!F$4:F$43<>"⏸️ POSTPONED")*('Project Portfolio'!A$4:A$43<>"")),_xlfn._xlws.FILTER(IF('Project Portfolio'!J$4:J$43=0,99999,'Project Portfolio'!J$4:J$43),('Project Portfolio'!F$4:F$43<>"✅ COMPLETE")*('Project Portfolio'!F$4:F$43<>"🚫 NOT APPROVED")*('Project Portfolio'!F$4:F$43<>"⏸️ POSTPONED")*('Project Portfolio'!A$4:A$43<>"")),1),ROW()-4),"")} -> 🟢 ON TRACK | E6: {=IFERROR(IF(INDEX(_xlfn.SORTBY(_xlfn._xlws.FILTER('Project Portfolio'!I$4:I$43,('Project Portfolio'!F$4:F$43<>"✅ COMPLETE")*('Project Portfolio'!F$4:F$43<>"🚫 NOT APPROVED")*('Project Portfolio'!F$4:F$43<>"⏸️ POSTPONED")*('Project Portfolio'!A$4:A$43<>"")),_xlfn._xlws.FILTER(IF('Project Portfolio'!J$4:J$43=0,99999,'Project Portfolio'!J$4:J$43),('Project Portfolio'!F$4:F$43<>"✅ COMPLETE")*('Project Portfolio'!F$4:F$43<>"🚫 NOT APPROVED")*('Project Portfolio'!F$4:F$43<>"⏸️ POSTPONED")*('Project Portfolio'!A$4:A$43<>"")),1),ROW()-4)=0,"",INDEX(_xlfn.SORTBY(_xlfn._xlws.FILTER('Project Portfolio'!I$4:I$43,('Project Portfolio'!F$4:F$43<>"✅ COMPLETE")*('Project Portfolio'!F$4:F$43<>"🚫 NOT APPROVED")*('Project Portfolio'!F$4:F$43<>"⏸️ POSTPONED")*('Project Portfolio'!A$4:A$43<>"")),_xlfn._xlws.FILTER(IF('Project Portfolio'!J$4:J$43=0,99999,'Project Portfolio'!J$4:J$43),('Project Portfolio'!F$4:F$43<>"✅ COMPLETE")*('Project Portfolio'!F$4:F$43<>"🚫 NOT APPROVED")*('Project Portfolio'!F$4:F$43<>"⏸️ POSTPONED")*('Project Portfolio'!A$4:A$43<>"")),1),ROW()-4)),"")} -> 45978 | F6: {=IFERROR(IF(INDEX(_xlfn.SORTBY(_xlfn._xlws.FILTER('Project Portfolio'!J$4:J$43,('Project Portfolio'!F$4:F$43<>"✅ COMPLETE")*('Project Portfolio'!F$4:F$43<>"🚫 NOT APPROVED")*('Project Portfolio'!F$4:F$43<>"⏸️ POSTPONED")*('Project Portfolio'!A$4:A$43<>"")),_xlfn._xlws.FILTER(IF('Project Portfolio'!J$4:J$43=0,99999,'Project Portfolio'!J$4:J$43),('Project Portfolio'!F$4:F$43<>"✅ COMPLETE")*('Project Portfolio'!F$4:F$43<>"🚫 NOT APPROVED")*('Project Portfolio'!F$4:F$43<>"⏸️ POSTPONED")*('Project Portfolio'!A$4:A$43<>"")),1),ROW()-4)=0,"",INDEX(_xlfn.SORTBY(_xlfn._xlws.FILTER('Project Portfolio'!J$4:J$43,('Project Portfolio'!F$4:F$43<>"✅ COMPLETE")*('Project Portfolio'!F$4:F$43<>"🚫 NOT APPROVED")*('Project Portfolio'!F$4:F$43<>"⏸️ POSTPONED")*('Project Portfolio'!A$4:A$43<>"")),_xlfn._xlws.FILTER(IF('Project Portfolio'!J$4:J$43=0,99999,'Project Portfolio'!J$4:J$43),('Project Portfolio'!F$4:F$43<>"✅ COMPLETE")*('Project Portfolio'!F$4:F$43<>"🚫 NOT APPROVED")*('Project Portfolio'!F$4:F$43<>"⏸️ POSTPONED")*('Project Portfolio'!A$4:A$43<>"")),1),ROW()-4)),"")} -> 46136 | G6: =IF(AND($E6>0,$F6>0,G$4+6>=$E6,G$4<=$F6),1,"") -> 1 | H6: =IF(AND($E6>0,$F6>0,H$4+6>=$E6,H$4<=$F6),1,"") -> 1 | I6: =IF(AND($E6>0,$F6>0,I$4+6>=$E6,I$4<=$F6),1,"") -> 1 | J6: =IF(AND($E6>0,$F6>0,J$4+6>=$E6,J$4<=$F6),1,"") -> 1 | K6: =IF(AND($E6>0,$F6>0,K$4+6>=$E6,K$4<=$F6),1,"") -> 1 | L6: =IF(AND($E6>0,$F6>0,L$4+6>=$E6,L$4<=$F6),1,"") -> 1 | M6: =IF(AND($E6>0,$F6>0,M$4+6>=$E6,M$4<=$F6),1,"") -> 1 | N6: =IF(AND($E6>0,$F6>0,N$4+6>=$E6,N$4<=$F6),1,"") -> 1 | ... BF6: =IF(AND($E6>0,$F6>0,BF$4+6>=$E6,BF$4<=$F6),1,"")
A7: 3 | B7: {=IFERROR(INDEX(_xlfn.SORTBY(_xlfn._xlws.FILTER('Project Portfolio'!A$4:A$43,('Project Portfolio'!F$4:F$43<>"✅ COMPLETE")*('Project Portfolio'!F$4:F$43<>"🚫 NOT APPROVED")*('Project Portfolio'!F$4:F$43<>"⏸️ POSTPONED")*('Project Portfolio'!A$4:A$43<>"")),_xlfn._xlws.FILTER(IF('Project Portfolio'!J$4:J$43=0,99999,'Project Portfolio'!J$4:J$43),('Project Portfolio'!F$4:F$43<>"✅ COMPLETE")*('Project Portfolio'!F$4:F$43<>"🚫 NOT APPROVED")*('Project Portfolio'!F$4:F$43<>"⏸️ POSTPONED")*('Project Portfolio'!A$4:A$43<>"")),1),ROW()-4),"")} -> ETE-83 | C7: {=IFERROR(INDEX(_xlfn.SORTBY(_xlfn._xlws.FILTER('Project Portfolio'!B$4:B$43,('Project Portfolio'!F$4:F$43<>"✅ COMPLETE")*('Project Portfolio'!F$4:F$43<>"🚫 NOT APPROVED")*('Project Portfolio'!F$4:F$43<>"⏸️ POSTPONED")*('Project Portfolio'!A$4:A$43<>"")),_xlfn._xlws.FILTER(IF('Project Portfolio'!J$4:J$43=0,99999,'Project Portfolio'!J$4:J$43),('Project Portfolio'!F$4:F$43<>"✅ COMPLETE")*('Project Portfolio'!F$4:F$43<>"🚫 NOT APPROVED")*('Project Portfolio'!F$4:F$43<>"⏸️ POSTPONED")*('Project Portfolio'!A$4:A$43<>"")),1),ROW()-4),"")} -> Customer Master Data Cleanup | D7: {=IFERROR(INDEX(_xlfn.SORTBY(_xlfn._xlws.FILTER('Project Portfolio'!F$4:F$43,('Project Portfolio'!F$4:F$43<>"✅ COMPLETE")*('Project Portfolio'!F$4:F$43<>"🚫 NOT APPROVED")*('Project Portfolio'!F$4:F$43<>"⏸️ POSTPONED")*('Project Portfolio'!A$4:A$43<>"")),_xlfn._xlws.FILTER(IF('Project Portfolio'!J$4:J$43=0,99999,'Project Portfolio'!J$4:J$43),('Project Portfolio'!F$4:F$43<>"✅ COMPLETE")*('Project Portfolio'!F$4:F$43<>"🚫 NOT APPROVED")*('Project Portfolio'!F$4:F$43<>"⏸️ POSTPONED")*('Project Portfolio'!A$4:A$43<>"")),1),ROW()-4),"")} -> 📋 NEEDS TECHNICAL SPEC | E7: {=IFERROR(IF(INDEX(_xlfn.SORTBY(_xlfn._xlws.FILTER('Project Portfolio'!I$4:I$43,('Project Portfolio'!F$4:F$43<>"✅ COMPLETE")*('Project Portfolio'!F$4:F$43<>"🚫 NOT APPROVED")*('Project Portfolio'!F$4:F$43<>"⏸️ POSTPONED")*('Project Portfolio'!A$4:A$43<>"")),_xlfn._xlws.FILTER(IF('Project Portfolio'!J$4:J$43=0,99999,'Project Portfolio'!J$4:J$43),('Project Portfolio'!F$4:F$43<>"✅ COMPLETE")*('Project Portfolio'!F$4:F$43<>"🚫 NOT APPROVED")*('Project Portfolio'!F$4:F$43<>"⏸️ POSTPONED")*('Project Portfolio'!A$4:A$43<>"")),1),ROW()-4)=0,"",INDEX(_xlfn.SORTBY(_xlfn._xlws.FILTER('Project Portfolio'!I$4:I$43,('Project Portfolio'!F$4:F$43<>"✅ COMPLETE")*('Project Portfolio'!F$4:F$43<>"🚫 NOT APPROVED")*('Project Portfolio'!F$4:F$43<>"⏸️ POSTPONED")*('Project Portfolio'!A$4:A$43<>"")),_xlfn._xlws.FILTER(IF('Project Portfolio'!J$4:J$43=0,99999,'Project Portfolio'!J$4:J$43),('Project Portfolio'!F$4:F$43<>"✅ COMPLETE")*('Project Portfolio'!F$4:F$43<>"🚫 NOT APPROVED")*('Project Portfolio'!F$4:F$43<>"⏸️ POSTPONED")*('Project Portfolio'!A$4:A$43<>"")),1),ROW()-4)),"")} -> 45944 | F7: {=IFERROR(IF(INDEX(_xlfn.SORTBY(_xlfn._xlws.FILTER('Project Portfolio'!J$4:J$43,('Project Portfolio'!F$4:F$43<>"✅ COMPLETE")*('Project Portfolio'!F$4:F$43<>"🚫 NOT APPROVED")*('Project Portfolio'!F$4:F$43<>"⏸️ POSTPONED")*('Project Portfolio'!A$4:A$43<>"")),_xlfn._xlws.FILTER(IF('Project Portfolio'!J$4:J$43=0,99999,'Project Portfolio'!J$4:J$43),('Project Portfolio'!F$4:F$43<>"✅ COMPLETE")*('Project Portfolio'!F$4:F$43<>"🚫 NOT APPROVED")*('Project Portfolio'!F$4:F$43<>"⏸️ POSTPONED")*('Project Portfolio'!A$4:A$43<>"")),1),ROW()-4)=0,"",INDEX(_xlfn.SORTBY(_xlfn._xlws.FILTER('Project Portfolio'!J$4:J$43,('Project Portfolio'!F$4:F$43<>"✅ COMPLETE")*('Project Portfolio'!F$4:F$43<>"🚫 NOT APPROVED")*('Project Portfolio'!F$4:F$43<>"⏸️ POSTPONED")*('Project Portfolio'!A$4:A$43<>"")),_xlfn._xlws.FILTER(IF('Project Portfolio'!J$4:J$43=0,99999,'Project Portfolio'!J$4:J$43),('Project Portfolio'!F$4:F$43<>"✅ COMPLETE")*('Project Portfolio'!F$4:F$43<>"🚫 NOT APPROVED")*('Project Portfolio'!F$4:F$43<>"⏸️ POSTPONED")*('Project Portfolio'!A$4:A$43<>"")),1),ROW()-4)),"")} -> 46174 | G7: =IF(AND($E7>0,$F7>0,G$4+6>=$E7,G$4<=$F7),1,"") -> 1 | H7: =IF(AND($E7>0,$F7>0,H$4+6>=$E7,H$4<=$F7),1,"") -> 1 | I7: =IF(AND($E7>0,$F7>0,I$4+6>=$E7,I$4<=$F7),1,"") -> 1 | J7: =IF(AND($E7>0,$F7>0,J$4+6>=$E7,J$4<=$F7),1,"") -> 1 | K7: =IF(AND($E7>0,$F7>0,K$4+6>=$E7,K$4<=$F7),1,"") -> 1 | L7: =IF(AND($E7>0,$F7>0,L$4+6>=$E7,L$4<=$F7),1,"") -> 1 | M7: =IF(AND($E7>0,$F7>0,M$4+6>=$E7,M$4<=$F7),1,"") -> 1 | N7: =IF(AND($E7>0,$F7>0,N$4+6>=$E7,N$4<=$F7),1,"") -> 1 | ... BF7: =IF(AND($E7>0,$F7>0,BF$4+6>=$E7,BF$4<=$F7),1,"")
A8: 4 | B8: {=IFERROR(INDEX(_xlfn.SORTBY(_xlfn._xlws.FILTER('Project Portfolio'!A$4:A$43,('Project Portfolio'!F$4:F$43<>"✅ COMPLETE")*('Project Portfolio'!F$4:F$43<>"🚫 NOT APPROVED")*('Project Portfolio'!F$4:F$43<>"⏸️ POSTPONED")*('Project Portfolio'!A$4:A$43<>"")),_xlfn._xlws.FILTER(IF('Project Portfolio'!J$4:J$43=0,99999,'Project Portfolio'!J$4:J$43),('Project Portfolio'!F$4:F$43<>"✅ COMPLETE")*('Project Portfolio'!F$4:F$43<>"🚫 NOT APPROVED")*('Project Portfolio'!F$4:F$43<>"⏸️ POSTPONED")*('Project Portfolio'!A$4:A$43<>"")),1),ROW()-4),"")} -> ETE-48 | C8: {=IFERROR(INDEX(_xlfn.SORTBY(_xlfn._xlws.FILTER('Project Portfolio'!B$4:B$43,('Project Portfolio'!F$4:F$43<>"✅ COMPLETE")*('Project Portfolio'!F$4:F$43<>"🚫 NOT APPROVED")*('Project Portfolio'!F$4:F$43<>"⏸️ POSTPONED")*('Project Portfolio'!A$4:A$43<>"")),_xlfn._xlws.FILTER(IF('Project Portfolio'!J$4:J$43=0,99999,'Project Portfolio'!J$4:J$43),('Project Portfolio'!F$4:F$43<>"✅ COMPLETE")*('Project Portfolio'!F$4:F$43<>"🚫 NOT APPROVED")*('Project Portfolio'!F$4:F$43<>"⏸️ POSTPONED")*('Project Portfolio'!A$4:A$43<>"")),1),ROW()-4),"")} -> System Connection Syteline-VKS | D8: {=IFERROR(INDEX(_xlfn.SORTBY(_xlfn._xlws.FILTER('Project Portfolio'!F$4:F$43,('Project Portfolio'!F$4:F$43<>"✅ COMPLETE")*('Project Portfolio'!F$4:F$43<>"🚫 NOT APPROVED")*('Project Portfolio'!F$4:F$43<>"⏸️ POSTPONED")*('Project Portfolio'!A$4:A$43<>"")),_xlfn._xlws.FILTER(IF('Project Portfolio'!J$4:J$43=0,99999,'Project Portfolio'!J$4:J$43),('Project Portfolio'!F$4:F$43<>"✅ COMPLETE")*('Project Portfolio'!F$4:F$43<>"🚫 NOT APPROVED")*('Project Portfolio'!F$4:F$43<>"⏸️ POSTPONED")*('Project Portfolio'!A$4:A$43<>"")),1),ROW()-4),"")} -> 🟢 ON TRACK | E8: {=IFERROR(IF(INDEX(_xlfn.SORTBY(_xlfn._xlws.FILTER('Project Portfolio'!I$4:I$43,('Project Portfolio'!F$4:F$43<>"✅ COMPLETE")*('Project Portfolio'!F$4:F$43<>"🚫 NOT APPROVED")*('Project Portfolio'!F$4:F$43<>"⏸️ POSTPONED")*('Project Portfolio'!A$4:A$43<>"")),_xlfn._xlws.FILTER(IF('Project Portfolio'!J$4:J$43=0,99999,'Project Portfolio'!J$4:J$43),('Project Portfolio'!F$4:F$43<>"✅ COMPLETE")*('Project Portfolio'!F$4:F$43<>"🚫 NOT APPROVED")*('Project Portfolio'!F$4:F$43<>"⏸️ POSTPONED")*('Project Portfolio'!A$4:A$43<>"")),1),ROW()-4)=0,"",INDEX(_xlfn.SORTBY(_xlfn._xlws.FILTER('Project Portfolio'!I$4:I$43,('Project Portfolio'!F$4:F$43<>"✅ COMPLETE")*('Project Portfolio'!F$4:F$43<>"🚫 NOT APPROVED")*('Project Portfolio'!F$4:F$43<>"⏸️ POSTPONED")*('Project Portfolio'!A$4:A$43<>"")),_xlfn._xlws.FILTER(IF('Project Portfolio'!J$4:J$43=0,99999,'Project Portfolio'!J$4:J$43),('Project Portfolio'!F$4:F$43<>"✅ COMPLETE")*('Project Portfolio'!F$4:F$43<>"🚫 NOT APPROVED")*('Project Portfolio'!F$4:F$43<>"⏸️ POSTPONED")*('Project Portfolio'!A$4:A$43<>"")),1),ROW()-4)),"")} -> 46068 | F8: {=IFERROR(IF(INDEX(_xlfn.SORTBY(_xlfn._xlws.FILTER('Project Portfolio'!J$4:J$43,('Project Portfolio'!F$4:F$43<>"✅ COMPLETE")*('Project Portfolio'!F$4:F$43<>"🚫 NOT APPROVED")*('Project Portfolio'!F$4:F$43<>"⏸️ POSTPONED")*('Project Portfolio'!A$4:A$43<>"")),_xlfn._xlws.FILTER(IF('Project Portfolio'!J$4:J$43=0,99999,'Project Portfolio'!J$4:J$43),('Project Portfolio'!F$4:F$43<>"✅ COMPLETE")*('Project Portfolio'!F$4:F$43<>"🚫 NOT APPROVED")*('Project Portfolio'!F$4:F$43<>"⏸️ POSTPONED")*('Project Portfolio'!A$4:A$43<>"")),1),ROW()-4)=0,"",INDEX(_xlfn.SORTBY(_xlfn._xlws.FILTER('Project Portfolio'!J$4:J$43,('Project Portfolio'!F$4:F$43<>"✅ COMPLETE")*('Project Portfolio'!F$4:F$43<>"🚫 NOT APPROVED")*('Project Portfolio'!F$4:F$43<>"⏸️ POSTPONED")*('Project Portfolio'!A$4:A$43<>"")),_xlfn._xlws.FILTER(IF('Project Portfolio'!J$4:J$43=0,99999,'Project Portfolio'!J$4:J$43),('Project Portfolio'!F$4:F$43<>"✅ COMPLETE")*('Project Portfolio'!F$4:F$43<>"🚫 NOT APPROVED")*('Project Portfolio'!F$4:F$43<>"⏸️ POSTPONED")*('Project Portfolio'!A$4:A$43<>"")),1),ROW()-4)),"")} -> 46203 | G8: =IF(AND($E8>0,$F8>0,G$4+6>=$E8,G$4<=$F8),1,"") | H8: =IF(AND($E8>0,$F8>0,H$4+6>=$E8,H$4<=$F8),1,"") | I8: =IF(AND($E8>0,$F8>0,I$4+6>=$E8,I$4<=$F8),1,"") | J8: =IF(AND($E8>0,$F8>0,J$4+6>=$E8,J$4<=$F8),1,"") | K8: =IF(AND($E8>0,$F8>0,K$4+6>=$E8,K$4<=$F8),1,"") | L8: =IF(AND($E8>0,$F8>0,L$4+6>=$E8,L$4<=$F8),1,"") -> 1 | M8: =IF(AND($E8>0,$F8>0,M$4+6>=$E8,M$4<=$F8),1,"") -> 1 | N8: =IF(AND($E8>0,$F8>0,N$4+6>=$E8,N$4<=$F8),1,"") -> 1 | ... BF8: =IF(AND($E8>0,$F8>0,BF$4+6>=$E8,BF$4<=$F8),1,"")
A9: 5 | B9: {=IFERROR(INDEX(_xlfn.SORTBY(_xlfn._xlws.FILTER('Project Portfolio'!A$4:A$43,('Project Portfolio'!F$4:F$43<>"✅ COMPLETE")*('Project Portfolio'!F$4:F$43<>"🚫 NOT APPROVED")*('Project Portfolio'!F$4:F$43<>"⏸️ POSTPONED")*('Project Portfolio'!A$4:A$43<>"")),_xlfn._xlws.FILTER(IF('Project Portfolio'!J$4:J$43=0,99999,'Project Portfolio'!J$4:J$43),('Project Portfolio'!F$4:F$43<>"✅ COMPLETE")*('Project Portfolio'!F$4:F$43<>"🚫 NOT APPROVED")*('Project Portfolio'!F$4:F$43<>"⏸️ POSTPONED")*('Project Portfolio'!A$4:A$43<>"")),1),ROW()-4),"")} -> ETE-43 | C9: {=IFERROR(INDEX(_xlfn.SORTBY(_xlfn._xlws.FILTER('Project Portfolio'!B$4:B$43,('Project Portfolio'!F$4:F$43<>"✅ COMPLETE")*('Project Portfolio'!F$4:F$43<>"🚫 NOT APPROVED")*('Project Portfolio'!F$4:F$43<>"⏸️ POSTPONED")*('Project Portfolio'!A$4:A$43<>"")),_xlfn._xlws.FILTER(IF('Project Portfolio'!J$4:J$43=0,99999,'Project Portfolio'!J$4:J$43),('Project Portfolio'!F$4:F$43<>"✅ COMPLETE")*('Project Portfolio'!F$4:F$43<>"🚫 NOT APPROVED")*('Project Portfolio'!F$4:F$43<>"⏸️ POSTPONED")*('Project Portfolio'!A$4:A$43<>"")),1),ROW()-4),"")} -> Data Security - Microsoft Purview | D9: {=IFERROR(INDEX(_xlfn.SORTBY(_xlfn._xlws.FILTER('Project Portfolio'!F$4:F$43,('Project Portfolio'!F$4:F$43<>"✅ COMPLETE")*('Project Portfolio'!F$4:F$43<>"🚫 NOT APPROVED")*('Project Portfolio'!F$4:F$43<>"⏸️ POSTPONED")*('Project Portfolio'!A$4:A$43<>"")),_xlfn._xlws.FILTER(IF('Project Portfolio'!J$4:J$43=0,99999,'Project Portfolio'!J$4:J$43),('Project Portfolio'!F$4:F$43<>"✅ COMPLETE")*('Project Portfolio'!F$4:F$43<>"🚫 NOT APPROVED")*('Project Portfolio'!F$4:F$43<>"⏸️ POSTPONED")*('Project Portfolio'!A$4:A$43<>"")),1),ROW()-4),"")} -> 🟢 ON TRACK | E9: {=IFERROR(IF(INDEX(_xlfn.SORTBY(_xlfn._xlws.FILTER('Project Portfolio'!I$4:I$43,('Project Portfolio'!F$4:F$43<>"✅ COMPLETE")*('Project Portfolio'!F$4:F$43<>"🚫 NOT APPROVED")*('Project Portfolio'!F$4:F$43<>"⏸️ POSTPONED")*('Project Portfolio'!A$4:A$43<>"")),_xlfn._xlws.FILTER(IF('Project Portfolio'!J$4:J$43=0,99999,'Project Portfolio'!J$4:J$43),('Project Portfolio'!F$4:F$43<>"✅ COMPLETE")*('Project Portfolio'!F$4:F$43<>"🚫 NOT APPROVED")*('Project Portfolio'!F$4:F$43<>"⏸️ POSTPONED")*('Project Portfolio'!A$4:A$43<>"")),1),ROW()-4)=0,"",INDEX(_xlfn.SORTBY(_xlfn._xlws.FILTER('Project Portfolio'!I$4:I$43,('Project Portfolio'!F$4:F$43<>"✅ COMPLETE")*('Project Portfolio'!F$4:F$43<>"🚫 NOT APPROVED")*('Project Portfolio'!F$4:F$43<>"⏸️ POSTPONED")*('Project Portfolio'!A$4:A$43<>"")),_xlfn._xlws.FILTER(IF('Project Portfolio'!J$4:J$43=0,99999,'Project Portfolio'!J$4:J$43),('Project Portfolio'!F$4:F$43<>"✅ COMPLETE")*('Project Portfolio'!F$4:F$43<>"🚫 NOT APPROVED")*('Project Portfolio'!F$4:F$43<>"⏸️ POSTPONED")*('Project Portfolio'!A$4:A$43<>"")),1),ROW()-4)),"")} -> 46055 | F9: {=IFERROR(IF(INDEX(_xlfn.SORTBY(_xlfn._xlws.FILTER('Project Portfolio'!J$4:J$43,('Project Portfolio'!F$4:F$43<>"✅ COMPLETE")*('Project Portfolio'!F$4:F$43<>"🚫 NOT APPROVED")*('Project Portfolio'!F$4:F$43<>"⏸️ POSTPONED")*('Project Portfolio'!A$4:A$43<>"")),_xlfn._xlws.FILTER(IF('Project Portfolio'!J$4:J$43=0,99999,'Project Portfolio'!J$4:J$43),('Project Portfolio'!F$4:F$43<>"✅ COMPLETE")*('Project Portfolio'!F$4:F$43<>"🚫 NOT APPROVED")*('Project Portfolio'!F$4:F$43<>"⏸️ POSTPONED")*('Project Portfolio'!A$4:A$43<>"")),1),ROW()-4)=0,"",INDEX(_xlfn.SORTBY(_xlfn._xlws.FILTER('Project Portfolio'!J$4:J$43,('Project Portfolio'!F$4:F$43<>"✅ COMPLETE")*('Project Portfolio'!F$4:F$43<>"🚫 NOT APPROVED")*('Project Portfolio'!F$4:F$43<>"⏸️ POSTPONED")*('Project Portfolio'!A$4:A$43<>"")),_xlfn._xlws.FILTER(IF('Project Portfolio'!J$4:J$43=0,99999,'Project Portfolio'!J$4:J$43),('Project Portfolio'!F$4:F$43<>"✅ COMPLETE")*('Project Portfolio'!F$4:F$43<>"🚫 NOT APPROVED")*('Project Portfolio'!F$4:F$43<>"⏸️ POSTPONED")*('Project Portfolio'!A$4:A$43<>"")),1),ROW()-4)),"")} -> 46203 | G9: =IF(AND($E9>0,$F9>0,G$4+6>=$E9,G$4<=$F9),1,"") | H9: =IF(AND($E9>0,$F9>0,H$4+6>=$E9,H$4<=$F9),1,"") | I9: =IF(AND($E9>0,$F9>0,I$4+6>=$E9,I$4<=$F9),1,"") | J9: =IF(AND($E9>0,$F9>0,J$4+6>=$E9,J$4<=$F9),1,"") | K9: =IF(AND($E9>0,$F9>0,K$4+6>=$E9,K$4<=$F9),1,"") -> 1 | L9: =IF(AND($E9>0,$F9>0,L$4+6>=$E9,L$4<=$F9),1,"") -> 1 | M9: =IF(AND($E9>0,$F9>0,M$4+6>=$E9,M$4<=$F9),1,"") -> 1 | N9: =IF(AND($E9>0,$F9>0,N$4+6>=$E9,N$4<=$F9),1,"") -> 1 | ... BF9: =IF(AND($E9>0,$F9>0,BF$4+6>=$E9,BF$4<=$F9),1,"")
A10: 6 | B10: {=IFERROR(INDEX(_xlfn.SORTBY(_xlfn._xlws.FILTER('Project Portfolio'!A$4:A$43,('Project Portfolio'!F$4:F$43<>"✅ COMPLETE")*('Project Portfolio'!F$4:F$43<>"🚫 NOT APPROVED")*('Project Portfolio'!F$4:F$43<>"⏸️ POSTPONED")*('Project Portfolio'!A$4:A$43<>"")),_xlfn._xlws.FILTER(IF('Project Portfolio'!J$4:J$43=0,99999,'Project Portfolio'!J$4:J$43),('Project Portfolio'!F$4:F$43<>"✅ COMPLETE")*('Project Portfolio'!F$4:F$43<>"🚫 NOT APPROVED")*('Project Portfolio'!F$4:F$43<>"⏸️ POSTPONED")*('Project Portfolio'!A$4:A$43<>"")),1),ROW()-4),"")} -> ETE-49 | C10: {=IFERROR(INDEX(_xlfn.SORTBY(_xlfn._xlws.FILTER('Project Portfolio'!B$4:B$43,('Project Portfolio'!F$4:F$43<>"✅ COMPLETE")*('Project Portfolio'!F$4:F$43<>"🚫 NOT APPROVED")*('Project Portfolio'!F$4:F$43<>"⏸️ POSTPONED")*('Project Portfolio'!A$4:A$43<>"")),_xlfn._xlws.FILTER(IF('Project Portfolio'!J$4:J$43=0,99999,'Project Portfolio'!J$4:J$43),('Project Portfolio'!F$4:F$43<>"✅ COMPLETE")*('Project Portfolio'!F$4:F$43<>"🚫 NOT APPROVED")*('Project Portfolio'!F$4:F$43<>"⏸️ POSTPONED")*('Project Portfolio'!A$4:A$43<>"")),1),ROW()-4),"")} -> Marketing: STE Rewards Tier | D10: {=IFERROR(INDEX(_xlfn.SORTBY(_xlfn._xlws.FILTER('Project Portfolio'!F$4:F$43,('Project Portfolio'!F$4:F$43<>"✅ COMPLETE")*('Project Portfolio'!F$4:F$43<>"🚫 NOT APPROVED")*('Project Portfolio'!F$4:F$43<>"⏸️ POSTPONED")*('Project Portfolio'!A$4:A$43<>"")),_xlfn._xlws.FILTER(IF('Project Portfolio'!J$4:J$43=0,99999,'Project Portfolio'!J$4:J$43),('Project Portfolio'!F$4:F$43<>"✅ COMPLETE")*('Project Portfolio'!F$4:F$43<>"🚫 NOT APPROVED")*('Project Portfolio'!F$4:F$43<>"⏸️ POSTPONED")*('Project Portfolio'!A$4:A$43<>"")),1),ROW()-4),"")} -> 📋 NEEDS TECHNICAL SPEC | E10: {=IFERROR(IF(INDEX(_xlfn.SORTBY(_xlfn._xlws.FILTER('Project Portfolio'!I$4:I$43,('Project Portfolio'!F$4:F$43<>"✅ COMPLETE")*('Project Portfolio'!F$4:F$43<>"🚫 NOT APPROVED")*('Project Portfolio'!F$4:F$43<>"⏸️ POSTPONED")*('Project Portfolio'!A$4:A$43<>"")),_xlfn._xlws.FILTER(IF('Project Portfolio'!J$4:J$43=0,99999,'Project Portfolio'!J$4:J$43),('Project Portfolio'!F$4:F$43<>"✅ COMPLETE")*('Project Portfolio'!F$4:F$43<>"🚫 NOT APPROVED")*('Project Portfolio'!F$4:F$43<>"⏸️ POSTPONED")*('Project Portfolio'!A$4:A$43<>"")),1),ROW()-4)=0,"",INDEX(_xlfn.SORTBY(_xlfn._xlws.FILTER('Project Portfolio'!I$4:I$43,('Project Portfolio'!F$4:F$43<>"✅ COMPLETE")*('Project Portfolio'!F$4:F$43<>"🚫 NOT APPROVED")*('Project Portfolio'!F$4:F$43<>"⏸️ POSTPONED")*('Project Portfolio'!A$4:A$43<>"")),_xlfn._xlws.FILTER(IF('Project Portfolio'!J$4:J$43=0,99999,'Project Portfolio'!J$4:J$43),('Project Portfolio'!F$4:F$43<>"✅ COMPLETE")*('Project Portfolio'!F$4:F$43<>"🚫 NOT APPROVED")*('Project Portfolio'!F$4:F$43<>"⏸️ POSTPONED")*('Project Portfolio'!A$4:A$43<>"")),1),ROW()-4)),"")} | F10: {=IFERROR(IF(INDEX(_xlfn.SORTBY(_xlfn._xlws.FILTER('Project Portfolio'!J$4:J$43,('Project Portfolio'!F$4:F$43<>"✅ COMPLETE")*('Project Portfolio'!F$4:F$43<>"🚫 NOT APPROVED")*('Project Portfolio'!F$4:F$43<>"⏸️ POSTPONED")*('Project Portfolio'!A$4:A$43<>"")),_xlfn._xlws.FILTER(IF('Project Portfolio'!J$4:J$43=0,99999,'Project Portfolio'!J$4:J$43),('Project Portfolio'!F$4:F$43<>"✅ COMPLETE")*('Project Portfolio'!F$4:F$43<>"🚫 NOT APPROVED")*('Project Portfolio'!F$4:F$43<>"⏸️ POSTPONED")*('Project Portfolio'!A$4:A$43<>"")),1),ROW()-4)=0,"",INDEX(_xlfn.SORTBY(_xlfn._xlws.FILTER('Project Portfolio'!J$4:J$43,('Project Portfolio'!F$4:F$43<>"✅ COMPLETE")*('Project Portfolio'!F$4:F$43<>"🚫 NOT APPROVED")*('Project Portfolio'!F$4:F$43<>"⏸️ POSTPONED")*('Project Portfolio'!A$4:A$43<>"")),_xlfn._xlws.FILTER(IF('Project Portfolio'!J$4:J$43=0,99999,'Project Portfolio'!J$4:J$43),('Project Portfolio'!F$4:F$43<>"✅ COMPLETE")*('Project Portfolio'!F$4:F$43<>"🚫 NOT APPROVED")*('Project Portfolio'!F$4:F$43<>"⏸️ POSTPONED")*('Project Portfolio'!A$4:A$43<>"")),1),ROW()-4)),"")} | G10: =IF(AND($E10>0,$F10>0,G$4+6>=$E10,G$4<=$F10),1,"") | H10: =IF(AND($E10>0,$F10>0,H$4+6>=$E10,H$4<=$F10),1,"") | I10: =IF(AND($E10>0,$F10>0,I$4+6>=$E10,I$4<=$F10),1,"") | J10: =IF(AND($E10>0,$F10>0,J$4+6>=$E10,J$4<=$F10),1,"") | K10: =IF(AND($E10>0,$F10>0,K$4+6>=$E10,K$4<=$F10),1,"") | L10: =IF(AND($E10>0,$F10>0,L$4+6>=$E10,L$4<=$F10),1,"") | M10: =IF(AND($E10>0,$F10>0,M$4+6>=$E10,M$4<=$F10),1,"") | N10: =IF(AND($E10>0,$F10>0,N$4+6>=$E10,N$4<=$F10),1,"") | ... BF10: =IF(AND($E10>0,$F10>0,BF$4+6>=$E10,BF$4<=$F10),1,"")
A11: 7 | B11: {=IFERROR(INDEX(_xlfn.SORTBY(_xlfn._xlws.FILTER('Project Portfolio'!A$4:A$43,('Project Portfolio'!F$4:F$43<>"✅ COMPLETE")*('Project Portfolio'!F$4:F$43<>"🚫 NOT APPROVED")*('Project Portfolio'!F$4:F$43<>"⏸️ POSTPONED")*('Project Portfolio'!A$4:A$43<>"")),_xlfn._xlws.FILTER(IF('Project Portfolio'!J$4:J$43=0,99999,'Project Portfolio'!J$4:J$43),('Project Portfolio'!F$4:F$43<>"✅ COMPLETE")*('Project Portfolio'!F$4:F$43<>"🚫 NOT APPROVED")*('Project Portfolio'!F$4:F$43<>"⏸️ POSTPONED")*('Project Portfolio'!A$4:A$43<>"")),1),ROW()-4),"")} -> ETE-7 | C11: {=IFERROR(INDEX(_xlfn.SORTBY(_xlfn._xlws.FILTER('Project Portfolio'!B$4:B$43,('Project Portfolio'!F$4:F$43<>"✅ COMPLETE")*('Project Portfolio'!F$4:F$43<>"🚫 NOT APPROVED")*('Project Portfolio'!F$4:F$43<>"⏸️ POSTPONED")*('Project Portfolio'!A$4:A$43<>"")),_xlfn._xlws.FILTER(IF('Project Portfolio'!J$4:J$43=0,99999,'Project Portfolio'!J$4:J$43),('Project Portfolio'!F$4:F$43<>"✅ COMPLETE")*('Project Portfolio'!F$4:F$43<>"🚫 NOT APPROVED")*('Project Portfolio'!F$4:F$43<>"⏸️ POSTPONED")*('Project Portfolio'!A$4:A$43<>"")),1),ROW()-4),"")} -> Outsourced Unit Core Accounting | D11: {=IFERROR(INDEX(_xlfn.SORTBY(_xlfn._xlws.FILTER('Project Portfolio'!F$4:F$43,('Project Portfolio'!F$4:F$43<>"✅ COMPLETE")*('Project Portfolio'!F$4:F$43<>"🚫 NOT APPROVED")*('Project Portfolio'!F$4:F$43<>"⏸️ POSTPONED")*('Project Portfolio'!A$4:A$43<>"")),_xlfn._xlws.FILTER(IF('Project Portfolio'!J$4:J$43=0,99999,'Project Portfolio'!J$4:J$43),('Project Portfolio'!F$4:F$43<>"✅ COMPLETE")*('Project Portfolio'!F$4:F$43<>"🚫 NOT APPROVED")*('Project Portfolio'!F$4:F$43<>"⏸️ POSTPONED")*('Project Portfolio'!A$4:A$43<>"")),1),ROW()-4),"")} -> 📋 NEEDS FUNCTIONAL SPEC | E11: {=IFERROR(IF(INDEX(_xlfn.SORTBY(_xlfn._xlws.FILTER('Project Portfolio'!I$4:I$43,('Project Portfolio'!F$4:F$43<>"✅ COMPLETE")*('Project Portfolio'!F$4:F$43<>"🚫 NOT APPROVED")*('Project Portfolio'!F$4:F$43<>"⏸️ POSTPONED")*('Project Portfolio'!A$4:A$43<>"")),_xlfn._xlws.FILTER(IF('Project Portfolio'!J$4:J$43=0,99999,'Project Portfolio'!J$4:J$43),('Project Portfolio'!F$4:F$43<>"✅ COMPLETE")*('Project Portfolio'!F$4:F$43<>"🚫 NOT APPROVED")*('Project Portfolio'!F$4:F$43<>"⏸️ POSTPONED")*('Project Portfolio'!A$4:A$43<>"")),1),ROW()-4)=0,"",INDEX(_xlfn.SORTBY(_xlfn._xlws.FILTER('Project Portfolio'!I$4:I$43,('Project Portfolio'!F$4:F$43<>"✅ COMPLETE")*('Project Portfolio'!F$4:F$43<>"🚫 NOT APPROVED")*('Project Portfolio'!F$4:F$43<>"⏸️ POSTPONED")*('Project Portfolio'!A$4:A$43<>"")),_xlfn._xlws.FILTER(IF('Project Portfolio'!J$4:J$43=0,99999,'Project Portfolio'!J$4:J$43),('Project Portfolio'!F$4:F$43<>"✅ COMPLETE")*('Project Portfolio'!F$4:F$43<>"🚫 NOT APPROVED")*('Project Portfolio'!F$4:F$43<>"⏸️ POSTPONED")*('Project Portfolio'!A$4:A$43<>"")),1),ROW()-4)),"")} | F11: {=IFERROR(IF(INDEX(_xlfn.SORTBY(_xlfn._xlws.FILTER('Project Portfolio'!J$4:J$43,('Project Portfolio'!F$4:F$43<>"✅ COMPLETE")*('Project Portfolio'!F$4:F$43<>"🚫 NOT APPROVED")*('Project Portfolio'!F$4:F$43<>"⏸️ POSTPONED")*('Project Portfolio'!A$4:A$43<>"")),_xlfn._xlws.FILTER(IF('Project Portfolio'!J$4:J$43=0,99999,'Project Portfolio'!J$4:J$43),('Project Portfolio'!F$4:F$43<>"✅ COMPLETE")*('Project Portfolio'!F$4:F$43<>"🚫 NOT APPROVED")*('Project Portfolio'!F$4:F$43<>"⏸️ POSTPONED")*('Project Portfolio'!A$4:A$43<>"")),1),ROW()-4)=0,"",INDEX(_xlfn.SORTBY(_xlfn._xlws.FILTER('Project Portfolio'!J$4:J$43,('Project Portfolio'!F$4:F$43<>"✅ COMPLETE")*('Project Portfolio'!F$4:F$43<>"🚫 NOT APPROVED")*('Project Portfolio'!F$4:F$43<>"⏸️ POSTPONED")*('Project Portfolio'!A$4:A$43<>"")),_xlfn._xlws.FILTER(IF('Project Portfolio'!J$4:J$43=0,99999,'Project Portfolio'!J$4:J$43),('Project Portfolio'!F$4:F$43<>"✅ COMPLETE")*('Project Portfolio'!F$4:F$43<>"🚫 NOT APPROVED")*('Project Portfolio'!F$4:F$43<>"⏸️ POSTPONED")*('Project Portfolio'!A$4:A$43<>"")),1),ROW()-4)),"")} | G11: =IF(AND($E11>0,$F11>0,G$4+6>=$E11,G$4<=$F11),1,"") | H11: =IF(AND($E11>0,$F11>0,H$4+6>=$E11,H$4<=$F11),1,"") | I11: =IF(AND($E11>0,$F11>0,I$4+6>=$E11,I$4<=$F11),1,"") | J11: =IF(AND($E11>0,$F11>0,J$4+6>=$E11,J$4<=$F11),1,"") | K11: =IF(AND($E11>0,$F11>0,K$4+6>=$E11,K$4<=$F11),1,"") | L11: =IF(AND($E11>0,$F11>0,L$4+6>=$E11,L$4<=$F11),1,"") | M11: =IF(AND($E11>0,$F11>0,M$4+6>=$E11,M$4<=$F11),1,"") | N11: =IF(AND($E11>0,$F11>0,N$4+6>=$E11,N$4<=$F11),1,"") | ... BF11: =IF(AND($E11>0,$F11>0,BF$4+6>=$E11,BF$4<=$F11),1,"")
A12: 8 | B12: {=IFERROR(INDEX(_xlfn.SORTBY(_xlfn._xlws.FILTER('Project Portfolio'!A$4:A$43,('Project Portfolio'!F$4:F$43<>"✅ COMPLETE")*('Project Portfolio'!F$4:F$43<>"🚫 NOT APPROVED")*('Project Portfolio'!F$4:F$43<>"⏸️ POSTPONED")*('Project Portfolio'!A$4:A$43<>"")),_xlfn._xlws.FILTER(IF('Project Portfolio'!J$4:J$43=0,99999,'Project Portfolio'!J$4:J$43),('Project Portfolio'!F$4:F$43<>"✅ COMPLETE")*('Project Portfolio'!F$4:F$43<>"🚫 NOT APPROVED")*('Project Portfolio'!F$4:F$43<>"⏸️ POSTPONED")*('Project Portfolio'!A$4:A$43<>"")),1),ROW()-4),"")} -> ETE-52 | C12: {=IFERROR(INDEX(_xlfn.SORTBY(_xlfn._xlws.FILTER('Project Portfolio'!B$4:B$43,('Project Portfolio'!F$4:F$43<>"✅ COMPLETE")*('Project Portfolio'!F$4:F$43<>"🚫 NOT APPROVED")*('Project Portfolio'!F$4:F$43<>"⏸️ POSTPONED")*('Project Portfolio'!A$4:A$43<>"")),_xlfn._xlws.FILTER(IF('Project Portfolio'!J$4:J$43=0,99999,'Project Portfolio'!J$4:J$43),('Project Portfolio'!F$4:F$43<>"✅ COMPLETE")*('Project Portfolio'!F$4:F$43<>"🚫 NOT APPROVED")*('Project Portfolio'!F$4:F$43<>"⏸️ POSTPONED")*('Project Portfolio'!A$4:A$43<>"")),1),ROW()-4),"")} -> SWIMS/Syteline Reporting | D12: {=IFERROR(INDEX(_xlfn.SORTBY(_xlfn._xlws.FILTER('Project Portfolio'!F$4:F$43,('Project Portfolio'!F$4:F$43<>"✅ COMPLETE")*('Project Portfolio'!F$4:F$43<>"🚫 NOT APPROVED")*('Project Portfolio'!F$4:F$43<>"⏸️ POSTPONED")*('Project Portfolio'!A$4:A$43<>"")),_xlfn._xlws.FILTER(IF('Project Portfolio'!J$4:J$43=0,99999,'Project Portfolio'!J$4:J$43),('Project Portfolio'!F$4:F$43<>"✅ COMPLETE")*('Project Portfolio'!F$4:F$43<>"🚫 NOT APPROVED")*('Project Portfolio'!F$4:F$43<>"⏸️ POSTPONED")*('Project Portfolio'!A$4:A$43<>"")),1),ROW()-4),"")} -> 📋 NEEDS TECHNICAL SPEC | E12: {=IFERROR(IF(INDEX(_xlfn.SORTBY(_xlfn._xlws.FILTER('Project Portfolio'!I$4:I$43,('Project Portfolio'!F$4:F$43<>"✅ COMPLETE")*('Project Portfolio'!F$4:F$43<>"🚫 NOT APPROVED")*('Project Portfolio'!F$4:F$43<>"⏸️ POSTPONED")*('Project Portfolio'!A$4:A$43<>"")),_xlfn._xlws.FILTER(IF('Project Portfolio'!J$4:J$43=0,99999,'Project Portfolio'!J$4:J$43),('Project Portfolio'!F$4:F$43<>"✅ COMPLETE")*('Project Portfolio'!F$4:F$43<>"🚫 NOT APPROVED")*('Project Portfolio'!F$4:F$43<>"⏸️ POSTPONED")*('Project Portfolio'!A$4:A$43<>"")),1),ROW()-4)=0,"",INDEX(_xlfn.SORTBY(_xlfn._xlws.FILTER('Project Portfolio'!I$4:I$43,('Project Portfolio'!F$4:F$43<>"✅ COMPLETE")*('Project Portfolio'!F$4:F$43<>"🚫 NOT APPROVED")*('Project Portfolio'!F$4:F$43<>"⏸️ POSTPONED")*('Project Portfolio'!A$4:A$43<>"")),_xlfn._xlws.FILTER(IF('Project Portfolio'!J$4:J$43=0,99999,'Project Portfolio'!J$4:J$43),('Project Portfolio'!F$4:F$43<>"✅ COMPLETE")*('Project Portfolio'!F$4:F$43<>"🚫 NOT APPROVED")*('Project Portfolio'!F$4:F$43<>"⏸️ POSTPONED")*('Project Portfolio'!A$4:A$43<>"")),1),ROW()-4)),"")} | F12: {=IFERROR(IF(INDEX(_xlfn.SORTBY(_xlfn._xlws.FILTER('Project Portfolio'!J$4:J$43,('Project Portfolio'!F$4:F$43<>"✅ COMPLETE")*('Project Portfolio'!F$4:F$43<>"🚫 NOT APPROVED")*('Project Portfolio'!F$4:F$43<>"⏸️ POSTPONED")*('Project Portfolio'!A$4:A$43<>"")),_xlfn._xlws.FILTER(IF('Project Portfolio'!J$4:J$43=0,99999,'Project Portfolio'!J$4:J$43),('Project Portfolio'!F$4:F$43<>"✅ COMPLETE")*('Project Portfolio'!F$4:F$43<>"🚫 NOT APPROVED")*('Project Portfolio'!F$4:F$43<>"⏸️ POSTPONED")*('Project Portfolio'!A$4:A$43<>"")),1),ROW()-4)=0,"",INDEX(_xlfn.SORTBY(_xlfn._xlws.FILTER('Project Portfolio'!J$4:J$43,('Project Portfolio'!F$4:F$43<>"✅ COMPLETE")*('Project Portfolio'!F$4:F$43<>"🚫 NOT APPROVED")*('Project Portfolio'!F$4:F$43<>"⏸️ POSTPONED")*('Project Portfolio'!A$4:A$43<>"")),_xlfn._xlws.FILTER(IF('Project Portfolio'!J$4:J$43=0,99999,'Project Portfolio'!J$4:J$43),('Project Portfolio'!F$4:F$43<>"✅ COMPLETE")*('Project Portfolio'!F$4:F$43<>"🚫 NOT APPROVED")*('Project Portfolio'!F$4:F$43<>"⏸️ POSTPONED")*('Project Portfolio'!A$4:A$43<>"")),1),ROW()-4)),"")} | G12: =IF(AND($E12>0,$F12>0,G$4+6>=$E12,G$4<=$F12),1,"") | H12: =IF(AND($E12>0,$F12>0,H$4+6>=$E12,H$4<=$F12),1,"") | I12: =IF(AND($E12>0,$F12>0,I$4+6>=$E12,I$4<=$F12),1,"") | J12: =IF(AND($E12>0,$F12>0,J$4+6>=$E12,J$4<=$F12),1,"") | K12: =IF(AND($E12>0,$F12>0,K$4+6>=$E12,K$4<=$F12),1,"") | L12: =IF(AND($E12>0,$F12>0,L$4+6>=$E12,L$4<=$F12),1,"") | M12: =IF(AND($E12>0,$F12>0,M$4+6>=$E12,M$4<=$F12),1,"") | N12: =IF(AND($E12>0,$F12>0,N$4+6>=$E12,N$4<=$F12),1,"") | ... BF12: =IF(AND($E12>0,$F12>0,BF$4+6>=$E12,BF$4<=$F12),1,"")
A13: 9 | B13: {=IFERROR(INDEX(_xlfn.SORTBY(_xlfn._xlws.FILTER('Project Portfolio'!A$4:A$43,('Project Portfolio'!F$4:F$43<>"✅ COMPLETE")*('Project Portfolio'!F$4:F$43<>"🚫 NOT APPROVED")*('Project Portfolio'!F$4:F$43<>"⏸️ POSTPONED")*('Project Portfolio'!A$4:A$43<>"")),_xlfn._xlws.FILTER(IF('Project Portfolio'!J$4:J$43=0,99999,'Project Portfolio'!J$4:J$43),('Project Portfolio'!F$4:F$43<>"✅ COMPLETE")*('Project Portfolio'!F$4:F$43<>"🚫 NOT APPROVED")*('Project Portfolio'!F$4:F$43<>"⏸️ POSTPONED")*('Project Portfolio'!A$4:A$43<>"")),1),ROW()-4),"")} -> ETE-16 | C13: {=IFERROR(INDEX(_xlfn.SORTBY(_xlfn._xlws.FILTER('Project Portfolio'!B$4:B$43,('Project Portfolio'!F$4:F$43<>"✅ COMPLETE")*('Project Portfolio'!F$4:F$43<>"🚫 NOT APPROVED")*('Project Portfolio'!F$4:F$43<>"⏸️ POSTPONED")*('Project Portfolio'!A$4:A$43<>"")),_xlfn._xlws.FILTER(IF('Project Portfolio'!J$4:J$43=0,99999,'Project Portfolio'!J$4:J$43),('Project Portfolio'!F$4:F$43<>"✅ COMPLETE")*('Project Portfolio'!F$4:F$43<>"🚫 NOT APPROVED")*('Project Portfolio'!F$4:F$43<>"⏸️ POSTPONED")*('Project Portfolio'!A$4:A$43<>"")),1),ROW()-4),"")} -> Partial Pay w/ CC from WMERP | D13: {=IFERROR(INDEX(_xlfn.SORTBY(_xlfn._xlws.FILTER('Project Portfolio'!F$4:F$43,('Project Portfolio'!F$4:F$43<>"✅ COMPLETE")*('Project Portfolio'!F$4:F$43<>"🚫 NOT APPROVED")*('Project Portfolio'!F$4:F$43<>"⏸️ POSTPONED")*('Project Portfolio'!A$4:A$43<>"")),_xlfn._xlws.FILTER(IF('Project Portfolio'!J$4:J$43=0,99999,'Project Portfolio'!J$4:J$43),('Project Portfolio'!F$4:F$43<>"✅ COMPLETE")*('Project Portfolio'!F$4:F$43<>"🚫 NOT APPROVED")*('Project Portfolio'!F$4:F$43<>"⏸️ POSTPONED")*('Project Portfolio'!A$4:A$43<>"")),1),ROW()-4),"")} -> ⚪ NOT STARTED | E13: {=IFERROR(IF(INDEX(_xlfn.SORTBY(_xlfn._xlws.FILTER('Project Portfolio'!I$4:I$43,('Project Portfolio'!F$4:F$43<>"✅ COMPLETE")*('Project Portfolio'!F$4:F$43<>"🚫 NOT APPROVED")*('Project Portfolio'!F$4:F$43<>"⏸️ POSTPONED")*('Project Portfolio'!A$4:A$43<>"")),_xlfn._xlws.FILTER(IF('Project Portfolio'!J$4:J$43=0,99999,'Project Portfolio'!J$4:J$43),('Project Portfolio'!F$4:F$43<>"✅ COMPLETE")*('Project Portfolio'!F$4:F$43<>"🚫 NOT APPROVED")*('Project Portfolio'!F$4:F$43<>"⏸️ POSTPONED")*('Project Portfolio'!A$4:A$43<>"")),1),ROW()-4)=0,"",INDEX(_xlfn.SORTBY(_xlfn._xlws.FILTER('Project Portfolio'!I$4:I$43,('Project Portfolio'!F$4:F$43<>"✅ COMPLETE")*('Project Portfolio'!F$4:F$43<>"🚫 NOT APPROVED")*('Project Portfolio'!F$4:F$43<>"⏸️ POSTPONED")*('Project Portfolio'!A$4:A$43<>"")),_xlfn._xlws.FILTER(IF('Project Portfolio'!J$4:J$43=0,99999,'Project Portfolio'!J$4:J$43),('Project Portfolio'!F$4:F$43<>"✅ COMPLETE")*('Project Portfolio'!F$4:F$43<>"🚫 NOT APPROVED")*('Project Portfolio'!F$4:F$43<>"⏸️ POSTPONED")*('Project Portfolio'!A$4:A$43<>"")),1),ROW()-4)),"")} | F13: {=IFERROR(IF(INDEX(_xlfn.SORTBY(_xlfn._xlws.FILTER('Project Portfolio'!J$4:J$43,('Project Portfolio'!F$4:F$43<>"✅ COMPLETE")*('Project Portfolio'!F$4:F$43<>"🚫 NOT APPROVED")*('Project Portfolio'!F$4:F$43<>"⏸️ POSTPONED")*('Project Portfolio'!A$4:A$43<>"")),_xlfn._xlws.FILTER(IF('Project Portfolio'!J$4:J$43=0,99999,'Project Portfolio'!J$4:J$43),('Project Portfolio'!F$4:F$43<>"✅ COMPLETE")*('Project Portfolio'!F$4:F$43<>"🚫 NOT APPROVED")*('Project Portfolio'!F$4:F$43<>"⏸️ POSTPONED")*('Project Portfolio'!A$4:A$43<>"")),1),ROW()-4)=0,"",INDEX(_xlfn.SORTBY(_xlfn._xlws.FILTER('Project Portfolio'!J$4:J$43,('Project Portfolio'!F$4:F$43<>"✅ COMPLETE")*('Project Portfolio'!F$4:F$43<>"🚫 NOT APPROVED")*('Project Portfolio'!F$4:F$43<>"⏸️ POSTPONED")*('Project Portfolio'!A$4:A$43<>"")),_xlfn._xlws.FILTER(IF('Project Portfolio'!J$4:J$43=0,99999,'Project Portfolio'!J$4:J$43),('Project Portfolio'!F$4:F$43<>"✅ COMPLETE")*('Project Portfolio'!F$4:F$43<>"🚫 NOT APPROVED")*('Project Portfolio'!F$4:F$43<>"⏸️ POSTPONED")*('Project Portfolio'!A$4:A$43<>"")),1),ROW()-4)),"")} | G13: =IF(AND($E13>0,$F13>0,G$4+6>=$E13,G$4<=$F13),1,"") | H13: =IF(AND($E13>0,$F13>0,H$4+6>=$E13,H$4<=$F13),1,"") | I13: =IF(AND($E13>0,$F13>0,I$4+6>=$E13,I$4<=$F13),1,"") | J13: =IF(AND($E13>0,$F13>0,J$4+6>=$E13,J$4<=$F13),1,"") | K13: =IF(AND($E13>0,$F13>0,K$4+6>=$E13,K$4<=$F13),1,"") | L13: =IF(AND($E13>0,$F13>0,L$4+6>=$E13,L$4<=$F13),1,"") | M13: =IF(AND($E13>0,$F13>0,M$4+6>=$E13,M$4<=$F13),1,"") | N13: =IF(AND($E13>0,$F13>0,N$4+6>=$E13,N$4<=$F13),1,"") | ... BF13: =IF(AND($E13>0,$F13>0,BF$4+6>=$E13,BF$4<=$F13),1,"")
A14: 10 | B14: {=IFERROR(INDEX(_xlfn.SORTBY(_xlfn._xlws.FILTER('Project Portfolio'!A$4:A$43,('Project Portfolio'!F$4:F$43<>"✅ COMPLETE")*('Project Portfolio'!F$4:F$43<>"🚫 NOT APPROVED")*('Project Portfolio'!F$4:F$43<>"⏸️ POSTPONED")*('Project Portfolio'!A$4:A$43<>"")),_xlfn._xlws.FILTER(IF('Project Portfolio'!J$4:J$43=0,99999,'Project Portfolio'!J$4:J$43),('Project Portfolio'!F$4:F$43<>"✅ COMPLETE")*('Project Portfolio'!F$4:F$43<>"🚫 NOT APPROVED")*('Project Portfolio'!F$4:F$43<>"⏸️ POSTPONED")*('Project Portfolio'!A$4:A$43<>"")),1),ROW()-4),"")} -> ETE-37 | C14: {=IFERROR(INDEX(_xlfn.SORTBY(_xlfn._xlws.FILTER('Project Portfolio'!B$4:B$43,('Project Portfolio'!F$4:F$43<>"✅ COMPLETE")*('Project Portfolio'!F$4:F$43<>"🚫 NOT APPROVED")*('Project Portfolio'!F$4:F$43<>"⏸️ POSTPONED")*('Project Portfolio'!A$4:A$43<>"")),_xlfn._xlws.FILTER(IF('Project Portfolio'!J$4:J$43=0,99999,'Project Portfolio'!J$4:J$43),('Project Portfolio'!F$4:F$43<>"✅ COMPLETE")*('Project Portfolio'!F$4:F$43<>"🚫 NOT APPROVED")*('Project Portfolio'!F$4:F$43<>"⏸️ POSTPONED")*('Project Portfolio'!A$4:A$43<>"")),1),ROW()-4),"")} -> Magic Search in BuyETE | D14: {=IFERROR(INDEX(_xlfn.SORTBY(_xlfn._xlws.FILTER('Project Portfolio'!F$4:F$43,('Project Portfolio'!F$4:F$43<>"✅ COMPLETE")*('Project Portfolio'!F$4:F$43<>"🚫 NOT APPROVED")*('Project Portfolio'!F$4:F$43<>"⏸️ POSTPONED")*('Project Portfolio'!A$4:A$43<>"")),_xlfn._xlws.FILTER(IF('Project Portfolio'!J$4:J$43=0,99999,'Project Portfolio'!J$4:J$43),('Project Portfolio'!F$4:F$43<>"✅ COMPLETE")*('Project Portfolio'!F$4:F$43<>"🚫 NOT APPROVED")*('Project Portfolio'!F$4:F$43<>"⏸️ POSTPONED")*('Project Portfolio'!A$4:A$43<>"")),1),ROW()-4),"")} -> 📋 NEEDS TECHNICAL SPEC | E14: {=IFERROR(IF(INDEX(_xlfn.SORTBY(_xlfn._xlws.FILTER('Project Portfolio'!I$4:I$43,('Project Portfolio'!F$4:F$43<>"✅ COMPLETE")*('Project Portfolio'!F$4:F$43<>"🚫 NOT APPROVED")*('Project Portfolio'!F$4:F$43<>"⏸️ POSTPONED")*('Project Portfolio'!A$4:A$43<>"")),_xlfn._xlws.FILTER(IF('Project Portfolio'!J$4:J$43=0,99999,'Project Portfolio'!J$4:J$43),('Project Portfolio'!F$4:F$43<>"✅ COMPLETE")*('Project Portfolio'!F$4:F$43<>"🚫 NOT APPROVED")*('Project Portfolio'!F$4:F$43<>"⏸️ POSTPONED")*('Project Portfolio'!A$4:A$43<>"")),1),ROW()-4)=0,"",INDEX(_xlfn.SORTBY(_xlfn._xlws.FILTER('Project Portfolio'!I$4:I$43,('Project Portfolio'!F$4:F$43<>"✅ COMPLETE")*('Project Portfolio'!F$4:F$43<>"🚫 NOT APPROVED")*('Project Portfolio'!F$4:F$43<>"⏸️ POSTPONED")*('Project Portfolio'!A$4:A$43<>"")),_xlfn._xlws.FILTER(IF('Project Portfolio'!J$4:J$43=0,99999,'Project Portfolio'!J$4:J$43),('Project Portfolio'!F$4:F$43<>"✅ COMPLETE")*('Project Portfolio'!F$4:F$43<>"🚫 NOT APPROVED")*('Project Portfolio'!F$4:F$43<>"⏸️ POSTPONED")*('Project Portfolio'!A$4:A$43<>"")),1),ROW()-4)),"")} | F14: {=IFERROR(IF(INDEX(_xlfn.SORTBY(_xlfn._xlws.FILTER('Project Portfolio'!J$4:J$43,('Project Portfolio'!F$4:F$43<>"✅ COMPLETE")*('Project Portfolio'!F$4:F$43<>"🚫 NOT APPROVED")*('Project Portfolio'!F$4:F$43<>"⏸️ POSTPONED")*('Project Portfolio'!A$4:A$43<>"")),_xlfn._xlws.FILTER(IF('Project Portfolio'!J$4:J$43=0,99999,'Project Portfolio'!J$4:J$43),('Project Portfolio'!F$4:F$43<>"✅ COMPLETE")*('Project Portfolio'!F$4:F$43<>"🚫 NOT APPROVED")*('Project Portfolio'!F$4:F$43<>"⏸️ POSTPONED")*('Project Portfolio'!A$4:A$43<>"")),1),ROW()-4)=0,"",INDEX(_xlfn.SORTBY(_xlfn._xlws.FILTER('Project Portfolio'!J$4:J$43,('Project Portfolio'!F$4:F$43<>"✅ COMPLETE")*('Project Portfolio'!F$4:F$43<>"🚫 NOT APPROVED")*('Project Portfolio'!F$4:F$43<>"⏸️ POSTPONED")*('Project Portfolio'!A$4:A$43<>"")),_xlfn._xlws.FILTER(IF('Project Portfolio'!J$4:J$43=0,99999,'Project Portfolio'!J$4:J$43),('Project Portfolio'!F$4:F$43<>"✅ COMPLETE")*('Project Portfolio'!F$4:F$43<>"🚫 NOT APPROVED")*('Project Portfolio'!F$4:F$43<>"⏸️ POSTPONED")*('Project Portfolio'!A$4:A$43<>"")),1),ROW()-4)),"")} | G14: =IF(AND($E14>0,$F14>0,G$4+6>=$E14,G$4<=$F14),1,"") | H14: =IF(AND($E14>0,$F14>0,H$4+6>=$E14,H$4<=$F14),1,"") | I14: =IF(AND($E14>0,$F14>0,I$4+6>=$E14,I$4<=$F14),1,"") | J14: =IF(AND($E14>0,$F14>0,J$4+6>=$E14,J$4<=$F14),1,"") | K14: =IF(AND($E14>0,$F14>0,K$4+6>=$E14,K$4<=$F14),1,"") | L14: =IF(AND($E14>0,$F14>0,L$4+6>=$E14,L$4<=$F14),1,"") | M14: =IF(AND($E14>0,$F14>0,M$4+6>=$E14,M$4<=$F14),1,"") | N14: =IF(AND($E14>0,$F14>0,N$4+6>=$E14,N$4<=$F14),1,"") | ... BF14: =IF(AND($E14>0,$F14>0,BF$4+6>=$E14,BF$4<=$F14),1,"")
A15: 11 | B15: {=IFERROR(INDEX(_xlfn.SORTBY(_xlfn._xlws.FILTER('Project Portfolio'!A$4:A$43,('Project Portfolio'!F$4:F$43<>"✅ COMPLETE")*('Project Portfolio'!F$4:F$43<>"🚫 NOT APPROVED")*('Project Portfolio'!F$4:F$43<>"⏸️ POSTPONED")*('Project Portfolio'!A$4:A$43<>"")),_xlfn._xlws.FILTER(IF('Project Portfolio'!J$4:J$43=0,99999,'Project Portfolio'!J$4:J$43),('Project Portfolio'!F$4:F$43<>"✅ COMPLETE")*('Project Portfolio'!F$4:F$43<>"🚫 NOT APPROVED")*('Project Portfolio'!F$4:F$43<>"⏸️ POSTPONED")*('Project Portfolio'!A$4:A$43<>"")),1),ROW()-4),"")} -> ETE-97 | C15: {=IFERROR(INDEX(_xlfn.SORTBY(_xlfn._xlws.FILTER('Project Portfolio'!B$4:B$43,('Project Portfolio'!F$4:F$43<>"✅ COMPLETE")*('Project Portfolio'!F$4:F$43<>"🚫 NOT APPROVED")*('Project Portfolio'!F$4:F$43<>"⏸️ POSTPONED")*('Project Portfolio'!A$4:A$43<>"")),_xlfn._xlws.FILTER(IF('Project Portfolio'!J$4:J$43=0,99999,'Project Portfolio'!J$4:J$43),('Project Portfolio'!F$4:F$43<>"✅ COMPLETE")*('Project Portfolio'!F$4:F$43<>"🚫 NOT APPROVED")*('Project Portfolio'!F$4:F$43<>"⏸️ POSTPONED")*('Project Portfolio'!A$4:A$43<>"")),1),ROW()-4),"")} -> Standard Order Process Notifications | D15: {=IFERROR(INDEX(_xlfn.SORTBY(_xlfn._xlws.FILTER('Project Portfolio'!F$4:F$43,('Project Portfolio'!F$4:F$43<>"✅ COMPLETE")*('Project Portfolio'!F$4:F$43<>"🚫 NOT APPROVED")*('Project Portfolio'!F$4:F$43<>"⏸️ POSTPONED")*('Project Portfolio'!A$4:A$43<>"")),_xlfn._xlws.FILTER(IF('Project Portfolio'!J$4:J$43=0,99999,'Project Portfolio'!J$4:J$43),('Project Portfolio'!F$4:F$43<>"✅ COMPLETE")*('Project Portfolio'!F$4:F$43<>"🚫 NOT APPROVED")*('Project Portfolio'!F$4:F$43<>"⏸️ POSTPONED")*('Project Portfolio'!A$4:A$43<>"")),1),ROW()-4),"")} -> ⚪ NOT STARTED | E15: {=IFERROR(IF(INDEX(_xlfn.SORTBY(_xlfn._xlws.FILTER('Project Portfolio'!I$4:I$43,('Project Portfolio'!F$4:F$43<>"✅ COMPLETE")*('Project Portfolio'!F$4:F$43<>"🚫 NOT APPROVED")*('Project Portfolio'!F$4:F$43<>"⏸️ POSTPONED")*('Project Portfolio'!A$4:A$43<>"")),_xlfn._xlws.FILTER(IF('Project Portfolio'!J$4:J$43=0,99999,'Project Portfolio'!J$4:J$43),('Project Portfolio'!F$4:F$43<>"✅ COMPLETE")*('Project Portfolio'!F$4:F$43<>"🚫 NOT APPROVED")*('Project Portfolio'!F$4:F$43<>"⏸️ POSTPONED")*('Project Portfolio'!A$4:A$43<>"")),1),ROW()-4)=0,"",INDEX(_xlfn.SORTBY(_xlfn._xlws.FILTER('Project Portfolio'!I$4:I$43,('Project Portfolio'!F$4:F$43<>"✅ COMPLETE")*('Project Portfolio'!F$4:F$43<>"🚫 NOT APPROVED")*('Project Portfolio'!F$4:F$43<>"⏸️ POSTPONED")*('Project Portfolio'!A$4:A$43<>"")),_xlfn._xlws.FILTER(IF('Project Portfolio'!J$4:J$43=0,99999,'Project Portfolio'!J$4:J$43),('Project Portfolio'!F$4:F$43<>"✅ COMPLETE")*('Project Portfolio'!F$4:F$43<>"🚫 NOT APPROVED")*('Project Portfolio'!F$4:F$43<>"⏸️ POSTPONED")*('Project Portfolio'!A$4:A$43<>"")),1),ROW()-4)),"")} | F15: {=IFERROR(IF(INDEX(_xlfn.SORTBY(_xlfn._xlws.FILTER('Project Portfolio'!J$4:J$43,('Project Portfolio'!F$4:F$43<>"✅ COMPLETE")*('Project Portfolio'!F$4:F$43<>"🚫 NOT APPROVED")*('Project Portfolio'!F$4:F$43<>"⏸️ POSTPONED")*('Project Portfolio'!A$4:A$43<>"")),_xlfn._xlws.FILTER(IF('Project Portfolio'!J$4:J$43=0,99999,'Project Portfolio'!J$4:J$43),('Project Portfolio'!F$4:F$43<>"✅ COMPLETE")*('Project Portfolio'!F$4:F$43<>"🚫 NOT APPROVED")*('Project Portfolio'!F$4:F$43<>"⏸️ POSTPONED")*('Project Portfolio'!A$4:A$43<>"")),1),ROW()-4)=0,"",INDEX(_xlfn.SORTBY(_xlfn._xlws.FILTER('Project Portfolio'!J$4:J$43,('Project Portfolio'!F$4:F$43<>"✅ COMPLETE")*('Project Portfolio'!F$4:F$43<>"🚫 NOT APPROVED")*('Project Portfolio'!F$4:F$43<>"⏸️ POSTPONED")*('Project Portfolio'!A$4:A$43<>"")),_xlfn._xlws.FILTER(IF('Project Portfolio'!J$4:J$43=0,99999,'Project Portfolio'!J$4:J$43),('Project Portfolio'!F$4:F$43<>"✅ COMPLETE")*('Project Portfolio'!F$4:F$43<>"🚫 NOT APPROVED")*('Project Portfolio'!F$4:F$43<>"⏸️ POSTPONED")*('Project Portfolio'!A$4:A$43<>"")),1),ROW()-4)),"")} | G15: =IF(AND($E15>0,$F15>0,G$4+6>=$E15,G$4<=$F15),1,"") | H15: =IF(AND($E15>0,$F15>0,H$4+6>=$E15,H$4<=$F15),1,"") | I15: =IF(AND($E15>0,$F15>0,I$4+6>=$E15,I$4<=$F15),1,"") | J15: =IF(AND($E15>0,$F15>0,J$4+6>=$E15,J$4<=$F15),1,"") | K15: =IF(AND($E15>0,$F15>0,K$4+6>=$E15,K$4<=$F15),1,"") | L15: =IF(AND($E15>0,$F15>0,L$4+6>=$E15,L$4<=$F15),1,"") | M15: =IF(AND($E15>0,$F15>0,M$4+6>=$E15,M$4<=$F15),1,"") | N15: =IF(AND($E15>0,$F15>0,N$4+6>=$E15,N$4<=$F15),1,"") | ... BF15: =IF(AND($E15>0,$F15>0,BF$4+6>=$E15,BF$4<=$F15),1,"")
A16: 12 | B16: {=IFERROR(INDEX(_xlfn.SORTBY(_xlfn._xlws.FILTER('Project Portfolio'!A$4:A$43,('Project Portfolio'!F$4:F$43<>"✅ COMPLETE")*('Project Portfolio'!F$4:F$43<>"🚫 NOT APPROVED")*('Project Portfolio'!F$4:F$43<>"⏸️ POSTPONED")*('Project Portfolio'!A$4:A$43<>"")),_xlfn._xlws.FILTER(IF('Project Portfolio'!J$4:J$43=0,99999,'Project Portfolio'!J$4:J$43),('Project Portfolio'!F$4:F$43<>"✅ COMPLETE")*('Project Portfolio'!F$4:F$43<>"🚫 NOT APPROVED")*('Project Portfolio'!F$4:F$43<>"⏸️ POSTPONED")*('Project Portfolio'!A$4:A$43<>"")),1),ROW()-4),"")} -> ETE-100 | C16: {=IFERROR(INDEX(_xlfn.SORTBY(_xlfn._xlws.FILTER('Project Portfolio'!B$4:B$43,('Project Portfolio'!F$4:F$43<>"✅ COMPLETE")*('Project Portfolio'!F$4:F$43<>"🚫 NOT APPROVED")*('Project Portfolio'!F$4:F$43<>"⏸️ POSTPONED")*('Project Portfolio'!A$4:A$43<>"")),_xlfn._xlws.FILTER(IF('Project Portfolio'!J$4:J$43=0,99999,'Project Portfolio'!J$4:J$43),('Project Portfolio'!F$4:F$43<>"✅ COMPLETE")*('Project Portfolio'!F$4:F$43<>"🚫 NOT APPROVED")*('Project Portfolio'!F$4:F$43<>"⏸️ POSTPONED")*('Project Portfolio'!A$4:A$43<>"")),1),ROW()-4),"")} -> ATSG Expired Members Self-Payment | D16: {=IFERROR(INDEX(_xlfn.SORTBY(_xlfn._xlws.FILTER('Project Portfolio'!F$4:F$43,('Project Portfolio'!F$4:F$43<>"✅ COMPLETE")*('Project Portfolio'!F$4:F$43<>"🚫 NOT APPROVED")*('Project Portfolio'!F$4:F$43<>"⏸️ POSTPONED")*('Project Portfolio'!A$4:A$43<>"")),_xlfn._xlws.FILTER(IF('Project Portfolio'!J$4:J$43=0,99999,'Project Portfolio'!J$4:J$43),('Project Portfolio'!F$4:F$43<>"✅ COMPLETE")*('Project Portfolio'!F$4:F$43<>"🚫 NOT APPROVED")*('Project Portfolio'!F$4:F$43<>"⏸️ POSTPONED")*('Project Portfolio'!A$4:A$43<>"")),1),ROW()-4),"")} -> 📋 NEEDS FUNCTIONAL SPEC | E16: {=IFERROR(IF(INDEX(_xlfn.SORTBY(_xlfn._xlws.FILTER('Project Portfolio'!I$4:I$43,('Project Portfolio'!F$4:F$43<>"✅ COMPLETE")*('Project Portfolio'!F$4:F$43<>"🚫 NOT APPROVED")*('Project Portfolio'!F$4:F$43<>"⏸️ POSTPONED")*('Project Portfolio'!A$4:A$43<>"")),_xlfn._xlws.FILTER(IF('Project Portfolio'!J$4:J$43=0,99999,'Project Portfolio'!J$4:J$43),('Project Portfolio'!F$4:F$43<>"✅ COMPLETE")*('Project Portfolio'!F$4:F$43<>"🚫 NOT APPROVED")*('Project Portfolio'!F$4:F$43<>"⏸️ POSTPONED")*('Project Portfolio'!A$4:A$43<>"")),1),ROW()-4)=0,"",INDEX(_xlfn.SORTBY(_xlfn._xlws.FILTER('Project Portfolio'!I$4:I$43,('Project Portfolio'!F$4:F$43<>"✅ COMPLETE")*('Project Portfolio'!F$4:F$43<>"🚫 NOT APPROVED")*('Project Portfolio'!F$4:F$43<>"⏸️ POSTPONED")*('Project Portfolio'!A$4:A$43<>"")),_xlfn._xlws.FILTER(IF('Project Portfolio'!J$4:J$43=0,99999,'Project Portfolio'!J$4:J$43),('Project Portfolio'!F$4:F$43<>"✅ COMPLETE")*('Project Portfolio'!F$4:F$43<>"🚫 NOT APPROVED")*('Project Portfolio'!F$4:F$43<>"⏸️ POSTPONED")*('Project Portfolio'!A$4:A$43<>"")),1),ROW()-4)),"")} | F16: {=IFERROR(IF(INDEX(_xlfn.SORTBY(_xlfn._xlws.FILTER('Project Portfolio'!J$4:J$43,('Project Portfolio'!F$4:F$43<>"✅ COMPLETE")*('Project Portfolio'!F$4:F$43<>"🚫 NOT APPROVED")*('Project Portfolio'!F$4:F$43<>"⏸️ POSTPONED")*('Project Portfolio'!A$4:A$43<>"")),_xlfn._xlws.FILTER(IF('Project Portfolio'!J$4:J$43=0,99999,'Project Portfolio'!J$4:J$43),('Project Portfolio'!F$4:F$43<>"✅ COMPLETE")*('Project Portfolio'!F$4:F$43<>"🚫 NOT APPROVED")*('Project Portfolio'!F$4:F$43<>"⏸️ POSTPONED")*('Project Portfolio'!A$4:A$43<>"")),1),ROW()-4)=0,"",INDEX(_xlfn.SORTBY(_xlfn._xlws.FILTER('Project Portfolio'!J$4:J$43,('Project Portfolio'!F$4:F$43<>"✅ COMPLETE")*('Project Portfolio'!F$4:F$43<>"🚫 NOT APPROVED")*('Project Portfolio'!F$4:F$43<>"⏸️ POSTPONED")*('Project Portfolio'!A$4:A$43<>"")),_xlfn._xlws.FILTER(IF('Project Portfolio'!J$4:J$43=0,99999,'Project Portfolio'!J$4:J$43),('Project Portfolio'!F$4:F$43<>"✅ COMPLETE")*('Project Portfolio'!F$4:F$43<>"🚫 NOT APPROVED")*('Project Portfolio'!F$4:F$43<>"⏸️ POSTPONED")*('Project Portfolio'!A$4:A$43<>"")),1),ROW()-4)),"")} | G16: =IF(AND($E16>0,$F16>0,G$4+6>=$E16,G$4<=$F16),1,"") | H16: =IF(AND($E16>0,$F16>0,H$4+6>=$E16,H$4<=$F16),1,"") | I16: =IF(AND($E16>0,$F16>0,I$4+6>=$E16,I$4<=$F16),1,"") | J16: =IF(AND($E16>0,$F16>0,J$4+6>=$E16,J$4<=$F16),1,"") | K16: =IF(AND($E16>0,$F16>0,K$4+6>=$E16,K$4<=$F16),1,"") | L16: =IF(AND($E16>0,$F16>0,L$4+6>=$E16,L$4<=$F16),1,"") | M16: =IF(AND($E16>0,$F16>0,M$4+6>=$E16,M$4<=$F16),1,"") | N16: =IF(AND($E16>0,$F16>0,N$4+6>=$E16,N$4<=$F16),1,"") | ... BF16: =IF(AND($E16>0,$F16>0,BF$4+6>=$E16,BF$4<=$F16),1,"")
A17: 13 | B17: {=IFERROR(INDEX(_xlfn.SORTBY(_xlfn._xlws.FILTER('Project Portfolio'!A$4:A$43,('Project Portfolio'!F$4:F$43<>"✅ COMPLETE")*('Project Portfolio'!F$4:F$43<>"🚫 NOT APPROVED")*('Project Portfolio'!F$4:F$43<>"⏸️ POSTPONED")*('Project Portfolio'!A$4:A$43<>"")),_xlfn._xlws.FILTER(IF('Project Portfolio'!J$4:J$43=0,99999,'Project Portfolio'!J$4:J$43),('Project Portfolio'!F$4:F$43<>"✅ COMPLETE")*('Project Portfolio'!F$4:F$43<>"🚫 NOT APPROVED")*('Project Portfolio'!F$4:F$43<>"⏸️ POSTPONED")*('Project Portfolio'!A$4:A$43<>"")),1),ROW()-4),"")} -> ETE-124 | C17: {=IFERROR(INDEX(_xlfn.SORTBY(_xlfn._xlws.FILTER('Project Portfolio'!B$4:B$43,('Project Portfolio'!F$4:F$43<>"✅ COMPLETE")*('Project Portfolio'!F$4:F$43<>"🚫 NOT APPROVED")*('Project Portfolio'!F$4:F$43<>"⏸️ POSTPONED")*('Project Portfolio'!A$4:A$43<>"")),_xlfn._xlws.FILTER(IF('Project Portfolio'!J$4:J$43=0,99999,'Project Portfolio'!J$4:J$43),('Project Portfolio'!F$4:F$43<>"✅ COMPLETE")*('Project Portfolio'!F$4:F$43<>"🚫 NOT APPROVED")*('Project Portfolio'!F$4:F$43<>"⏸️ POSTPONED")*('Project Portfolio'!A$4:A$43<>"")),1),ROW()-4),"")} -> Clean Up Return Loads | D17: {=IFERROR(INDEX(_xlfn.SORTBY(_xlfn._xlws.FILTER('Project Portfolio'!F$4:F$43,('Project Portfolio'!F$4:F$43<>"✅ COMPLETE")*('Project Portfolio'!F$4:F$43<>"🚫 NOT APPROVED")*('Project Portfolio'!F$4:F$43<>"⏸️ POSTPONED")*('Project Portfolio'!A$4:A$43<>"")),_xlfn._xlws.FILTER(IF('Project Portfolio'!J$4:J$43=0,99999,'Project Portfolio'!J$4:J$43),('Project Portfolio'!F$4:F$43<>"✅ COMPLETE")*('Project Portfolio'!F$4:F$43<>"🚫 NOT APPROVED")*('Project Portfolio'!F$4:F$43<>"⏸️ POSTPONED")*('Project Portfolio'!A$4:A$43<>"")),1),ROW()-4),"")} -> 📋 NEEDS TECHNICAL SPEC | E17: {=IFERROR(IF(INDEX(_xlfn.SORTBY(_xlfn._xlws.FILTER('Project Portfolio'!I$4:I$43,('Project Portfolio'!F$4:F$43<>"✅ COMPLETE")*('Project Portfolio'!F$4:F$43<>"🚫 NOT APPROVED")*('Project Portfolio'!F$4:F$43<>"⏸️ POSTPONED")*('Project Portfolio'!A$4:A$43<>"")),_xlfn._xlws.FILTER(IF('Project Portfolio'!J$4:J$43=0,99999,'Project Portfolio'!J$4:J$43),('Project Portfolio'!F$4:F$43<>"✅ COMPLETE")*('Project Portfolio'!F$4:F$43<>"🚫 NOT APPROVED")*('Project Portfolio'!F$4:F$43<>"⏸️ POSTPONED")*('Project Portfolio'!A$4:A$43<>"")),1),ROW()-4)=0,"",INDEX(_xlfn.SORTBY(_xlfn._xlws.FILTER('Project Portfolio'!I$4:I$43,('Project Portfolio'!F$4:F$43<>"✅ COMPLETE")*('Project Portfolio'!F$4:F$43<>"🚫 NOT APPROVED")*('Project Portfolio'!F$4:F$43<>"⏸️ POSTPONED")*('Project Portfolio'!A$4:A$43<>"")),_xlfn._xlws.FILTER(IF('Project Portfolio'!J$4:J$43=0,99999,'Project Portfolio'!J$4:J$43),('Project Portfolio'!F$4:F$43<>"✅ COMPLETE")*('Project Portfolio'!F$4:F$43<>"🚫 NOT APPROVED")*('Project Portfolio'!F$4:F$43<>"⏸️ POSTPONED")*('Project Portfolio'!A$4:A$43<>"")),1),ROW()-4)),"")} | F17: {=IFERROR(IF(INDEX(_xlfn.SORTBY(_xlfn._xlws.FILTER('Project Portfolio'!J$4:J$43,('Project Portfolio'!F$4:F$43<>"✅ COMPLETE")*('Project Portfolio'!F$4:F$43<>"🚫 NOT APPROVED")*('Project Portfolio'!F$4:F$43<>"⏸️ POSTPONED")*('Project Portfolio'!A$4:A$43<>"")),_xlfn._xlws.FILTER(IF('Project Portfolio'!J$4:J$43=0,99999,'Project Portfolio'!J$4:J$43),('Project Portfolio'!F$4:F$43<>"✅ COMPLETE")*('Project Portfolio'!F$4:F$43<>"🚫 NOT APPROVED")*('Project Portfolio'!F$4:F$43<>"⏸️ POSTPONED")*('Project Portfolio'!A$4:A$43<>"")),1),ROW()-4)=0,"",INDEX(_xlfn.SORTBY(_xlfn._xlws.FILTER('Project Portfolio'!J$4:J$43,('Project Portfolio'!F$4:F$43<>"✅ COMPLETE")*('Project Portfolio'!F$4:F$43<>"🚫 NOT APPROVED")*('Project Portfolio'!F$4:F$43<>"⏸️ POSTPONED")*('Project Portfolio'!A$4:A$43<>"")),_xlfn._xlws.FILTER(IF('Project Portfolio'!J$4:J$43=0,99999,'Project Portfolio'!J$4:J$43),('Project Portfolio'!F$4:F$43<>"✅ COMPLETE")*('Project Portfolio'!F$4:F$43<>"🚫 NOT APPROVED")*('Project Portfolio'!F$4:F$43<>"⏸️ POSTPONED")*('Project Portfolio'!A$4:A$43<>"")),1),ROW()-4)),"")} | G17: =IF(AND($E17>0,$F17>0,G$4+6>=$E17,G$4<=$F17),1,"") | H17: =IF(AND($E17>0,$F17>0,H$4+6>=$E17,H$4<=$F17),1,"") | I17: =IF(AND($E17>0,$F17>0,I$4+6>=$E17,I$4<=$F17),1,"") | J17: =IF(AND($E17>0,$F17>0,J$4+6>=$E17,J$4<=$F17),1,"") | K17: =IF(AND($E17>0,$F17>0,K$4+6>=$E17,K$4<=$F17),1,"") | L17: =IF(AND($E17>0,$F17>0,L$4+6>=$E17,L$4<=$F17),1,"") | M17: =IF(AND($E17>0,$F17>0,M$4+6>=$E17,M$4<=$F17),1,"") | N17: =IF(AND($E17>0,$F17>0,N$4+6>=$E17,N$4<=$F17),1,"") | ... BF17: =IF(AND($E17>0,$F17>0,BF$4+6>=$E17,BF$4<=$F17),1,"")
B18: {=IFERROR(INDEX(_xlfn.SORTBY(_xlfn._xlws.FILTER('Project Portfolio'!A$4:A$43,('Project Portfolio'!F$4:F$43<>"✅ COMPLETE")*('Project Portfolio'!F$4:F$43<>"🚫 NOT APPROVED")*('Project Portfolio'!F$4:F$43<>"⏸️ POSTPONED")*('Project Portfolio'!A$4:A$43<>"")),_xlfn._xlws.FILTER(IF('Project Portfolio'!J$4:J$43=0,99999,'Project Portfolio'!J$4:J$43),('Project Portfolio'!F$4:F$43<>"✅ COMPLETE")*('Project Portfolio'!F$4:F$43<>"🚫 NOT APPROVED")*('Project Portfolio'!F$4:F$43<>"⏸️ POSTPONED")*('Project Portfolio'!A$4:A$43<>"")),1),ROW()-4),"")} | C18: {=IFERROR(INDEX(_xlfn.SORTBY(_xlfn._xlws.FILTER('Project Portfolio'!B$4:B$43,('Project Portfolio'!F$4:F$43<>"✅ COMPLETE")*('Project Portfolio'!F$4:F$43<>"🚫 NOT APPROVED")*('Project Portfolio'!F$4:F$43<>"⏸️ POSTPONED")*('Project Portfolio'!A$4:A$43<>"")),_xlfn._xlws.FILTER(IF('Project Portfolio'!J$4:J$43=0,99999,'Project Portfolio'!J$4:J$43),('Project Portfolio'!F$4:F$43<>"✅ COMPLETE")*('Project Portfolio'!F$4:F$43<>"🚫 NOT APPROVED")*('Project Portfolio'!F$4:F$43<>"⏸️ POSTPONED")*('Project Portfolio'!A$4:A$43<>"")),1),ROW()-4),"")} | D18: {=IFERROR(INDEX(_xlfn.SORTBY(_xlfn._xlws.FILTER('Project Portfolio'!F$4:F$43,('Project Portfolio'!F$4:F$43<>"✅ COMPLETE")*('Project Portfolio'!F$4:F$43<>"🚫 NOT APPROVED")*('Project Portfolio'!F$4:F$43<>"⏸️ POSTPONED")*('Project Portfolio'!A$4:A$43<>"")),_xlfn._xlws.FILTER(IF('Project Portfolio'!J$4:J$43=0,99999,'Project Portfolio'!J$4:J$43),('Project Portfolio'!F$4:F$43<>"✅ COMPLETE")*('Project Portfolio'!F$4:F$43<>"🚫 NOT APPROVED")*('Project Portfolio'!F$4:F$43<>"⏸️ POSTPONED")*('Project Portfolio'!A$4:A$43<>"")),1),ROW()-4),"")} | E18: {=IFERROR(IF(INDEX(_xlfn.SORTBY(_xlfn._xlws.FILTER('Project Portfolio'!I$4:I$43,('Project Portfolio'!F$4:F$43<>"✅ COMPLETE")*('Project Portfolio'!F$4:F$43<>"🚫 NOT APPROVED")*('Project Portfolio'!F$4:F$43<>"⏸️ POSTPONED")*('Project Portfolio'!A$4:A$43<>"")),_xlfn._xlws.FILTER(IF('Project Portfolio'!J$4:J$43=0,99999,'Project Portfolio'!J$4:J$43),('Project Portfolio'!F$4:F$43<>"✅ COMPLETE")*('Project Portfolio'!F$4:F$43<>"🚫 NOT APPROVED")*('Project Portfolio'!F$4:F$43<>"⏸️ POSTPONED")*('Project Portfolio'!A$4:A$43<>"")),1),ROW()-4)=0,"",INDEX(_xlfn.SORTBY(_xlfn._xlws.FILTER('Project Portfolio'!I$4:I$43,('Project Portfolio'!F$4:F$43<>"✅ COMPLETE")*('Project Portfolio'!F$4:F$43<>"🚫 NOT APPROVED")*('Project Portfolio'!F$4:F$43<>"⏸️ POSTPONED")*('Project Portfolio'!A$4:A$43<>"")),_xlfn._xlws.FILTER(IF('Project Portfolio'!J$4:J$43=0,99999,'Project Portfolio'!J$4:J$43),('Project Portfolio'!F$4:F$43<>"✅ COMPLETE")*('Project Portfolio'!F$4:F$43<>"🚫 NOT APPROVED")*('Project Portfolio'!F$4:F$43<>"⏸️ POSTPONED")*('Project Portfolio'!A$4:A$43<>"")),1),ROW()-4)),"")} | F18: {=IFERROR(IF(INDEX(_xlfn.SORTBY(_xlfn._xlws.FILTER('Project Portfolio'!J$4:J$43,('Project Portfolio'!F$4:F$43<>"✅ COMPLETE")*('Project Portfolio'!F$4:F$43<>"🚫 NOT APPROVED")*('Project Portfolio'!F$4:F$43<>"⏸️ POSTPONED")*('Project Portfolio'!A$4:A$43<>"")),_xlfn._xlws.FILTER(IF('Project Portfolio'!J$4:J$43=0,99999,'Project Portfolio'!J$4:J$43),('Project Portfolio'!F$4:F$43<>"✅ COMPLETE")*('Project Portfolio'!F$4:F$43<>"🚫 NOT APPROVED")*('Project Portfolio'!F$4:F$43<>"⏸️ POSTPONED")*('Project Portfolio'!A$4:A$43<>"")),1),ROW()-4)=0,"",INDEX(_xlfn.SORTBY(_xlfn._xlws.FILTER('Project Portfolio'!J$4:J$43,('Project Portfolio'!F$4:F$43<>"✅ COMPLETE")*('Project Portfolio'!F$4:F$43<>"🚫 NOT APPROVED")*('Project Portfolio'!F$4:F$43<>"⏸️ POSTPONED")*('Project Portfolio'!A$4:A$43<>"")),_xlfn._xlws.FILTER(IF('Project Portfolio'!J$4:J$43=0,99999,'Project Portfolio'!J$4:J$43),('Project Portfolio'!F$4:F$43<>"✅ COMPLETE")*('Project Portfolio'!F$4:F$43<>"🚫 NOT APPROVED")*('Project Portfolio'!F$4:F$43<>"⏸️ POSTPONED")*('Project Portfolio'!A$4:A$43<>"")),1),ROW()-4)),"")} | G18: =IF(AND($E18>0,$F18>0,G$4+6>=$E18,G$4<=$F18),1,"") | H18: =IF(AND($E18>0,$F18>0,H$4+6>=$E18,H$4<=$F18),1,"") | I18: =IF(AND($E18>0,$F18>0,I$4+6>=$E18,I$4<=$F18),1,"") | J18: =IF(AND($E18>0,$F18>0,J$4+6>=$E18,J$4<=$F18),1,"") | K18: =IF(AND($E18>0,$F18>0,K$4+6>=$E18,K$4<=$F18),1,"") | L18: =IF(AND($E18>0,$F18>0,L$4+6>=$E18,L$4<=$F18),1,"") | M18: =IF(AND($E18>0,$F18>0,M$4+6>=$E18,M$4<=$F18),1,"") | N18: =IF(AND($E18>0,$F18>0,N$4+6>=$E18,N$4<=$F18),1,"") | ... BF18: =IF(AND($E18>0,$F18>0,BF$4+6>=$E18,BF$4<=$F18),1,"")
B19: {=IFERROR(INDEX(_xlfn.SORTBY(_xlfn._xlws.FILTER('Project Portfolio'!A$4:A$43,('Project Portfolio'!F$4:F$43<>"✅ COMPLETE")*('Project Portfolio'!F$4:F$43<>"🚫 NOT APPROVED")*('Project Portfolio'!F$4:F$43<>"⏸️ POSTPONED")*('Project Portfolio'!A$4:A$43<>"")),_xlfn._xlws.FILTER(IF('Project Portfolio'!J$4:J$43=0,99999,'Project Portfolio'!J$4:J$43),('Project Portfolio'!F$4:F$43<>"✅ COMPLETE")*('Project Portfolio'!F$4:F$43<>"🚫 NOT APPROVED")*('Project Portfolio'!F$4:F$43<>"⏸️ POSTPONED")*('Project Portfolio'!A$4:A$43<>"")),1),ROW()-4),"")} | C19: {=IFERROR(INDEX(_xlfn.SORTBY(_xlfn._xlws.FILTER('Project Portfolio'!B$4:B$43,('Project Portfolio'!F$4:F$43<>"✅ COMPLETE")*('Project Portfolio'!F$4:F$43<>"🚫 NOT APPROVED")*('Project Portfolio'!F$4:F$43<>"⏸️ POSTPONED")*('Project Portfolio'!A$4:A$43<>"")),_xlfn._xlws.FILTER(IF('Project Portfolio'!J$4:J$43=0,99999,'Project Portfolio'!J$4:J$43),('Project Portfolio'!F$4:F$43<>"✅ COMPLETE")*('Project Portfolio'!F$4:F$43<>"🚫 NOT APPROVED")*('Project Portfolio'!F$4:F$43<>"⏸️ POSTPONED")*('Project Portfolio'!A$4:A$43<>"")),1),ROW()-4),"")} | D19: {=IFERROR(INDEX(_xlfn.SORTBY(_xlfn._xlws.FILTER('Project Portfolio'!F$4:F$43,('Project Portfolio'!F$4:F$43<>"✅ COMPLETE")*('Project Portfolio'!F$4:F$43<>"🚫 NOT APPROVED")*('Project Portfolio'!F$4:F$43<>"⏸️ POSTPONED")*('Project Portfolio'!A$4:A$43<>"")),_xlfn._xlws.FILTER(IF('Project Portfolio'!J$4:J$43=0,99999,'Project Portfolio'!J$4:J$43),('Project Portfolio'!F$4:F$43<>"✅ COMPLETE")*('Project Portfolio'!F$4:F$43<>"🚫 NOT APPROVED")*('Project Portfolio'!F$4:F$43<>"⏸️ POSTPONED")*('Project Portfolio'!A$4:A$43<>"")),1),ROW()-4),"")} | E19: {=IFERROR(IF(INDEX(_xlfn.SORTBY(_xlfn._xlws.FILTER('Project Portfolio'!I$4:I$43,('Project Portfolio'!F$4:F$43<>"✅ COMPLETE")*('Project Portfolio'!F$4:F$43<>"🚫 NOT APPROVED")*('Project Portfolio'!F$4:F$43<>"⏸️ POSTPONED")*('Project Portfolio'!A$4:A$43<>"")),_xlfn._xlws.FILTER(IF('Project Portfolio'!J$4:J$43=0,99999,'Project Portfolio'!J$4:J$43),('Project Portfolio'!F$4:F$43<>"✅ COMPLETE")*('Project Portfolio'!F$4:F$43<>"🚫 NOT APPROVED")*('Project Portfolio'!F$4:F$43<>"⏸️ POSTPONED")*('Project Portfolio'!A$4:A$43<>"")),1),ROW()-4)=0,"",INDEX(_xlfn.SORTBY(_xlfn._xlws.FILTER('Project Portfolio'!I$4:I$43,('Project Portfolio'!F$4:F$43<>"✅ COMPLETE")*('Project Portfolio'!F$4:F$43<>"🚫 NOT APPROVED")*('Project Portfolio'!F$4:F$43<>"⏸️ POSTPONED")*('Project Portfolio'!A$4:A$43<>"")),_xlfn._xlws.FILTER(IF('Project Portfolio'!J$4:J$43=0,99999,'Project Portfolio'!J$4:J$43),('Project Portfolio'!F$4:F$43<>"✅ COMPLETE")*('Project Portfolio'!F$4:F$43<>"🚫 NOT APPROVED")*('Project Portfolio'!F$4:F$43<>"⏸️ POSTPONED")*('Project Portfolio'!A$4:A$43<>"")),1),ROW()-4)),"")} | F19: {=IFERROR(IF(INDEX(_xlfn.SORTBY(_xlfn._xlws.FILTER('Project Portfolio'!J$4:J$43,('Project Portfolio'!F$4:F$43<>"✅ COMPLETE")*('Project Portfolio'!F$4:F$43<>"🚫 NOT APPROVED")*('Project Portfolio'!F$4:F$43<>"⏸️ POSTPONED")*('Project Portfolio'!A$4:A$43<>"")),_xlfn._xlws.FILTER(IF('Project Portfolio'!J$4:J$43=0,99999,'Project Portfolio'!J$4:J$43),('Project Portfolio'!F$4:F$43<>"✅ COMPLETE")*('Project Portfolio'!F$4:F$43<>"🚫 NOT APPROVED")*('Project Portfolio'!F$4:F$43<>"⏸️ POSTPONED")*('Project Portfolio'!A$4:A$43<>"")),1),ROW()-4)=0,"",INDEX(_xlfn.SORTBY(_xlfn._xlws.FILTER('Project Portfolio'!J$4:J$43,('Project Portfolio'!F$4:F$43<>"✅ COMPLETE")*('Project Portfolio'!F$4:F$43<>"🚫 NOT APPROVED")*('Project Portfolio'!F$4:F$43<>"⏸️ POSTPONED")*('Project Portfolio'!A$4:A$43<>"")),_xlfn._xlws.FILTER(IF('Project Portfolio'!J$4:J$43=0,99999,'Project Portfolio'!J$4:J$43),('Project Portfolio'!F$4:F$43<>"✅ COMPLETE")*('Project Portfolio'!F$4:F$43<>"🚫 NOT APPROVED")*('Project Portfolio'!F$4:F$43<>"⏸️ POSTPONED")*('Project Portfolio'!A$4:A$43<>"")),1),ROW()-4)),"")} | G19: =IF(AND($E19>0,$F19>0,G$4+6>=$E19,G$4<=$F19),1,"") | H19: =IF(AND($E19>0,$F19>0,H$4+6>=$E19,H$4<=$F19),1,"") | I19: =IF(AND($E19>0,$F19>0,I$4+6>=$E19,I$4<=$F19),1,"") | J19: =IF(AND($E19>0,$F19>0,J$4+6>=$E19,J$4<=$F19),1,"") | K19: =IF(AND($E19>0,$F19>0,K$4+6>=$E19,K$4<=$F19),1,"") | L19: =IF(AND($E19>0,$F19>0,L$4+6>=$E19,L$4<=$F19),1,"") | M19: =IF(AND($E19>0,$F19>0,M$4+6>=$E19,M$4<=$F19),1,"") | N19: =IF(AND($E19>0,$F19>0,N$4+6>=$E19,N$4<=$F19),1,"") | ... BF19: =IF(AND($E19>0,$F19>0,BF$4+6>=$E19,BF$4<=$F19),1,"")
B20: {=IFERROR(INDEX(_xlfn.SORTBY(_xlfn._xlws.FILTER('Project Portfolio'!A$4:A$43,('Project Portfolio'!F$4:F$43<>"✅ COMPLETE")*('Project Portfolio'!F$4:F$43<>"🚫 NOT APPROVED")*('Project Portfolio'!F$4:F$43<>"⏸️ POSTPONED")*('Project Portfolio'!A$4:A$43<>"")),_xlfn._xlws.FILTER(IF('Project Portfolio'!J$4:J$43=0,99999,'Project Portfolio'!J$4:J$43),('Project Portfolio'!F$4:F$43<>"✅ COMPLETE")*('Project Portfolio'!F$4:F$43<>"🚫 NOT APPROVED")*('Project Portfolio'!F$4:F$43<>"⏸️ POSTPONED")*('Project Portfolio'!A$4:A$43<>"")),1),ROW()-4),"")} | C20: {=IFERROR(INDEX(_xlfn.SORTBY(_xlfn._xlws.FILTER('Project Portfolio'!B$4:B$43,('Project Portfolio'!F$4:F$43<>"✅ COMPLETE")*('Project Portfolio'!F$4:F$43<>"🚫 NOT APPROVED")*('Project Portfolio'!F$4:F$43<>"⏸️ POSTPONED")*('Project Portfolio'!A$4:A$43<>"")),_xlfn._xlws.FILTER(IF('Project Portfolio'!J$4:J$43=0,99999,'Project Portfolio'!J$4:J$43),('Project Portfolio'!F$4:F$43<>"✅ COMPLETE")*('Project Portfolio'!F$4:F$43<>"🚫 NOT APPROVED")*('Project Portfolio'!F$4:F$43<>"⏸️ POSTPONED")*('Project Portfolio'!A$4:A$43<>"")),1),ROW()-4),"")} | D20: {=IFERROR(INDEX(_xlfn.SORTBY(_xlfn._xlws.FILTER('Project Portfolio'!F$4:F$43,('Project Portfolio'!F$4:F$43<>"✅ COMPLETE")*('Project Portfolio'!F$4:F$43<>"🚫 NOT APPROVED")*('Project Portfolio'!F$4:F$43<>"⏸️ POSTPONED")*('Project Portfolio'!A$4:A$43<>"")),_xlfn._xlws.FILTER(IF('Project Portfolio'!J$4:J$43=0,99999,'Project Portfolio'!J$4:J$43),('Project Portfolio'!F$4:F$43<>"✅ COMPLETE")*('Project Portfolio'!F$4:F$43<>"🚫 NOT APPROVED")*('Project Portfolio'!F$4:F$43<>"⏸️ POSTPONED")*('Project Portfolio'!A$4:A$43<>"")),1),ROW()-4),"")} | E20: {=IFERROR(IF(INDEX(_xlfn.SORTBY(_xlfn._xlws.FILTER('Project Portfolio'!I$4:I$43,('Project Portfolio'!F$4:F$43<>"✅ COMPLETE")*('Project Portfolio'!F$4:F$43<>"🚫 NOT APPROVED")*('Project Portfolio'!F$4:F$43<>"⏸️ POSTPONED")*('Project Portfolio'!A$4:A$43<>"")),_xlfn._xlws.FILTER(IF('Project Portfolio'!J$4:J$43=0,99999,'Project Portfolio'!J$4:J$43),('Project Portfolio'!F$4:F$43<>"✅ COMPLETE")*('Project Portfolio'!F$4:F$43<>"🚫 NOT APPROVED")*('Project Portfolio'!F$4:F$43<>"⏸️ POSTPONED")*('Project Portfolio'!A$4:A$43<>"")),1),ROW()-4)=0,"",INDEX(_xlfn.SORTBY(_xlfn._xlws.FILTER('Project Portfolio'!I$4:I$43,('Project Portfolio'!F$4:F$43<>"✅ COMPLETE")*('Project Portfolio'!F$4:F$43<>"🚫 NOT APPROVED")*('Project Portfolio'!F$4:F$43<>"⏸️ POSTPONED")*('Project Portfolio'!A$4:A$43<>"")),_xlfn._xlws.FILTER(IF('Project Portfolio'!J$4:J$43=0,99999,'Project Portfolio'!J$4:J$43),('Project Portfolio'!F$4:F$43<>"✅ COMPLETE")*('Project Portfolio'!F$4:F$43<>"🚫 NOT APPROVED")*('Project Portfolio'!F$4:F$43<>"⏸️ POSTPONED")*('Project Portfolio'!A$4:A$43<>"")),1),ROW()-4)),"")} | F20: {=IFERROR(IF(INDEX(_xlfn.SORTBY(_xlfn._xlws.FILTER('Project Portfolio'!J$4:J$43,('Project Portfolio'!F$4:F$43<>"✅ COMPLETE")*('Project Portfolio'!F$4:F$43<>"🚫 NOT APPROVED")*('Project Portfolio'!F$4:F$43<>"⏸️ POSTPONED")*('Project Portfolio'!A$4:A$43<>"")),_xlfn._xlws.FILTER(IF('Project Portfolio'!J$4:J$43=0,99999,'Project Portfolio'!J$4:J$43),('Project Portfolio'!F$4:F$43<>"✅ COMPLETE")*('Project Portfolio'!F$4:F$43<>"🚫 NOT APPROVED")*('Project Portfolio'!F$4:F$43<>"⏸️ POSTPONED")*('Project Portfolio'!A$4:A$43<>"")),1),ROW()-4)=0,"",INDEX(_xlfn.SORTBY(_xlfn._xlws.FILTER('Project Portfolio'!J$4:J$43,('Project Portfolio'!F$4:F$43<>"✅ COMPLETE")*('Project Portfolio'!F$4:F$43<>"🚫 NOT APPROVED")*('Project Portfolio'!F$4:F$43<>"⏸️ POSTPONED")*('Project Portfolio'!A$4:A$43<>"")),_xlfn._xlws.FILTER(IF('Project Portfolio'!J$4:J$43=0,99999,'Project Portfolio'!J$4:J$43),('Project Portfolio'!F$4:F$43<>"✅ COMPLETE")*('Project Portfolio'!F$4:F$43<>"🚫 NOT APPROVED")*('Project Portfolio'!F$4:F$43<>"⏸️ POSTPONED")*('Project Portfolio'!A$4:A$43<>"")),1),ROW()-4)),"")} | G20: =IF(AND($E20>0,$F20>0,G$4+6>=$E20,G$4<=$F20),1,"") | H20: =IF(AND($E20>0,$F20>0,H$4+6>=$E20,H$4<=$F20),1,"") | I20: =IF(AND($E20>0,$F20>0,I$4+6>=$E20,I$4<=$F20),1,"") | J20: =IF(AND($E20>0,$F20>0,J$4+6>=$E20,J$4<=$F20),1,"") | K20: =IF(AND($E20>0,$F20>0,K$4+6>=$E20,K$4<=$F20),1,"") | L20: =IF(AND($E20>0,$F20>0,L$4+6>=$E20,L$4<=$F20),1,"") | M20: =IF(AND($E20>0,$F20>0,M$4+6>=$E20,M$4<=$F20),1,"") | N20: =IF(AND($E20>0,$F20>0,N$4+6>=$E20,N$4<=$F20),1,"") | ... BF20: =IF(AND($E20>0,$F20>0,BF$4+6>=$E20,BF$4<=$F20),1,"")
B21: {=IFERROR(INDEX(_xlfn.SORTBY(_xlfn._xlws.FILTER('Project Portfolio'!A$4:A$43,('Project Portfolio'!F$4:F$43<>"✅ COMPLETE")*('Project Portfolio'!F$4:F$43<>"🚫 NOT APPROVED")*('Project Portfolio'!F$4:F$43<>"⏸️ POSTPONED")*('Project Portfolio'!A$4:A$43<>"")),_xlfn._xlws.FILTER(IF('Project Portfolio'!J$4:J$43=0,99999,'Project Portfolio'!J$4:J$43),('Project Portfolio'!F$4:F$43<>"✅ COMPLETE")*('Project Portfolio'!F$4:F$43<>"🚫 NOT APPROVED")*('Project Portfolio'!F$4:F$43<>"⏸️ POSTPONED")*('Project Portfolio'!A$4:A$43<>"")),1),ROW()-4),"")} | C21: {=IFERROR(INDEX(_xlfn.SORTBY(_xlfn._xlws.FILTER('Project Portfolio'!B$4:B$43,('Project Portfolio'!F$4:F$43<>"✅ COMPLETE")*('Project Portfolio'!F$4:F$43<>"🚫 NOT APPROVED")*('Project Portfolio'!F$4:F$43<>"⏸️ POSTPONED")*('Project Portfolio'!A$4:A$43<>"")),_xlfn._xlws.FILTER(IF('Project Portfolio'!J$4:J$43=0,99999,'Project Portfolio'!J$4:J$43),('Project Portfolio'!F$4:F$43<>"✅ COMPLETE")*('Project Portfolio'!F$4:F$43<>"🚫 NOT APPROVED")*('Project Portfolio'!F$4:F$43<>"⏸️ POSTPONED")*('Project Portfolio'!A$4:A$43<>"")),1),ROW()-4),"")} | D21: {=IFERROR(INDEX(_xlfn.SORTBY(_xlfn._xlws.FILTER('Project Portfolio'!F$4:F$43,('Project Portfolio'!F$4:F$43<>"✅ COMPLETE")*('Project Portfolio'!F$4:F$43<>"🚫 NOT APPROVED")*('Project Portfolio'!F$4:F$43<>"⏸️ POSTPONED")*('Project Portfolio'!A$4:A$43<>"")),_xlfn._xlws.FILTER(IF('Project Portfolio'!J$4:J$43=0,99999,'Project Portfolio'!J$4:J$43),('Project Portfolio'!F$4:F$43<>"✅ COMPLETE")*('Project Portfolio'!F$4:F$43<>"🚫 NOT APPROVED")*('Project Portfolio'!F$4:F$43<>"⏸️ POSTPONED")*('Project Portfolio'!A$4:A$43<>"")),1),ROW()-4),"")} | E21: {=IFERROR(IF(INDEX(_xlfn.SORTBY(_xlfn._xlws.FILTER('Project Portfolio'!I$4:I$43,('Project Portfolio'!F$4:F$43<>"✅ COMPLETE")*('Project Portfolio'!F$4:F$43<>"🚫 NOT APPROVED")*('Project Portfolio'!F$4:F$43<>"⏸️ POSTPONED")*('Project Portfolio'!A$4:A$43<>"")),_xlfn._xlws.FILTER(IF('Project Portfolio'!J$4:J$43=0,99999,'Project Portfolio'!J$4:J$43),('Project Portfolio'!F$4:F$43<>"✅ COMPLETE")*('Project Portfolio'!F$4:F$43<>"🚫 NOT APPROVED")*('Project Portfolio'!F$4:F$43<>"⏸️ POSTPONED")*('Project Portfolio'!A$4:A$43<>"")),1),ROW()-4)=0,"",INDEX(_xlfn.SORTBY(_xlfn._xlws.FILTER('Project Portfolio'!I$4:I$43,('Project Portfolio'!F$4:F$43<>"✅ COMPLETE")*('Project Portfolio'!F$4:F$43<>"🚫 NOT APPROVED")*('Project Portfolio'!F$4:F$43<>"⏸️ POSTPONED")*('Project Portfolio'!A$4:A$43<>"")),_xlfn._xlws.FILTER(IF('Project Portfolio'!J$4:J$43=0,99999,'Project Portfolio'!J$4:J$43),('Project Portfolio'!F$4:F$43<>"✅ COMPLETE")*('Project Portfolio'!F$4:F$43<>"🚫 NOT APPROVED")*('Project Portfolio'!F$4:F$43<>"⏸️ POSTPONED")*('Project Portfolio'!A$4:A$43<>"")),1),ROW()-4)),"")} | F21: {=IFERROR(IF(INDEX(_xlfn.SORTBY(_xlfn._xlws.FILTER('Project Portfolio'!J$4:J$43,('Project Portfolio'!F$4:F$43<>"✅ COMPLETE")*('Project Portfolio'!F$4:F$43<>"🚫 NOT APPROVED")*('Project Portfolio'!F$4:F$43<>"⏸️ POSTPONED")*('Project Portfolio'!A$4:A$43<>"")),_xlfn._xlws.FILTER(IF('Project Portfolio'!J$4:J$43=0,99999,'Project Portfolio'!J$4:J$43),('Project Portfolio'!F$4:F$43<>"✅ COMPLETE")*('Project Portfolio'!F$4:F$43<>"🚫 NOT APPROVED")*('Project Portfolio'!F$4:F$43<>"⏸️ POSTPONED")*('Project Portfolio'!A$4:A$43<>"")),1),ROW()-4)=0,"",INDEX(_xlfn.SORTBY(_xlfn._xlws.FILTER('Project Portfolio'!J$4:J$43,('Project Portfolio'!F$4:F$43<>"✅ COMPLETE")*('Project Portfolio'!F$4:F$43<>"🚫 NOT APPROVED")*('Project Portfolio'!F$4:F$43<>"⏸️ POSTPONED")*('Project Portfolio'!A$4:A$43<>"")),_xlfn._xlws.FILTER(IF('Project Portfolio'!J$4:J$43=0,99999,'Project Portfolio'!J$4:J$43),('Project Portfolio'!F$4:F$43<>"✅ COMPLETE")*('Project Portfolio'!F$4:F$43<>"🚫 NOT APPROVED")*('Project Portfolio'!F$4:F$43<>"⏸️ POSTPONED")*('Project Portfolio'!A$4:A$43<>"")),1),ROW()-4)),"")} | G21: =IF(AND($E21>0,$F21>0,G$4+6>=$E21,G$4<=$F21),1,"") | H21: =IF(AND($E21>0,$F21>0,H$4+6>=$E21,H$4<=$F21),1,"") | I21: =IF(AND($E21>0,$F21>0,I$4+6>=$E21,I$4<=$F21),1,"") | J21: =IF(AND($E21>0,$F21>0,J$4+6>=$E21,J$4<=$F21),1,"") | K21: =IF(AND($E21>0,$F21>0,K$4+6>=$E21,K$4<=$F21),1,"") | L21: =IF(AND($E21>0,$F21>0,L$4+6>=$E21,L$4<=$F21),1,"") | M21: =IF(AND($E21>0,$F21>0,M$4+6>=$E21,M$4<=$F21),1,"") | N21: =IF(AND($E21>0,$F21>0,N$4+6>=$E21,N$4<=$F21),1,"") | ... BF21: =IF(AND($E21>0,$F21>0,BF$4+6>=$E21,BF$4<=$F21),1,"")
B22: {=IFERROR(INDEX(_xlfn.SORTBY(_xlfn._xlws.FILTER('Project Portfolio'!A$4:A$43,('Project Portfolio'!F$4:F$43<>"✅ COMPLETE")*('Project Portfolio'!F$4:F$43<>"🚫 NOT APPROVED")*('Project Portfolio'!F$4:F$43<>"⏸️ POSTPONED")*('Project Portfolio'!A$4:A$43<>"")),_xlfn._xlws.FILTER(IF('Project Portfolio'!J$4:J$43=0,99999,'Project Portfolio'!J$4:J$43),('Project Portfolio'!F$4:F$43<>"✅ COMPLETE")*('Project Portfolio'!F$4:F$43<>"🚫 NOT APPROVED")*('Project Portfolio'!F$4:F$43<>"⏸️ POSTPONED")*('Project Portfolio'!A$4:A$43<>"")),1),ROW()-4),"")} | C22: {=IFERROR(INDEX(_xlfn.SORTBY(_xlfn._xlws.FILTER('Project Portfolio'!B$4:B$43,('Project Portfolio'!F$4:F$43<>"✅ COMPLETE")*('Project Portfolio'!F$4:F$43<>"🚫 NOT APPROVED")*('Project Portfolio'!F$4:F$43<>"⏸️ POSTPONED")*('Project Portfolio'!A$4:A$43<>"")),_xlfn._xlws.FILTER(IF('Project Portfolio'!J$4:J$43=0,99999,'Project Portfolio'!J$4:J$43),('Project Portfolio'!F$4:F$43<>"✅ COMPLETE")*('Project Portfolio'!F$4:F$43<>"🚫 NOT APPROVED")*('Project Portfolio'!F$4:F$43<>"⏸️ POSTPONED")*('Project Portfolio'!A$4:A$43<>"")),1),ROW()-4),"")} | D22: {=IFERROR(INDEX(_xlfn.SORTBY(_xlfn._xlws.FILTER('Project Portfolio'!F$4:F$43,('Project Portfolio'!F$4:F$43<>"✅ COMPLETE")*('Project Portfolio'!F$4:F$43<>"🚫 NOT APPROVED")*('Project Portfolio'!F$4:F$43<>"⏸️ POSTPONED")*('Project Portfolio'!A$4:A$43<>"")),_xlfn._xlws.FILTER(IF('Project Portfolio'!J$4:J$43=0,99999,'Project Portfolio'!J$4:J$43),('Project Portfolio'!F$4:F$43<>"✅ COMPLETE")*('Project Portfolio'!F$4:F$43<>"🚫 NOT APPROVED")*('Project Portfolio'!F$4:F$43<>"⏸️ POSTPONED")*('Project Portfolio'!A$4:A$43<>"")),1),ROW()-4),"")} | E22: {=IFERROR(IF(INDEX(_xlfn.SORTBY(_xlfn._xlws.FILTER('Project Portfolio'!I$4:I$43,('Project Portfolio'!F$4:F$43<>"✅ COMPLETE")*('Project Portfolio'!F$4:F$43<>"🚫 NOT APPROVED")*('Project Portfolio'!F$4:F$43<>"⏸️ POSTPONED")*('Project Portfolio'!A$4:A$43<>"")),_xlfn._xlws.FILTER(IF('Project Portfolio'!J$4:J$43=0,99999,'Project Portfolio'!J$4:J$43),('Project Portfolio'!F$4:F$43<>"✅ COMPLETE")*('Project Portfolio'!F$4:F$43<>"🚫 NOT APPROVED")*('Project Portfolio'!F$4:F$43<>"⏸️ POSTPONED")*('Project Portfolio'!A$4:A$43<>"")),1),ROW()-4)=0,"",INDEX(_xlfn.SORTBY(_xlfn._xlws.FILTER('Project Portfolio'!I$4:I$43,('Project Portfolio'!F$4:F$43<>"✅ COMPLETE")*('Project Portfolio'!F$4:F$43<>"🚫 NOT APPROVED")*('Project Portfolio'!F$4:F$43<>"⏸️ POSTPONED")*('Project Portfolio'!A$4:A$43<>"")),_xlfn._xlws.FILTER(IF('Project Portfolio'!J$4:J$43=0,99999,'Project Portfolio'!J$4:J$43),('Project Portfolio'!F$4:F$43<>"✅ COMPLETE")*('Project Portfolio'!F$4:F$43<>"🚫 NOT APPROVED")*('Project Portfolio'!F$4:F$43<>"⏸️ POSTPONED")*('Project Portfolio'!A$4:A$43<>"")),1),ROW()-4)),"")} | F22: {=IFERROR(IF(INDEX(_xlfn.SORTBY(_xlfn._xlws.FILTER('Project Portfolio'!J$4:J$43,('Project Portfolio'!F$4:F$43<>"✅ COMPLETE")*('Project Portfolio'!F$4:F$43<>"🚫 NOT APPROVED")*('Project Portfolio'!F$4:F$43<>"⏸️ POSTPONED")*('Project Portfolio'!A$4:A$43<>"")),_xlfn._xlws.FILTER(IF('Project Portfolio'!J$4:J$43=0,99999,'Project Portfolio'!J$4:J$43),('Project Portfolio'!F$4:F$43<>"✅ COMPLETE")*('Project Portfolio'!F$4:F$43<>"🚫 NOT APPROVED")*('Project Portfolio'!F$4:F$43<>"⏸️ POSTPONED")*('Project Portfolio'!A$4:A$43<>"")),1),ROW()-4)=0,"",INDEX(_xlfn.SORTBY(_xlfn._xlws.FILTER('Project Portfolio'!J$4:J$43,('Project Portfolio'!F$4:F$43<>"✅ COMPLETE")*('Project Portfolio'!F$4:F$43<>"🚫 NOT APPROVED")*('Project Portfolio'!F$4:F$43<>"⏸️ POSTPONED")*('Project Portfolio'!A$4:A$43<>"")),_xlfn._xlws.FILTER(IF('Project Portfolio'!J$4:J$43=0,99999,'Project Portfolio'!J$4:J$43),('Project Portfolio'!F$4:F$43<>"✅ COMPLETE")*('Project Portfolio'!F$4:F$43<>"🚫 NOT APPROVED")*('Project Portfolio'!F$4:F$43<>"⏸️ POSTPONED")*('Project Portfolio'!A$4:A$43<>"")),1),ROW()-4)),"")} | G22: =IF(AND($E22>0,$F22>0,G$4+6>=$E22,G$4<=$F22),1,"") | H22: =IF(AND($E22>0,$F22>0,H$4+6>=$E22,H$4<=$F22),1,"") | I22: =IF(AND($E22>0,$F22>0,I$4+6>=$E22,I$4<=$F22),1,"") | J22: =IF(AND($E22>0,$F22>0,J$4+6>=$E22,J$4<=$F22),1,"") | K22: =IF(AND($E22>0,$F22>0,K$4+6>=$E22,K$4<=$F22),1,"") | L22: =IF(AND($E22>0,$F22>0,L$4+6>=$E22,L$4<=$F22),1,"") | M22: =IF(AND($E22>0,$F22>0,M$4+6>=$E22,M$4<=$F22),1,"") | N22: =IF(AND($E22>0,$F22>0,N$4+6>=$E22,N$4<=$F22),1,"") | ... BF22: =IF(AND($E22>0,$F22>0,BF$4+6>=$E22,BF$4<=$F22),1,"")
B23: {=IFERROR(INDEX(_xlfn.SORTBY(_xlfn._xlws.FILTER('Project Portfolio'!A$4:A$43,('Project Portfolio'!F$4:F$43<>"✅ COMPLETE")*('Project Portfolio'!F$4:F$43<>"🚫 NOT APPROVED")*('Project Portfolio'!F$4:F$43<>"⏸️ POSTPONED")*('Project Portfolio'!A$4:A$43<>"")),_xlfn._xlws.FILTER(IF('Project Portfolio'!J$4:J$43=0,99999,'Project Portfolio'!J$4:J$43),('Project Portfolio'!F$4:F$43<>"✅ COMPLETE")*('Project Portfolio'!F$4:F$43<>"🚫 NOT APPROVED")*('Project Portfolio'!F$4:F$43<>"⏸️ POSTPONED")*('Project Portfolio'!A$4:A$43<>"")),1),ROW()-4),"")} | C23: {=IFERROR(INDEX(_xlfn.SORTBY(_xlfn._xlws.FILTER('Project Portfolio'!B$4:B$43,('Project Portfolio'!F$4:F$43<>"✅ COMPLETE")*('Project Portfolio'!F$4:F$43<>"🚫 NOT APPROVED")*('Project Portfolio'!F$4:F$43<>"⏸️ POSTPONED")*('Project Portfolio'!A$4:A$43<>"")),_xlfn._xlws.FILTER(IF('Project Portfolio'!J$4:J$43=0,99999,'Project Portfolio'!J$4:J$43),('Project Portfolio'!F$4:F$43<>"✅ COMPLETE")*('Project Portfolio'!F$4:F$43<>"🚫 NOT APPROVED")*('Project Portfolio'!F$4:F$43<>"⏸️ POSTPONED")*('Project Portfolio'!A$4:A$43<>"")),1),ROW()-4),"")} | D23: {=IFERROR(INDEX(_xlfn.SORTBY(_xlfn._xlws.FILTER('Project Portfolio'!F$4:F$43,('Project Portfolio'!F$4:F$43<>"✅ COMPLETE")*('Project Portfolio'!F$4:F$43<>"🚫 NOT APPROVED")*('Project Portfolio'!F$4:F$43<>"⏸️ POSTPONED")*('Project Portfolio'!A$4:A$43<>"")),_xlfn._xlws.FILTER(IF('Project Portfolio'!J$4:J$43=0,99999,'Project Portfolio'!J$4:J$43),('Project Portfolio'!F$4:F$43<>"✅ COMPLETE")*('Project Portfolio'!F$4:F$43<>"🚫 NOT APPROVED")*('Project Portfolio'!F$4:F$43<>"⏸️ POSTPONED")*('Project Portfolio'!A$4:A$43<>"")),1),ROW()-4),"")} | E23: {=IFERROR(IF(INDEX(_xlfn.SORTBY(_xlfn._xlws.FILTER('Project Portfolio'!I$4:I$43,('Project Portfolio'!F$4:F$43<>"✅ COMPLETE")*('Project Portfolio'!F$4:F$43<>"🚫 NOT APPROVED")*('Project Portfolio'!F$4:F$43<>"⏸️ POSTPONED")*('Project Portfolio'!A$4:A$43<>"")),_xlfn._xlws.FILTER(IF('Project Portfolio'!J$4:J$43=0,99999,'Project Portfolio'!J$4:J$43),('Project Portfolio'!F$4:F$43<>"✅ COMPLETE")*('Project Portfolio'!F$4:F$43<>"🚫 NOT APPROVED")*('Project Portfolio'!F$4:F$43<>"⏸️ POSTPONED")*('Project Portfolio'!A$4:A$43<>"")),1),ROW()-4)=0,"",INDEX(_xlfn.SORTBY(_xlfn._xlws.FILTER('Project Portfolio'!I$4:I$43,('Project Portfolio'!F$4:F$43<>"✅ COMPLETE")*('Project Portfolio'!F$4:F$43<>"🚫 NOT APPROVED")*('Project Portfolio'!F$4:F$43<>"⏸️ POSTPONED")*('Project Portfolio'!A$4:A$43<>"")),_xlfn._xlws.FILTER(IF('Project Portfolio'!J$4:J$43=0,99999,'Project Portfolio'!J$4:J$43),('Project Portfolio'!F$4:F$43<>"✅ COMPLETE")*('Project Portfolio'!F$4:F$43<>"🚫 NOT APPROVED")*('Project Portfolio'!F$4:F$43<>"⏸️ POSTPONED")*('Project Portfolio'!A$4:A$43<>"")),1),ROW()-4)),"")} | F23: {=IFERROR(IF(INDEX(_xlfn.SORTBY(_xlfn._xlws.FILTER('Project Portfolio'!J$4:J$43,('Project Portfolio'!F$4:F$43<>"✅ COMPLETE")*('Project Portfolio'!F$4:F$43<>"🚫 NOT APPROVED")*('Project Portfolio'!F$4:F$43<>"⏸️ POSTPONED")*('Project Portfolio'!A$4:A$43<>"")),_xlfn._xlws.FILTER(IF('Project Portfolio'!J$4:J$43=0,99999,'Project Portfolio'!J$4:J$43),('Project Portfolio'!F$4:F$43<>"✅ COMPLETE")*('Project Portfolio'!F$4:F$43<>"🚫 NOT APPROVED")*('Project Portfolio'!F$4:F$43<>"⏸️ POSTPONED")*('Project Portfolio'!A$4:A$43<>"")),1),ROW()-4)=0,"",INDEX(_xlfn.SORTBY(_xlfn._xlws.FILTER('Project Portfolio'!J$4:J$43,('Project Portfolio'!F$4:F$43<>"✅ COMPLETE")*('Project Portfolio'!F$4:F$43<>"🚫 NOT APPROVED")*('Project Portfolio'!F$4:F$43<>"⏸️ POSTPONED")*('Project Portfolio'!A$4:A$43<>"")),_xlfn._xlws.FILTER(IF('Project Portfolio'!J$4:J$43=0,99999,'Project Portfolio'!J$4:J$43),('Project Portfolio'!F$4:F$43<>"✅ COMPLETE")*('Project Portfolio'!F$4:F$43<>"🚫 NOT APPROVED")*('Project Portfolio'!F$4:F$43<>"⏸️ POSTPONED")*('Project Portfolio'!A$4:A$43<>"")),1),ROW()-4)),"")} | G23: =IF(AND($E23>0,$F23>0,G$4+6>=$E23,G$4<=$F23),1,"") | H23: =IF(AND($E23>0,$F23>0,H$4+6>=$E23,H$4<=$F23),1,"") | I23: =IF(AND($E23>0,$F23>0,I$4+6>=$E23,I$4<=$F23),1,"") | J23: =IF(AND($E23>0,$F23>0,J$4+6>=$E23,J$4<=$F23),1,"") | K23: =IF(AND($E23>0,$F23>0,K$4+6>=$E23,K$4<=$F23),1,"") | L23: =IF(AND($E23>0,$F23>0,L$4+6>=$E23,L$4<=$F23),1,"") | M23: =IF(AND($E23>0,$F23>0,M$4+6>=$E23,M$4<=$F23),1,"") | N23: =IF(AND($E23>0,$F23>0,N$4+6>=$E23,N$4<=$F23),1,"") | ... BF23: =IF(AND($E23>0,$F23>0,BF$4+6>=$E23,BF$4<=$F23),1,"")
B24: {=IFERROR(INDEX(_xlfn.SORTBY(_xlfn._xlws.FILTER('Project Portfolio'!A$4:A$43,('Project Portfolio'!F$4:F$43<>"✅ COMPLETE")*('Project Portfolio'!F$4:F$43<>"🚫 NOT APPROVED")*('Project Portfolio'!F$4:F$43<>"⏸️ POSTPONED")*('Project Portfolio'!A$4:A$43<>"")),_xlfn._xlws.FILTER(IF('Project Portfolio'!J$4:J$43=0,99999,'Project Portfolio'!J$4:J$43),('Project Portfolio'!F$4:F$43<>"✅ COMPLETE")*('Project Portfolio'!F$4:F$43<>"🚫 NOT APPROVED")*('Project Portfolio'!F$4:F$43<>"⏸️ POSTPONED")*('Project Portfolio'!A$4:A$43<>"")),1),ROW()-4),"")} | C24: {=IFERROR(INDEX(_xlfn.SORTBY(_xlfn._xlws.FILTER('Project Portfolio'!B$4:B$43,('Project Portfolio'!F$4:F$43<>"✅ COMPLETE")*('Project Portfolio'!F$4:F$43<>"🚫 NOT APPROVED")*('Project Portfolio'!F$4:F$43<>"⏸️ POSTPONED")*('Project Portfolio'!A$4:A$43<>"")),_xlfn._xlws.FILTER(IF('Project Portfolio'!J$4:J$43=0,99999,'Project Portfolio'!J$4:J$43),('Project Portfolio'!F$4:F$43<>"✅ COMPLETE")*('Project Portfolio'!F$4:F$43<>"🚫 NOT APPROVED")*('Project Portfolio'!F$4:F$43<>"⏸️ POSTPONED")*('Project Portfolio'!A$4:A$43<>"")),1),ROW()-4),"")} | D24: {=IFERROR(INDEX(_xlfn.SORTBY(_xlfn._xlws.FILTER('Project Portfolio'!F$4:F$43,('Project Portfolio'!F$4:F$43<>"✅ COMPLETE")*('Project Portfolio'!F$4:F$43<>"🚫 NOT APPROVED")*('Project Portfolio'!F$4:F$43<>"⏸️ POSTPONED")*('Project Portfolio'!A$4:A$43<>"")),_xlfn._xlws.FILTER(IF('Project Portfolio'!J$4:J$43=0,99999,'Project Portfolio'!J$4:J$43),('Project Portfolio'!F$4:F$43<>"✅ COMPLETE")*('Project Portfolio'!F$4:F$43<>"🚫 NOT APPROVED")*('Project Portfolio'!F$4:F$43<>"⏸️ POSTPONED")*('Project Portfolio'!A$4:A$43<>"")),1),ROW()-4),"")} | E24: {=IFERROR(IF(INDEX(_xlfn.SORTBY(_xlfn._xlws.FILTER('Project Portfolio'!I$4:I$43,('Project Portfolio'!F$4:F$43<>"✅ COMPLETE")*('Project Portfolio'!F$4:F$43<>"🚫 NOT APPROVED")*('Project Portfolio'!F$4:F$43<>"⏸️ POSTPONED")*('Project Portfolio'!A$4:A$43<>"")),_xlfn._xlws.FILTER(IF('Project Portfolio'!J$4:J$43=0,99999,'Project Portfolio'!J$4:J$43),('Project Portfolio'!F$4:F$43<>"✅ COMPLETE")*('Project Portfolio'!F$4:F$43<>"🚫 NOT APPROVED")*('Project Portfolio'!F$4:F$43<>"⏸️ POSTPONED")*('Project Portfolio'!A$4:A$43<>"")),1),ROW()-4)=0,"",INDEX(_xlfn.SORTBY(_xlfn._xlws.FILTER('Project Portfolio'!I$4:I$43,('Project Portfolio'!F$4:F$43<>"✅ COMPLETE")*('Project Portfolio'!F$4:F$43<>"🚫 NOT APPROVED")*('Project Portfolio'!F$4:F$43<>"⏸️ POSTPONED")*('Project Portfolio'!A$4:A$43<>"")),_xlfn._xlws.FILTER(IF('Project Portfolio'!J$4:J$43=0,99999,'Project Portfolio'!J$4:J$43),('Project Portfolio'!F$4:F$43<>"✅ COMPLETE")*('Project Portfolio'!F$4:F$43<>"🚫 NOT APPROVED")*('Project Portfolio'!F$4:F$43<>"⏸️ POSTPONED")*('Project Portfolio'!A$4:A$43<>"")),1),ROW()-4)),"")} | F24: {=IFERROR(IF(INDEX(_xlfn.SORTBY(_xlfn._xlws.FILTER('Project Portfolio'!J$4:J$43,('Project Portfolio'!F$4:F$43<>"✅ COMPLETE")*('Project Portfolio'!F$4:F$43<>"🚫 NOT APPROVED")*('Project Portfolio'!F$4:F$43<>"⏸️ POSTPONED")*('Project Portfolio'!A$4:A$43<>"")),_xlfn._xlws.FILTER(IF('Project Portfolio'!J$4:J$43=0,99999,'Project Portfolio'!J$4:J$43),('Project Portfolio'!F$4:F$43<>"✅ COMPLETE")*('Project Portfolio'!F$4:F$43<>"🚫 NOT APPROVED")*('Project Portfolio'!F$4:F$43<>"⏸️ POSTPONED")*('Project Portfolio'!A$4:A$43<>"")),1),ROW()-4)=0,"",INDEX(_xlfn.SORTBY(_xlfn._xlws.FILTER('Project Portfolio'!J$4:J$43,('Project Portfolio'!F$4:F$43<>"✅ COMPLETE")*('Project Portfolio'!F$4:F$43<>"🚫 NOT APPROVED")*('Project Portfolio'!F$4:F$43<>"⏸️ POSTPONED")*('Project Portfolio'!A$4:A$43<>"")),_xlfn._xlws.FILTER(IF('Project Portfolio'!J$4:J$43=0,99999,'Project Portfolio'!J$4:J$43),('Project Portfolio'!F$4:F$43<>"✅ COMPLETE")*('Project Portfolio'!F$4:F$43<>"🚫 NOT APPROVED")*('Project Portfolio'!F$4:F$43<>"⏸️ POSTPONED")*('Project Portfolio'!A$4:A$43<>"")),1),ROW()-4)),"")} | G24: =IF(AND($E24>0,$F24>0,G$4+6>=$E24,G$4<=$F24),1,"") | H24: =IF(AND($E24>0,$F24>0,H$4+6>=$E24,H$4<=$F24),1,"") | I24: =IF(AND($E24>0,$F24>0,I$4+6>=$E24,I$4<=$F24),1,"") | J24: =IF(AND($E24>0,$F24>0,J$4+6>=$E24,J$4<=$F24),1,"") | K24: =IF(AND($E24>0,$F24>0,K$4+6>=$E24,K$4<=$F24),1,"") | L24: =IF(AND($E24>0,$F24>0,L$4+6>=$E24,L$4<=$F24),1,"") | M24: =IF(AND($E24>0,$F24>0,M$4+6>=$E24,M$4<=$F24),1,"") | N24: =IF(AND($E24>0,$F24>0,N$4+6>=$E24,N$4<=$F24),1,"") | ... BF24: =IF(AND($E24>0,$F24>0,BF$4+6>=$E24,BF$4<=$F24),1,"")
B25: {=IFERROR(INDEX(_xlfn.SORTBY(_xlfn._xlws.FILTER('Project Portfolio'!A$4:A$43,('Project Portfolio'!F$4:F$43<>"✅ COMPLETE")*('Project Portfolio'!F$4:F$43<>"🚫 NOT APPROVED")*('Project Portfolio'!F$4:F$43<>"⏸️ POSTPONED")*('Project Portfolio'!A$4:A$43<>"")),_xlfn._xlws.FILTER(IF('Project Portfolio'!J$4:J$43=0,99999,'Project Portfolio'!J$4:J$43),('Project Portfolio'!F$4:F$43<>"✅ COMPLETE")*('Project Portfolio'!F$4:F$43<>"🚫 NOT APPROVED")*('Project Portfolio'!F$4:F$43<>"⏸️ POSTPONED")*('Project Portfolio'!A$4:A$43<>"")),1),ROW()-4),"")} | C25: {=IFERROR(INDEX(_xlfn.SORTBY(_xlfn._xlws.FILTER('Project Portfolio'!B$4:B$43,('Project Portfolio'!F$4:F$43<>"✅ COMPLETE")*('Project Portfolio'!F$4:F$43<>"🚫 NOT APPROVED")*('Project Portfolio'!F$4:F$43<>"⏸️ POSTPONED")*('Project Portfolio'!A$4:A$43<>"")),_xlfn._xlws.FILTER(IF('Project Portfolio'!J$4:J$43=0,99999,'Project Portfolio'!J$4:J$43),('Project Portfolio'!F$4:F$43<>"✅ COMPLETE")*('Project Portfolio'!F$4:F$43<>"🚫 NOT APPROVED")*('Project Portfolio'!F$4:F$43<>"⏸️ POSTPONED")*('Project Portfolio'!A$4:A$43<>"")),1),ROW()-4),"")} | D25: {=IFERROR(INDEX(_xlfn.SORTBY(_xlfn._xlws.FILTER('Project Portfolio'!F$4:F$43,('Project Portfolio'!F$4:F$43<>"✅ COMPLETE")*('Project Portfolio'!F$4:F$43<>"🚫 NOT APPROVED")*('Project Portfolio'!F$4:F$43<>"⏸️ POSTPONED")*('Project Portfolio'!A$4:A$43<>"")),_xlfn._xlws.FILTER(IF('Project Portfolio'!J$4:J$43=0,99999,'Project Portfolio'!J$4:J$43),('Project Portfolio'!F$4:F$43<>"✅ COMPLETE")*('Project Portfolio'!F$4:F$43<>"🚫 NOT APPROVED")*('Project Portfolio'!F$4:F$43<>"⏸️ POSTPONED")*('Project Portfolio'!A$4:A$43<>"")),1),ROW()-4),"")} | E25: {=IFERROR(IF(INDEX(_xlfn.SORTBY(_xlfn._xlws.FILTER('Project Portfolio'!I$4:I$43,('Project Portfolio'!F$4:F$43<>"✅ COMPLETE")*('Project Portfolio'!F$4:F$43<>"🚫 NOT APPROVED")*('Project Portfolio'!F$4:F$43<>"⏸️ POSTPONED")*('Project Portfolio'!A$4:A$43<>"")),_xlfn._xlws.FILTER(IF('Project Portfolio'!J$4:J$43=0,99999,'Project Portfolio'!J$4:J$43),('Project Portfolio'!F$4:F$43<>"✅ COMPLETE")*('Project Portfolio'!F$4:F$43<>"🚫 NOT APPROVED")*('Project Portfolio'!F$4:F$43<>"⏸️ POSTPONED")*('Project Portfolio'!A$4:A$43<>"")),1),ROW()-4)=0,"",INDEX(_xlfn.SORTBY(_xlfn._xlws.FILTER('Project Portfolio'!I$4:I$43,('Project Portfolio'!F$4:F$43<>"✅ COMPLETE")*('Project Portfolio'!F$4:F$43<>"🚫 NOT APPROVED")*('Project Portfolio'!F$4:F$43<>"⏸️ POSTPONED")*('Project Portfolio'!A$4:A$43<>"")),_xlfn._xlws.FILTER(IF('Project Portfolio'!J$4:J$43=0,99999,'Project Portfolio'!J$4:J$43),('Project Portfolio'!F$4:F$43<>"✅ COMPLETE")*('Project Portfolio'!F$4:F$43<>"🚫 NOT APPROVED")*('Project Portfolio'!F$4:F$43<>"⏸️ POSTPONED")*('Project Portfolio'!A$4:A$43<>"")),1),ROW()-4)),"")} | F25: {=IFERROR(IF(INDEX(_xlfn.SORTBY(_xlfn._xlws.FILTER('Project Portfolio'!J$4:J$43,('Project Portfolio'!F$4:F$43<>"✅ COMPLETE")*('Project Portfolio'!F$4:F$43<>"🚫 NOT APPROVED")*('Project Portfolio'!F$4:F$43<>"⏸️ POSTPONED")*('Project Portfolio'!A$4:A$43<>"")),_xlfn._xlws.FILTER(IF('Project Portfolio'!J$4:J$43=0,99999,'Project Portfolio'!J$4:J$43),('Project Portfolio'!F$4:F$43<>"✅ COMPLETE")*('Project Portfolio'!F$4:F$43<>"🚫 NOT APPROVED")*('Project Portfolio'!F$4:F$43<>"⏸️ POSTPONED")*('Project Portfolio'!A$4:A$43<>"")),1),ROW()-4)=0,"",INDEX(_xlfn.SORTBY(_xlfn._xlws.FILTER('Project Portfolio'!J$4:J$43,('Project Portfolio'!F$4:F$43<>"✅ COMPLETE")*('Project Portfolio'!F$4:F$43<>"🚫 NOT APPROVED")*('Project Portfolio'!F$4:F$43<>"⏸️ POSTPONED")*('Project Portfolio'!A$4:A$43<>"")),_xlfn._xlws.FILTER(IF('Project Portfolio'!J$4:J$43=0,99999,'Project Portfolio'!J$4:J$43),('Project Portfolio'!F$4:F$43<>"✅ COMPLETE")*('Project Portfolio'!F$4:F$43<>"🚫 NOT APPROVED")*('Project Portfolio'!F$4:F$43<>"⏸️ POSTPONED")*('Project Portfolio'!A$4:A$43<>"")),1),ROW()-4)),"")} | G25: =IF(AND($E25>0,$F25>0,G$4+6>=$E25,G$4<=$F25),1,"") | H25: =IF(AND($E25>0,$F25>0,H$4+6>=$E25,H$4<=$F25),1,"") | I25: =IF(AND($E25>0,$F25>0,I$4+6>=$E25,I$4<=$F25),1,"") | J25: =IF(AND($E25>0,$F25>0,J$4+6>=$E25,J$4<=$F25),1,"") | K25: =IF(AND($E25>0,$F25>0,K$4+6>=$E25,K$4<=$F25),1,"") | L25: =IF(AND($E25>0,$F25>0,L$4+6>=$E25,L$4<=$F25),1,"") | M25: =IF(AND($E25>0,$F25>0,M$4+6>=$E25,M$4<=$F25),1,"") | N25: =IF(AND($E25>0,$F25>0,N$4+6>=$E25,N$4<=$F25),1,"") | ... BF25: =IF(AND($E25>0,$F25>0,BF$4+6>=$E25,BF$4<=$F25),1,"")
B26: {=IFERROR(INDEX(_xlfn.SORTBY(_xlfn._xlws.FILTER('Project Portfolio'!A$4:A$43,('Project Portfolio'!F$4:F$43<>"✅ COMPLETE")*('Project Portfolio'!F$4:F$43<>"🚫 NOT APPROVED")*('Project Portfolio'!F$4:F$43<>"⏸️ POSTPONED")*('Project Portfolio'!A$4:A$43<>"")),_xlfn._xlws.FILTER(IF('Project Portfolio'!J$4:J$43=0,99999,'Project Portfolio'!J$4:J$43),('Project Portfolio'!F$4:F$43<>"✅ COMPLETE")*('Project Portfolio'!F$4:F$43<>"🚫 NOT APPROVED")*('Project Portfolio'!F$4:F$43<>"⏸️ POSTPONED")*('Project Portfolio'!A$4:A$43<>"")),1),ROW()-4),"")} | C26: {=IFERROR(INDEX(_xlfn.SORTBY(_xlfn._xlws.FILTER('Project Portfolio'!B$4:B$43,('Project Portfolio'!F$4:F$43<>"✅ COMPLETE")*('Project Portfolio'!F$4:F$43<>"🚫 NOT APPROVED")*('Project Portfolio'!F$4:F$43<>"⏸️ POSTPONED")*('Project Portfolio'!A$4:A$43<>"")),_xlfn._xlws.FILTER(IF('Project Portfolio'!J$4:J$43=0,99999,'Project Portfolio'!J$4:J$43),('Project Portfolio'!F$4:F$43<>"✅ COMPLETE")*('Project Portfolio'!F$4:F$43<>"🚫 NOT APPROVED")*('Project Portfolio'!F$4:F$43<>"⏸️ POSTPONED")*('Project Portfolio'!A$4:A$43<>"")),1),ROW()-4),"")} | D26: {=IFERROR(INDEX(_xlfn.SORTBY(_xlfn._xlws.FILTER('Project Portfolio'!F$4:F$43,('Project Portfolio'!F$4:F$43<>"✅ COMPLETE")*('Project Portfolio'!F$4:F$43<>"🚫 NOT APPROVED")*('Project Portfolio'!F$4:F$43<>"⏸️ POSTPONED")*('Project Portfolio'!A$4:A$43<>"")),_xlfn._xlws.FILTER(IF('Project Portfolio'!J$4:J$43=0,99999,'Project Portfolio'!J$4:J$43),('Project Portfolio'!F$4:F$43<>"✅ COMPLETE")*('Project Portfolio'!F$4:F$43<>"🚫 NOT APPROVED")*('Project Portfolio'!F$4:F$43<>"⏸️ POSTPONED")*('Project Portfolio'!A$4:A$43<>"")),1),ROW()-4),"")} | E26: {=IFERROR(IF(INDEX(_xlfn.SORTBY(_xlfn._xlws.FILTER('Project Portfolio'!I$4:I$43,('Project Portfolio'!F$4:F$43<>"✅ COMPLETE")*('Project Portfolio'!F$4:F$43<>"🚫 NOT APPROVED")*('Project Portfolio'!F$4:F$43<>"⏸️ POSTPONED")*('Project Portfolio'!A$4:A$43<>"")),_xlfn._xlws.FILTER(IF('Project Portfolio'!J$4:J$43=0,99999,'Project Portfolio'!J$4:J$43),('Project Portfolio'!F$4:F$43<>"✅ COMPLETE")*('Project Portfolio'!F$4:F$43<>"🚫 NOT APPROVED")*('Project Portfolio'!F$4:F$43<>"⏸️ POSTPONED")*('Project Portfolio'!A$4:A$43<>"")),1),ROW()-4)=0,"",INDEX(_xlfn.SORTBY(_xlfn._xlws.FILTER('Project Portfolio'!I$4:I$43,('Project Portfolio'!F$4:F$43<>"✅ COMPLETE")*('Project Portfolio'!F$4:F$43<>"🚫 NOT APPROVED")*('Project Portfolio'!F$4:F$43<>"⏸️ POSTPONED")*('Project Portfolio'!A$4:A$43<>"")),_xlfn._xlws.FILTER(IF('Project Portfolio'!J$4:J$43=0,99999,'Project Portfolio'!J$4:J$43),('Project Portfolio'!F$4:F$43<>"✅ COMPLETE")*('Project Portfolio'!F$4:F$43<>"🚫 NOT APPROVED")*('Project Portfolio'!F$4:F$43<>"⏸️ POSTPONED")*('Project Portfolio'!A$4:A$43<>"")),1),ROW()-4)),"")} | F26: {=IFERROR(IF(INDEX(_xlfn.SORTBY(_xlfn._xlws.FILTER('Project Portfolio'!J$4:J$43,('Project Portfolio'!F$4:F$43<>"✅ COMPLETE")*('Project Portfolio'!F$4:F$43<>"🚫 NOT APPROVED")*('Project Portfolio'!F$4:F$43<>"⏸️ POSTPONED")*('Project Portfolio'!A$4:A$43<>"")),_xlfn._xlws.FILTER(IF('Project Portfolio'!J$4:J$43=0,99999,'Project Portfolio'!J$4:J$43),('Project Portfolio'!F$4:F$43<>"✅ COMPLETE")*('Project Portfolio'!F$4:F$43<>"🚫 NOT APPROVED")*('Project Portfolio'!F$4:F$43<>"⏸️ POSTPONED")*('Project Portfolio'!A$4:A$43<>"")),1),ROW()-4)=0,"",INDEX(_xlfn.SORTBY(_xlfn._xlws.FILTER('Project Portfolio'!J$4:J$43,('Project Portfolio'!F$4:F$43<>"✅ COMPLETE")*('Project Portfolio'!F$4:F$43<>"🚫 NOT APPROVED")*('Project Portfolio'!F$4:F$43<>"⏸️ POSTPONED")*('Project Portfolio'!A$4:A$43<>"")),_xlfn._xlws.FILTER(IF('Project Portfolio'!J$4:J$43=0,99999,'Project Portfolio'!J$4:J$43),('Project Portfolio'!F$4:F$43<>"✅ COMPLETE")*('Project Portfolio'!F$4:F$43<>"🚫 NOT APPROVED")*('Project Portfolio'!F$4:F$43<>"⏸️ POSTPONED")*('Project Portfolio'!A$4:A$43<>"")),1),ROW()-4)),"")} | G26: =IF(AND($E26>0,$F26>0,G$4+6>=$E26,G$4<=$F26),1,"") | H26: =IF(AND($E26>0,$F26>0,H$4+6>=$E26,H$4<=$F26),1,"") | I26: =IF(AND($E26>0,$F26>0,I$4+6>=$E26,I$4<=$F26),1,"") | J26: =IF(AND($E26>0,$F26>0,J$4+6>=$E26,J$4<=$F26),1,"") | K26: =IF(AND($E26>0,$F26>0,K$4+6>=$E26,K$4<=$F26),1,"") | L26: =IF(AND($E26>0,$F26>0,L$4+6>=$E26,L$4<=$F26),1,"") | M26: =IF(AND($E26>0,$F26>0,M$4+6>=$E26,M$4<=$F26),1,"") | N26: =IF(AND($E26>0,$F26>0,N$4+6>=$E26,N$4<=$F26),1,"") | ... BF26: =IF(AND($E26>0,$F26>0,BF$4+6>=$E26,BF$4<=$F26),1,"")
B27: {=IFERROR(INDEX(_xlfn.SORTBY(_xlfn._xlws.FILTER('Project Portfolio'!A$4:A$43,('Project Portfolio'!F$4:F$43<>"✅ COMPLETE")*('Project Portfolio'!F$4:F$43<>"🚫 NOT APPROVED")*('Project Portfolio'!F$4:F$43<>"⏸️ POSTPONED")*('Project Portfolio'!A$4:A$43<>"")),_xlfn._xlws.FILTER(IF('Project Portfolio'!J$4:J$43=0,99999,'Project Portfolio'!J$4:J$43),('Project Portfolio'!F$4:F$43<>"✅ COMPLETE")*('Project Portfolio'!F$4:F$43<>"🚫 NOT APPROVED")*('Project Portfolio'!F$4:F$43<>"⏸️ POSTPONED")*('Project Portfolio'!A$4:A$43<>"")),1),ROW()-4),"")} | C27: {=IFERROR(INDEX(_xlfn.SORTBY(_xlfn._xlws.FILTER('Project Portfolio'!B$4:B$43,('Project Portfolio'!F$4:F$43<>"✅ COMPLETE")*('Project Portfolio'!F$4:F$43<>"🚫 NOT APPROVED")*('Project Portfolio'!F$4:F$43<>"⏸️ POSTPONED")*('Project Portfolio'!A$4:A$43<>"")),_xlfn._xlws.FILTER(IF('Project Portfolio'!J$4:J$43=0,99999,'Project Portfolio'!J$4:J$43),('Project Portfolio'!F$4:F$43<>"✅ COMPLETE")*('Project Portfolio'!F$4:F$43<>"🚫 NOT APPROVED")*('Project Portfolio'!F$4:F$43<>"⏸️ POSTPONED")*('Project Portfolio'!A$4:A$43<>"")),1),ROW()-4),"")} | D27: {=IFERROR(INDEX(_xlfn.SORTBY(_xlfn._xlws.FILTER('Project Portfolio'!F$4:F$43,('Project Portfolio'!F$4:F$43<>"✅ COMPLETE")*('Project Portfolio'!F$4:F$43<>"🚫 NOT APPROVED")*('Project Portfolio'!F$4:F$43<>"⏸️ POSTPONED")*('Project Portfolio'!A$4:A$43<>"")),_xlfn._xlws.FILTER(IF('Project Portfolio'!J$4:J$43=0,99999,'Project Portfolio'!J$4:J$43),('Project Portfolio'!F$4:F$43<>"✅ COMPLETE")*('Project Portfolio'!F$4:F$43<>"🚫 NOT APPROVED")*('Project Portfolio'!F$4:F$43<>"⏸️ POSTPONED")*('Project Portfolio'!A$4:A$43<>"")),1),ROW()-4),"")} | E27: {=IFERROR(IF(INDEX(_xlfn.SORTBY(_xlfn._xlws.FILTER('Project Portfolio'!I$4:I$43,('Project Portfolio'!F$4:F$43<>"✅ COMPLETE")*('Project Portfolio'!F$4:F$43<>"🚫 NOT APPROVED")*('Project Portfolio'!F$4:F$43<>"⏸️ POSTPONED")*('Project Portfolio'!A$4:A$43<>"")),_xlfn._xlws.FILTER(IF('Project Portfolio'!J$4:J$43=0,99999,'Project Portfolio'!J$4:J$43),('Project Portfolio'!F$4:F$43<>"✅ COMPLETE")*('Project Portfolio'!F$4:F$43<>"🚫 NOT APPROVED")*('Project Portfolio'!F$4:F$43<>"⏸️ POSTPONED")*('Project Portfolio'!A$4:A$43<>"")),1),ROW()-4)=0,"",INDEX(_xlfn.SORTBY(_xlfn._xlws.FILTER('Project Portfolio'!I$4:I$43,('Project Portfolio'!F$4:F$43<>"✅ COMPLETE")*('Project Portfolio'!F$4:F$43<>"🚫 NOT APPROVED")*('Project Portfolio'!F$4:F$43<>"⏸️ POSTPONED")*('Project Portfolio'!A$4:A$43<>"")),_xlfn._xlws.FILTER(IF('Project Portfolio'!J$4:J$43=0,99999,'Project Portfolio'!J$4:J$43),('Project Portfolio'!F$4:F$43<>"✅ COMPLETE")*('Project Portfolio'!F$4:F$43<>"🚫 NOT APPROVED")*('Project Portfolio'!F$4:F$43<>"⏸️ POSTPONED")*('Project Portfolio'!A$4:A$43<>"")),1),ROW()-4)),"")} | F27: {=IFERROR(IF(INDEX(_xlfn.SORTBY(_xlfn._xlws.FILTER('Project Portfolio'!J$4:J$43,('Project Portfolio'!F$4:F$43<>"✅ COMPLETE")*('Project Portfolio'!F$4:F$43<>"🚫 NOT APPROVED")*('Project Portfolio'!F$4:F$43<>"⏸️ POSTPONED")*('Project Portfolio'!A$4:A$43<>"")),_xlfn._xlws.FILTER(IF('Project Portfolio'!J$4:J$43=0,99999,'Project Portfolio'!J$4:J$43),('Project Portfolio'!F$4:F$43<>"✅ COMPLETE")*('Project Portfolio'!F$4:F$43<>"🚫 NOT APPROVED")*('Project Portfolio'!F$4:F$43<>"⏸️ POSTPONED")*('Project Portfolio'!A$4:A$43<>"")),1),ROW()-4)=0,"",INDEX(_xlfn.SORTBY(_xlfn._xlws.FILTER('Project Portfolio'!J$4:J$43,('Project Portfolio'!F$4:F$43<>"✅ COMPLETE")*('Project Portfolio'!F$4:F$43<>"🚫 NOT APPROVED")*('Project Portfolio'!F$4:F$43<>"⏸️ POSTPONED")*('Project Portfolio'!A$4:A$43<>"")),_xlfn._xlws.FILTER(IF('Project Portfolio'!J$4:J$43=0,99999,'Project Portfolio'!J$4:J$43),('Project Portfolio'!F$4:F$43<>"✅ COMPLETE")*('Project Portfolio'!F$4:F$43<>"🚫 NOT APPROVED")*('Project Portfolio'!F$4:F$43<>"⏸️ POSTPONED")*('Project Portfolio'!A$4:A$43<>"")),1),ROW()-4)),"")} | G27: =IF(AND($E27>0,$F27>0,G$4+6>=$E27,G$4<=$F27),1,"") | H27: =IF(AND($E27>0,$F27>0,H$4+6>=$E27,H$4<=$F27),1,"") | I27: =IF(AND($E27>0,$F27>0,I$4+6>=$E27,I$4<=$F27),1,"") | J27: =IF(AND($E27>0,$F27>0,J$4+6>=$E27,J$4<=$F27),1,"") | K27: =IF(AND($E27>0,$F27>0,K$4+6>=$E27,K$4<=$F27),1,"") | L27: =IF(AND($E27>0,$F27>0,L$4+6>=$E27,L$4<=$F27),1,"") | M27: =IF(AND($E27>0,$F27>0,M$4+6>=$E27,M$4<=$F27),1,"") | N27: =IF(AND($E27>0,$F27>0,N$4+6>=$E27,N$4<=$F27),1,"") | ... BF27: =IF(AND($E27>0,$F27>0,BF$4+6>=$E27,BF$4<=$F27),1,"")
B28: {=IFERROR(INDEX(_xlfn.SORTBY(_xlfn._xlws.FILTER('Project Portfolio'!A$4:A$43,('Project Portfolio'!F$4:F$43<>"✅ COMPLETE")*('Project Portfolio'!F$4:F$43<>"🚫 NOT APPROVED")*('Project Portfolio'!F$4:F$43<>"⏸️ POSTPONED")*('Project Portfolio'!A$4:A$43<>"")),_xlfn._xlws.FILTER(IF('Project Portfolio'!J$4:J$43=0,99999,'Project Portfolio'!J$4:J$43),('Project Portfolio'!F$4:F$43<>"✅ COMPLETE")*('Project Portfolio'!F$4:F$43<>"🚫 NOT APPROVED")*('Project Portfolio'!F$4:F$43<>"⏸️ POSTPONED")*('Project Portfolio'!A$4:A$43<>"")),1),ROW()-4),"")} | C28: {=IFERROR(INDEX(_xlfn.SORTBY(_xlfn._xlws.FILTER('Project Portfolio'!B$4:B$43,('Project Portfolio'!F$4:F$43<>"✅ COMPLETE")*('Project Portfolio'!F$4:F$43<>"🚫 NOT APPROVED")*('Project Portfolio'!F$4:F$43<>"⏸️ POSTPONED")*('Project Portfolio'!A$4:A$43<>"")),_xlfn._xlws.FILTER(IF('Project Portfolio'!J$4:J$43=0,99999,'Project Portfolio'!J$4:J$43),('Project Portfolio'!F$4:F$43<>"✅ COMPLETE")*('Project Portfolio'!F$4:F$43<>"🚫 NOT APPROVED")*('Project Portfolio'!F$4:F$43<>"⏸️ POSTPONED")*('Project Portfolio'!A$4:A$43<>"")),1),ROW()-4),"")} | D28: {=IFERROR(INDEX(_xlfn.SORTBY(_xlfn._xlws.FILTER('Project Portfolio'!F$4:F$43,('Project Portfolio'!F$4:F$43<>"✅ COMPLETE")*('Project Portfolio'!F$4:F$43<>"🚫 NOT APPROVED")*('Project Portfolio'!F$4:F$43<>"⏸️ POSTPONED")*('Project Portfolio'!A$4:A$43<>"")),_xlfn._xlws.FILTER(IF('Project Portfolio'!J$4:J$43=0,99999,'Project Portfolio'!J$4:J$43),('Project Portfolio'!F$4:F$43<>"✅ COMPLETE")*('Project Portfolio'!F$4:F$43<>"🚫 NOT APPROVED")*('Project Portfolio'!F$4:F$43<>"⏸️ POSTPONED")*('Project Portfolio'!A$4:A$43<>"")),1),ROW()-4),"")} | E28: {=IFERROR(IF(INDEX(_xlfn.SORTBY(_xlfn._xlws.FILTER('Project Portfolio'!I$4:I$43,('Project Portfolio'!F$4:F$43<>"✅ COMPLETE")*('Project Portfolio'!F$4:F$43<>"🚫 NOT APPROVED")*('Project Portfolio'!F$4:F$43<>"⏸️ POSTPONED")*('Project Portfolio'!A$4:A$43<>"")),_xlfn._xlws.FILTER(IF('Project Portfolio'!J$4:J$43=0,99999,'Project Portfolio'!J$4:J$43),('Project Portfolio'!F$4:F$43<>"✅ COMPLETE")*('Project Portfolio'!F$4:F$43<>"🚫 NOT APPROVED")*('Project Portfolio'!F$4:F$43<>"⏸️ POSTPONED")*('Project Portfolio'!A$4:A$43<>"")),1),ROW()-4)=0,"",INDEX(_xlfn.SORTBY(_xlfn._xlws.FILTER('Project Portfolio'!I$4:I$43,('Project Portfolio'!F$4:F$43<>"✅ COMPLETE")*('Project Portfolio'!F$4:F$43<>"🚫 NOT APPROVED")*('Project Portfolio'!F$4:F$43<>"⏸️ POSTPONED")*('Project Portfolio'!A$4:A$43<>"")),_xlfn._xlws.FILTER(IF('Project Portfolio'!J$4:J$43=0,99999,'Project Portfolio'!J$4:J$43),('Project Portfolio'!F$4:F$43<>"✅ COMPLETE")*('Project Portfolio'!F$4:F$43<>"🚫 NOT APPROVED")*('Project Portfolio'!F$4:F$43<>"⏸️ POSTPONED")*('Project Portfolio'!A$4:A$43<>"")),1),ROW()-4)),"")} | F28: {=IFERROR(IF(INDEX(_xlfn.SORTBY(_xlfn._xlws.FILTER('Project Portfolio'!J$4:J$43,('Project Portfolio'!F$4:F$43<>"✅ COMPLETE")*('Project Portfolio'!F$4:F$43<>"🚫 NOT APPROVED")*('Project Portfolio'!F$4:F$43<>"⏸️ POSTPONED")*('Project Portfolio'!A$4:A$43<>"")),_xlfn._xlws.FILTER(IF('Project Portfolio'!J$4:J$43=0,99999,'Project Portfolio'!J$4:J$43),('Project Portfolio'!F$4:F$43<>"✅ COMPLETE")*('Project Portfolio'!F$4:F$43<>"🚫 NOT APPROVED")*('Project Portfolio'!F$4:F$43<>"⏸️ POSTPONED")*('Project Portfolio'!A$4:A$43<>"")),1),ROW()-4)=0,"",INDEX(_xlfn.SORTBY(_xlfn._xlws.FILTER('Project Portfolio'!J$4:J$43,('Project Portfolio'!F$4:F$43<>"✅ COMPLETE")*('Project Portfolio'!F$4:F$43<>"🚫 NOT APPROVED")*('Project Portfolio'!F$4:F$43<>"⏸️ POSTPONED")*('Project Portfolio'!A$4:A$43<>"")),_xlfn._xlws.FILTER(IF('Project Portfolio'!J$4:J$43=0,99999,'Project Portfolio'!J$4:J$43),('Project Portfolio'!F$4:F$43<>"✅ COMPLETE")*('Project Portfolio'!F$4:F$43<>"🚫 NOT APPROVED")*('Project Portfolio'!F$4:F$43<>"⏸️ POSTPONED")*('Project Portfolio'!A$4:A$43<>"")),1),ROW()-4)),"")} | G28: =IF(AND($E28>0,$F28>0,G$4+6>=$E28,G$4<=$F28),1,"") | H28: =IF(AND($E28>0,$F28>0,H$4+6>=$E28,H$4<=$F28),1,"") | I28: =IF(AND($E28>0,$F28>0,I$4+6>=$E28,I$4<=$F28),1,"") | J28: =IF(AND($E28>0,$F28>0,J$4+6>=$E28,J$4<=$F28),1,"") | K28: =IF(AND($E28>0,$F28>0,K$4+6>=$E28,K$4<=$F28),1,"") | L28: =IF(AND($E28>0,$F28>0,L$4+6>=$E28,L$4<=$F28),1,"") | M28: =IF(AND($E28>0,$F28>0,M$4+6>=$E28,M$4<=$F28),1,"") | N28: =IF(AND($E28>0,$F28>0,N$4+6>=$E28,N$4<=$F28),1,"") | ... BF28: =IF(AND($E28>0,$F28>0,BF$4+6>=$E28,BF$4<=$F28),1,"")
B29: {=IFERROR(INDEX(_xlfn.SORTBY(_xlfn._xlws.FILTER('Project Portfolio'!A$4:A$43,('Project Portfolio'!F$4:F$43<>"✅ COMPLETE")*('Project Portfolio'!F$4:F$43<>"🚫 NOT APPROVED")*('Project Portfolio'!F$4:F$43<>"⏸️ POSTPONED")*('Project Portfolio'!A$4:A$43<>"")),_xlfn._xlws.FILTER(IF('Project Portfolio'!J$4:J$43=0,99999,'Project Portfolio'!J$4:J$43),('Project Portfolio'!F$4:F$43<>"✅ COMPLETE")*('Project Portfolio'!F$4:F$43<>"🚫 NOT APPROVED")*('Project Portfolio'!F$4:F$43<>"⏸️ POSTPONED")*('Project Portfolio'!A$4:A$43<>"")),1),ROW()-4),"")} | C29: {=IFERROR(INDEX(_xlfn.SORTBY(_xlfn._xlws.FILTER('Project Portfolio'!B$4:B$43,('Project Portfolio'!F$4:F$43<>"✅ COMPLETE")*('Project Portfolio'!F$4:F$43<>"🚫 NOT APPROVED")*('Project Portfolio'!F$4:F$43<>"⏸️ POSTPONED")*('Project Portfolio'!A$4:A$43<>"")),_xlfn._xlws.FILTER(IF('Project Portfolio'!J$4:J$43=0,99999,'Project Portfolio'!J$4:J$43),('Project Portfolio'!F$4:F$43<>"✅ COMPLETE")*('Project Portfolio'!F$4:F$43<>"🚫 NOT APPROVED")*('Project Portfolio'!F$4:F$43<>"⏸️ POSTPONED")*('Project Portfolio'!A$4:A$43<>"")),1),ROW()-4),"")} | D29: {=IFERROR(INDEX(_xlfn.SORTBY(_xlfn._xlws.FILTER('Project Portfolio'!F$4:F$43,('Project Portfolio'!F$4:F$43<>"✅ COMPLETE")*('Project Portfolio'!F$4:F$43<>"🚫 NOT APPROVED")*('Project Portfolio'!F$4:F$43<>"⏸️ POSTPONED")*('Project Portfolio'!A$4:A$43<>"")),_xlfn._xlws.FILTER(IF('Project Portfolio'!J$4:J$43=0,99999,'Project Portfolio'!J$4:J$43),('Project Portfolio'!F$4:F$43<>"✅ COMPLETE")*('Project Portfolio'!F$4:F$43<>"🚫 NOT APPROVED")*('Project Portfolio'!F$4:F$43<>"⏸️ POSTPONED")*('Project Portfolio'!A$4:A$43<>"")),1),ROW()-4),"")} | E29: {=IFERROR(IF(INDEX(_xlfn.SORTBY(_xlfn._xlws.FILTER('Project Portfolio'!I$4:I$43,('Project Portfolio'!F$4:F$43<>"✅ COMPLETE")*('Project Portfolio'!F$4:F$43<>"🚫 NOT APPROVED")*('Project Portfolio'!F$4:F$43<>"⏸️ POSTPONED")*('Project Portfolio'!A$4:A$43<>"")),_xlfn._xlws.FILTER(IF('Project Portfolio'!J$4:J$43=0,99999,'Project Portfolio'!J$4:J$43),('Project Portfolio'!F$4:F$43<>"✅ COMPLETE")*('Project Portfolio'!F$4:F$43<>"🚫 NOT APPROVED")*('Project Portfolio'!F$4:F$43<>"⏸️ POSTPONED")*('Project Portfolio'!A$4:A$43<>"")),1),ROW()-4)=0,"",INDEX(_xlfn.SORTBY(_xlfn._xlws.FILTER('Project Portfolio'!I$4:I$43,('Project Portfolio'!F$4:F$43<>"✅ COMPLETE")*('Project Portfolio'!F$4:F$43<>"🚫 NOT APPROVED")*('Project Portfolio'!F$4:F$43<>"⏸️ POSTPONED")*('Project Portfolio'!A$4:A$43<>"")),_xlfn._xlws.FILTER(IF('Project Portfolio'!J$4:J$43=0,99999,'Project Portfolio'!J$4:J$43),('Project Portfolio'!F$4:F$43<>"✅ COMPLETE")*('Project Portfolio'!F$4:F$43<>"🚫 NOT APPROVED")*('Project Portfolio'!F$4:F$43<>"⏸️ POSTPONED")*('Project Portfolio'!A$4:A$43<>"")),1),ROW()-4)),"")} | F29: {=IFERROR(IF(INDEX(_xlfn.SORTBY(_xlfn._xlws.FILTER('Project Portfolio'!J$4:J$43,('Project Portfolio'!F$4:F$43<>"✅ COMPLETE")*('Project Portfolio'!F$4:F$43<>"🚫 NOT APPROVED")*('Project Portfolio'!F$4:F$43<>"⏸️ POSTPONED")*('Project Portfolio'!A$4:A$43<>"")),_xlfn._xlws.FILTER(IF('Project Portfolio'!J$4:J$43=0,99999,'Project Portfolio'!J$4:J$43),('Project Portfolio'!F$4:F$43<>"✅ COMPLETE")*('Project Portfolio'!F$4:F$43<>"🚫 NOT APPROVED")*('Project Portfolio'!F$4:F$43<>"⏸️ POSTPONED")*('Project Portfolio'!A$4:A$43<>"")),1),ROW()-4)=0,"",INDEX(_xlfn.SORTBY(_xlfn._xlws.FILTER('Project Portfolio'!J$4:J$43,('Project Portfolio'!F$4:F$43<>"✅ COMPLETE")*('Project Portfolio'!F$4:F$43<>"🚫 NOT APPROVED")*('Project Portfolio'!F$4:F$43<>"⏸️ POSTPONED")*('Project Portfolio'!A$4:A$43<>"")),_xlfn._xlws.FILTER(IF('Project Portfolio'!J$4:J$43=0,99999,'Project Portfolio'!J$4:J$43),('Project Portfolio'!F$4:F$43<>"✅ COMPLETE")*('Project Portfolio'!F$4:F$43<>"🚫 NOT APPROVED")*('Project Portfolio'!F$4:F$43<>"⏸️ POSTPONED")*('Project Portfolio'!A$4:A$43<>"")),1),ROW()-4)),"")} | G29: =IF(AND($E29>0,$F29>0,G$4+6>=$E29,G$4<=$F29),1,"") | H29: =IF(AND($E29>0,$F29>0,H$4+6>=$E29,H$4<=$F29),1,"") | I29: =IF(AND($E29>0,$F29>0,I$4+6>=$E29,I$4<=$F29),1,"") | J29: =IF(AND($E29>0,$F29>0,J$4+6>=$E29,J$4<=$F29),1,"") | K29: =IF(AND($E29>0,$F29>0,K$4+6>=$E29,K$4<=$F29),1,"") | L29: =IF(AND($E29>0,$F29>0,L$4+6>=$E29,L$4<=$F29),1,"") | M29: =IF(AND($E29>0,$F29>0,M$4+6>=$E29,M$4<=$F29),1,"") | N29: =IF(AND($E29>0,$F29>0,N$4+6>=$E29,N$4<=$F29),1,"") | ... BF29: =IF(AND($E29>0,$F29>0,BF$4+6>=$E29,BF$4<=$F29),1,"")
... B33: {=IFERROR(INDEX(_xlfn.SORTBY(_xlfn._xlws.FILTER('Project Portfolio'!A$4:A$43,('Project Portfolio'!F$4:F$43<>"✅ COMPLETE")*('Project Portfolio'!F$4:F$43<>"🚫 NOT APPROVED")*('Project Portfolio'!F$4:F$43<>"⏸️ POSTPONED")*('Project Portfolio'!A$4:A$43<>"")),_xlfn._xlws.FILTER(IF('Project Portfolio'!J$4:J$43=0,99999,'Project Portfolio'!J$4:J$43),('Project Portfolio'!F$4:F$43<>"✅ COMPLETE")*('Project Portfolio'!F$4:F$43<>"🚫 NOT APPROVED")*('Project Portfolio'!F$4:F$43<>"⏸️ POSTPONED")*('Project Portfolio'!A$4:A$43<>"")),1),ROW()-4),"")} | C33: {=IFERROR(INDEX(_xlfn.SORTBY(_xlfn._xlws.FILTER('Project Portfolio'!B$4:B$43,('Project Portfolio'!F$4:F$43<>"✅ COMPLETE")*('Project Portfolio'!F$4:F$43<>"🚫 NOT APPROVED")*('Project Portfolio'!F$4:F$43<>"⏸️ POSTPONED")*('Project Portfolio'!A$4:A$43<>"")),_xlfn._xlws.FILTER(IF('Project Portfolio'!J$4:J$43=0,99999,'Project Portfolio'!J$4:J$43),('Project Portfolio'!F$4:F$43<>"✅ COMPLETE")*('Project Portfolio'!F$4:F$43<>"🚫 NOT APPROVED")*('Project Portfolio'!F$4:F$43<>"⏸️ POSTPONED")*('Project Portfolio'!A$4:A$43<>"")),1),ROW()-4),"")} | D33: {=IFERROR(INDEX(_xlfn.SORTBY(_xlfn._xlws.FILTER('Project Portfolio'!F$4:F$43,('Project Portfolio'!F$4:F$43<>"✅ COMPLETE")*('Project Portfolio'!F$4:F$43<>"🚫 NOT APPROVED")*('Project Portfolio'!F$4:F$43<>"⏸️ POSTPONED")*('Project Portfolio'!A$4:A$43<>"")),_xlfn._xlws.FILTER(IF('Project Portfolio'!J$4:J$43=0,99999,'Project Portfolio'!J$4:J$43),('Project Portfolio'!F$4:F$43<>"✅ COMPLETE")*('Project Portfolio'!F$4:F$43<>"🚫 NOT APPROVED")*('Project Portfolio'!F$4:F$43<>"⏸️ POSTPONED")*('Project Portfolio'!A$4:A$43<>"")),1),ROW()-4),"")} | E33: {=IFERROR(IF(INDEX(_xlfn.SORTBY(_xlfn._xlws.FILTER('Project Portfolio'!I$4:I$43,('Project Portfolio'!F$4:F$43<>"✅ COMPLETE")*('Project Portfolio'!F$4:F$43<>"🚫 NOT APPROVED")*('Project Portfolio'!F$4:F$43<>"⏸️ POSTPONED")*('Project Portfolio'!A$4:A$43<>"")),_xlfn._xlws.FILTER(IF('Project Portfolio'!J$4:J$43=0,99999,'Project Portfolio'!J$4:J$43),('Project Portfolio'!F$4:F$43<>"✅ COMPLETE")*('Project Portfolio'!F$4:F$43<>"🚫 NOT APPROVED")*('Project Portfolio'!F$4:F$43<>"⏸️ POSTPONED")*('Project Portfolio'!A$4:A$43<>"")),1),ROW()-4)=0,"",INDEX(_xlfn.SORTBY(_xlfn._xlws.FILTER('Project Portfolio'!I$4:I$43,('Project Portfolio'!F$4:F$43<>"✅ COMPLETE")*('Project Portfolio'!F$4:F$43<>"🚫 NOT APPROVED")*('Project Portfolio'!F$4:F$43<>"⏸️ POSTPONED")*('Project Portfolio'!A$4:A$43<>"")),_xlfn._xlws.FILTER(IF('Project Portfolio'!J$4:J$43=0,99999,'Project Portfolio'!J$4:J$43),('Project Portfolio'!F$4:F$43<>"✅ COMPLETE")*('Project Portfolio'!F$4:F$43<>"🚫 NOT APPROVED")*('Project Portfolio'!F$4:F$43<>"⏸️ POSTPONED")*('Project Portfolio'!A$4:A$43<>"")),1),ROW()-4)),"")} | F33: {=IFERROR(IF(INDEX(_xlfn.SORTBY(_xlfn._xlws.FILTER('Project Portfolio'!J$4:J$43,('Project Portfolio'!F$4:F$43<>"✅ COMPLETE")*('Project Portfolio'!F$4:F$43<>"🚫 NOT APPROVED")*('Project Portfolio'!F$4:F$43<>"⏸️ POSTPONED")*('Project Portfolio'!A$4:A$43<>"")),_xlfn._xlws.FILTER(IF('Project Portfolio'!J$4:J$43=0,99999,'Project Portfolio'!J$4:J$43),('Project Portfolio'!F$4:F$43<>"✅ COMPLETE")*('Project Portfolio'!F$4:F$43<>"🚫 NOT APPROVED")*('Project Portfolio'!F$4:F$43<>"⏸️ POSTPONED")*('Project Portfolio'!A$4:A$43<>"")),1),ROW()-4)=0,"",INDEX(_xlfn.SORTBY(_xlfn._xlws.FILTER('Project Portfolio'!J$4:J$43,('Project Portfolio'!F$4:F$43<>"✅ COMPLETE")*('Project Portfolio'!F$4:F$43<>"🚫 NOT APPROVED")*('Project Portfolio'!F$4:F$43<>"⏸️ POSTPONED")*('Project Portfolio'!A$4:A$43<>"")),_xlfn._xlws.FILTER(IF('Project Portfolio'!J$4:J$43=0,99999,'Project Portfolio'!J$4:J$43),('Project Portfolio'!F$4:F$43<>"✅ COMPLETE")*('Project Portfolio'!F$4:F$43<>"🚫 NOT APPROVED")*('Project Portfolio'!F$4:F$43<>"⏸️ POSTPONED")*('Project Portfolio'!A$4:A$43<>"")),1),ROW()-4)),"")} | G33: =IF(AND($E33>0,$F33>0,G$4+6>=$E33,G$4<=$F33),1,"") | H33: =IF(AND($E33>0,$F33>0,H$4+6>=$E33,H$4<=$F33),1,"") | I33: =IF(AND($E33>0,$F33>0,I$4+6>=$E33,I$4<=$F33),1,"") | J33: =IF(AND($E33>0,$F33>0,J$4+6>=$E33,J$4<=$F33),1,"") | K33: =IF(AND($E33>0,$F33>0,K$4+6>=$E33,K$4<=$F33),1,"") | L33: =IF(AND($E33>0,$F33>0,L$4+6>=$E33,L$4<=$F33),1,"") | M33: =IF(AND($E33>0,$F33>0,M$4+6>=$E33,M$4<=$F33),1,"") | N33: =IF(AND($E33>0,$F33>0,N$4+6>=$E33,N$4<=$F33),1,"") | ... BF33: =IF(AND($E33>0,$F33>0,BF$4+6>=$E33,BF$4<=$F33),1,"")

Sheet RM_Guide
A1: ETE IT PMO — Resource Model Guide
A2: A plain-English explanation of how the Resource Model works, what each sheet does, and how to use it.
A4: THE BIG PICTURE
A5: What is this? | B5: A set of 4 connected sheets that answer: "Do we have enough people for all these projects, and when will we be in trouble?"
A6: Why does it exist? | B6: The Portfolio shows WHAT projects we have. The Resource Model shows WHETHER we can actually staff them — and when bottlenecks will hit.
A7: Who should use it? | B7: PMO leads for weekly planning, resource decisions, and "what if" scenario testing (hiring, project delays, reprioritization).
A8: How do the sheets connect? | B8: RM_Assumptions (rules) → RM_Demand (how much work) → RM_SupplyVsDemand (big picture) → RM_WeeklyHeatmap (when exactly).
A9: What are the blue cells? | B9: Any cell with a blue/light blue background is an INPUT you can change. These are your scenario levers — adjust them and the model recalculates automatically.
A11: SHEET-BY-SHEET EXPLANATION
A13: 📋 RM_Assumptions | B13: "What are our rules?" — This is the control panel for the whole model.
A14: Time Allocation (rows 6-12) | B14: Each person works 40 hrs/week, but not all of it goes to projects. Admin (10%) and Break/Fix support (10%) eat into that, leaving 80% = 32 hrs/week for project work. You can change these percentages.
A15: SDLC Phase Weights (row 16) | B15: A project isn't evenly spread. It's 10% Discovery → 10% Planning → 15% Design → 30% Build → 20% Test → 15% Deploy. These must add to 100%. Change them to match your actual project lifecycle.
A16: Role Effort by Phase (rows 21-28) | B16: THIS IS THE KEY INSIGHT. A DBA isn't equally busy throughout a project. They barely touch Discovery (5%) but are heavily loaded in Build (30%). A BA is the opposite — 30% in Discovery, only 10% in Build. These percentages drive the weekly demand spikes in the heatmap.
A17: Team Supply (rows 30-38) | B17: Auto-counts headcount and hours from the Team Roster. You don't edit these — they update when Team Roster changes.
A19: 📊 RM_Demand | B19: "How much work is coming?" — Calculates total demand from active projects.
A20: Active Projects (rows 6-18) | B20: Automatically pulls all non-complete, non-postponed projects from the Portfolio. You don't edit these rows — they update when Portfolio changes.
A21: Total Demand by Role (rows 24-30) | B21: For each role, adds up: (Project Est. Hours × Role Allocation %) across all active projects. Shows you the total hours each role needs to deliver.
A22: Project × Role Detail (rows 36-48) | B22: A breakdown showing exactly how many hours each project needs from each role. Useful for seeing which projects are driving the most demand.
A24: ⚖️ RM_SupplyVsDemand | B24: "Are we OK overall?" — A summary scorecard comparing supply to demand.
A25: Capacity Scorecard (rows 5-7) | B25: The headline numbers: Total Supply hrs/wk, Total Demand hrs/wk, Net Gap (+ means surplus, - means deficit), and Overall Utilization %.
A26: By Role (rows 11-17) | B26: Same comparison broken out by role. Color-coded: green = fine, yellow = tight, red = over capacity. This tells you WHERE the problem is.
... A32: The Heatmap (rows 34-40) | B32: The payoff. Each cell shows utilization % for one role in one week. Green (<80%) = fine. Yellow (80-99%) = getting tight. Red (100%+) = overloaded, need to act. Demand shifts week-to-week because the model knows which SDLC phase each project is in.
A35: HOW TO RUN SCENARIOS
A36: "What if we hire another DBA?" | B36: Go to RM_WeeklyHeatmap → cell C11 (DBA Add/Remove) → type 1. The DBA row in the heatmap will drop from red to green. If it works, you've justified the hire.
A37: "What if we delay a project?" | B37: Go to RM_WeeklyHeatmap → find the project in rows 17-29 → change its Start Date (column D) or End Date (column E). The heatmap will shift that project's demand to different weeks.
A38: "What if a project takes longer?" | B38: Push the End Date further out. The same total hours get spread over more weeks, so weekly demand drops — but it stays on the heatmap longer.
A39: "What if we change how much BA time a project needs?" | B39: Go to RM_Assumptions → Role Effort by Phase (rows 21-28) → adjust the BA row. This changes how much BA demand every project generates during each phase.
A40: "What if we shift more time to admin?" | B40: Go to RM_Assumptions → Time Allocation (rows 7-9) → increase Admin %, decrease Project %. Everyone's available project hours shrink, so utilization goes up across the board.
A41: Reset everything | B41: Set all Headcount Adjusters back to 0. The project dates will revert to Portfolio defaults on their own (they pull from Portfolio when not overridden).
A44: READING THE HEATMAP COLORS
A45: 🟢 Green (under 80%) | B45: This role has capacity. No action needed.
A46: 🟡 Yellow (80-99%) | B46: At risk. A short burst of yellow (1-2 weeks) is OK — people can push through. But sustained yellow over 3+ weeks means you're running tight and any surprise will tip into red.
A47: 🔴 Red (100% or higher) | B47: Over capacity. This role physically can't deliver everything assigned to them. Something has to give: hire more, delay a project, or reassign work. The higher the %, the worse it is (183% means you'd need almost 2x the people).
A48: All zeros (0%) | B48: Either no projects are active that week, or no projects need that role. Check if project dates are set correctly in the timeline section.
A51: IMPORTANT NOTES
A52: Projects with no dates | B52: If a project in the Portfolio has no Start/End date, the heatmap defaults it to starting today with a 12-week duration. Once real dates are added to the Portfolio, it picks them up automatically.
A53: Completed/Postponed projects | B53: These are automatically excluded from all demand calculations. You don't need to remove them.
A54: Phase totals over 100% | B54: In RM_Assumptions, the Phase Total row may show >100%. This is correct — it means multiple roles work on the same phase. It's not a distribution (doesn't need to sum to 100%), it's effort intensity per role.
A55: Headcount vs. Team Roster | B55: Base headcount in the heatmap comes from Team Roster via RM_Assumptions. The Adjuster in the heatmap is a temporary "what if" — it doesn't change the actual roster.
A56: Don't edit gray cells | B56: Gray cells contain formulas. If you overwrite them, the model breaks. Only edit blue cells.
A58: 📅 RM_Gantt (Resource-Leveled Gantt) | B58: "What's the recommended schedule?" — Shows projects rescheduled to avoid resource overloads.
A59: What it does | B59: Takes all 13 active projects, sorts them by priority (Highest first), and schedules them one by one. If adding a project would push any role over 100% capacity, it pushes that project's start date forward week-by-week until it fits.
A60: Schedule Table (cols A-I) | B60: Shows each project's original dates vs. adjusted dates. The "Shifted" column tells you how many weeks a project was pushed. Yellow-highlighted adjusted dates = the project moved.
A61: Gantt Bars (cols J+) | B61: Color-coded bars: Red = Highest priority, Yellow = High, Blue = Medium. Green ghost bars show where a shifted project was originally scheduled.
A62: Key insight | B62: The DBA is the binding constraint. All 5 Medium projects had to shift because of DBA overload. Highest and High priority projects kept their original dates.
A63: ⚠️ Important | B63: This is a one-time snapshot, NOT a live formula. After changing headcount adjusters or project dates in RM_WeeklyHeatmap, ask Claude to regenerate the Gantt to get an updated recommended schedule.

Sheet Capacity Heatmap
A1: ETE IT PMO — Weekly Capacity Heatmap
A2: Overloaded (>100%) | B2: At Capacity (85-100%) | C2: Healthy (50-84%) | D2: Underutilized (<50%)
E3: WK 1 | F3: WK 2 | G3: WK 3 | H3: WK 4 | I3: WK 5 | J3: WK 6 | K3: WK 7 | L3: WK 8 | M3: WK 9 | N3: WK 10 | O3: WK 11 | P3: WK 12 | Q3: WK 13 | R3: WK 14 | S3: WK 15 | T3: WK 16 | U3: WK 17 | V3: WK 18 | W3: WK 19 | X3: WK 20 | Y3: WK 21 | Z3: WK 22 | AA3: WK 23 | AB3: WK 24 | AC3: WK 25 | AD3: WK 26
A4: Resource | B4: Role | C4: Team | D4: Net Capacity (hrs/wk) | E4: 46023 | F4: =E4+7 -> 46030 | G4: =F4+7 -> 46037 | H4: =G4+7 -> 46044 | I4: =H4+7 -> 46051 | J4: =I4+7 -> 46058 | K4: =J4+7 -> 46065 | L4: =K4+7 -> 46072 | M4: =L4+7 -> 46079 | ... AD4: =AC4+7 -> 46198
A5: Ajay Kumar | B5: Functional | C5: Synnergie | D5: ='Team Roster'!K4 -> 21 | E5: {=IFERROR(SUMPRODUCT(('Project Portfolio'!$F$4:$F$42<>"✅ COMPLETE")*(('Project Portfolio'!$M$4:$M$42=$A5)+('Project Portfolio'!$N$4:$N$42=$A5)+('Project Portfolio'!$O$4:$O$42=$A5)+('Project Portfolio'!$P$4:$P$42=$A5)>0)*('Project Portfolio'!$I$4:$I$42>0)*('Project Portfolio'!$J$4:$J$42>0)*('Project Portfolio'!$I$4:$I$42<=E$4+6)*('Project Portfolio'!$J$4:$J$42>=E$4)*('Project Portfolio'!$R$4:$R$42*IF($B5="Business Analyst",'Project Portfolio'!$T$4:$T$42,IF($B5="Functional",'Project Portfolio'!$U$4:$U$42,IF($B5="Technical",'Project Portfolio'!$V$4:$V$42,IF($B5="Developer",'Project Portfolio'!$W$4:$W$42,IF($B5="Infrastructure",'Project Portfolio'!$X$4:$X$42,IF($B5="DBA",'Project Portfolio'!$Y$4:$Y$42,IF($B5="Project Manager",'Project Portfolio'!$Z$4:$Z$42,IF($B5="WMS Consultant",'Project Portfolio'!$AA$4:$AA$42,0))))))))/IF(INT(('Project Portfolio'!$J$4:$J$42-'Project Portfolio'!$I$4:$I$42)/7+1)>0,INT(('Project Portfolio'!$J$4:$J$42-'Project Portfolio'!$I$4:$I$42)/7+1),1)))/$D5,0)} -> 0 | F5: {=IFERROR(SUMPRODUCT(('Project Portfolio'!$F$4:$F$42<>"✅ COMPLETE")*(('Project Portfolio'!$M$4:$M$42=$A5)+('Project Portfolio'!$N$4:$N$42=$A5)+('Project Portfolio'!$O$4:$O$42=$A5)+('Project Portfolio'!$P$4:$P$42=$A5)>0)*('Project Portfolio'!$I$4:$I$42>0)*('Project Portfolio'!$J$4:$J$42>0)*('Project Portfolio'!$I$4:$I$42<=F$4+6)*('Project Portfolio'!$J$4:$J$42>=F$4)*('Project Portfolio'!$R$4:$R$42*IF($B5="Business Analyst",'Project Portfolio'!$T$4:$T$42,IF($B5="Functional",'Project Portfolio'!$U$4:$U$42,IF($B5="Technical",'Project Portfolio'!$V$4:$V$42,IF($B5="Developer",'Project Portfolio'!$W$4:$W$42,IF($B5="Infrastructure",'Project Portfolio'!$X$4:$X$42,IF($B5="DBA",'Project Portfolio'!$Y$4:$Y$42,IF($B5="Project Manager",'Project Portfolio'!$Z$4:$Z$42,IF($B5="WMS Consultant",'Project Portfolio'!$AA$4:$AA$42,0))))))))/IF(INT(('Project Portfolio'!$J$4:$J$42-'Project Portfolio'!$I$4:$I$42)/7+1)>0,INT(('Project Portfolio'!$J$4:$J$42-'Project Portfolio'!$I$4:$I$42)/7+1),1)))/$D5,0)} -> 0 | G5: {=IFERROR(SUMPRODUCT(('Project Portfolio'!$F$4:$F$42<>"✅ COMPLETE")*(('Project Portfolio'!$M$4:$M$42=$A5)+('Project Portfolio'!$N$4:$N$42=$A5)+('Project Portfolio'!$O$4:$O$42=$A5)+('Project Portfolio'!$P$4:$P$42=$A5)>0)*('Project Portfolio'!$I$4:$I$42>0)*('Project Portfolio'!$J$4:$J$42>0)*('Project Portfolio'!$I$4:$I$42<=G$4+6)*('Project Portfolio'!$J$4:$J$42>=G$4)*('Project Portfolio'!$R$4:$R$42*IF($B5="Business Analyst",'Project Portfolio'!$T$4:$T$42,IF($B5="Functional",'Project Portfolio'!$U$4:$U$42,IF($B5="Technical",'Project Portfolio'!$V$4:$V$42,IF($B5="Developer",'Project Portfolio'!$W$4:$W$42,IF($B5="Infrastructure",'Project Portfolio'!$X$4:$X$42,IF($B5="DBA",'Project Portfolio'!$Y$4:$Y$42,IF($B5="Project Manager",'Project Portfolio'!$Z$4:$Z$42,IF($B5="WMS Consultant",'Project Portfolio'!$AA$4:$AA$42,0))))))))/IF(INT(('Project Portfolio'!$J$4:$J$42-'Project Portfolio'!$I$4:$I$42)/7+1)>0,INT(('Project Portfolio'!$J$4:$J$42-'Project Portfolio'!$I$4:$I$42)/7+1),1)))/$D5,0)} -> 0 | H5: {=IFERROR(SUMPRODUCT(('Project Portfolio'!$F$4:$F$42<>"✅ COMPLETE")*(('Project Portfolio'!$M$4:$M$42=$A5)+('Project Portfolio'!$N$4:$N$42=$A5)+('Project Portfolio'!$O$4:$O$42=$A5)+('Project Portfolio'!$P$4:$P$42=$A5)>0)*('Project Portfolio'!$I$4:$I$42>0)*('Project Portfolio'!$J$4:$J$42>0)*('Project Portfolio'!$I$4:$I$42<=H$4+6)*('Project Portfolio'!$J$4:$J$42>=H$4)*('Project Portfolio'!$R$4:$R$42*IF($B5="Business Analyst",'Project Portfolio'!$T$4:$T$42,IF($B5="Functional",'Project Portfolio'!$U$4:$U$42,IF($B5="Technical",'Project Portfolio'!$V$4:$V$42,IF($B5="Developer",'Project Portfolio'!$W$4:$W$42,IF($B5="Infrastructure",'Project Portfolio'!$X$4:$X$42,IF($B5="DBA",'Project Portfolio'!$Y$4:$Y$42,IF($B5="Project Manager",'Project Portfolio'!$Z$4:$Z$42,IF($B5="WMS Consultant",'Project Portfolio'!$AA$4:$AA$42,0))))))))/IF(INT(('Project Portfolio'!$J$4:$J$42-'Project Portfolio'!$I$4:$I$42)/7+1)>0,INT(('Project Portfolio'!$J$4:$J$42-'Project Portfolio'!$I$4:$I$42)/7+1),1)))/$D5,0)} -> 0 | I5: {=IFERROR(SUMPRODUCT(('Project Portfolio'!$F$4:$F$42<>"✅ COMPLETE")*(('Project Portfolio'!$M$4:$M$42=$A5)+('Project Portfolio'!$N$4:$N$42=$A5)+('Project Portfolio'!$O$4:$O$42=$A5)+('Project Portfolio'!$P$4:$P$42=$A5)>0)*('Project Portfolio'!$I$4:$I$42>0)*('Project Portfolio'!$J$4:$J$42>0)*('Project Portfolio'!$I$4:$I$42<=I$4+6)*('Project Portfolio'!$J$4:$J$42>=I$4)*('Project Portfolio'!$R$4:$R$42*IF($B5="Business Analyst",'Project Portfolio'!$T$4:$T$42,IF($B5="Functional",'Project Portfolio'!$U$4:$U$42,IF($B5="Technical",'Project Portfolio'!$V$4:$V$42,IF($B5="Developer",'Project Portfolio'!$W$4:$W$42,IF($B5="Infrastructure",'Project Portfolio'!$X$4:$X$42,IF($B5="DBA",'Project Portfolio'!$Y$4:$Y$42,IF($B5="Project Manager",'Project Portfolio'!$Z$4:$Z$42,IF($B5="WMS Consultant",'Project Portfolio'!$AA$4:$AA$42,0))))))))/IF(INT(('Project Portfolio'!$J$4:$J$42-'Project Portfolio'!$I$4:$I$42)/7+1)>0,INT(('Project Portfolio'!$J$4:$J$42-'Project Portfolio'!$I$4:$I$42)/7+1),1)))/$D5,0)} -> 0 | J5: {=IFERROR(SUMPRODUCT(('Project Portfolio'!$F$4:$F$42<>"✅ COMPLETE")*(('Project Portfolio'!$M$4:$M$42=$A5)+('Project Portfolio'!$N$4:$N$42=$A5)+('Project Portfolio'!$O$4:$O$42=$A5)+('Project Portfolio'!$P$4:$P$42=$A5)>0)*('Project Portfolio'!$I$4:$I$42>0)*('Project Portfolio'!$J$4:$J$42>0)*('Project Portfolio'!$I$4:$I$42<=J$4+6)*('Project Portfolio'!$J$4:$J$42>=J$4)*('Project Portfolio'!$R$4:$R$42*IF($B5="Business Analyst",'Project Portfolio'!$T$4:$T$42,IF($B5="Functional",'Project Portfolio'!$U$4:$U$42,IF($B5="Technical",'Project Portfolio'!$V$4:$V$42,IF($B5="Developer",'Project Portfolio'!$W$4:$W$42,IF($B5="Infrastructure",'Project Portfolio'!$X$4:$X$42,IF($B5="DBA",'Project Portfolio'!$Y$4:$Y$42,IF($B5="Project Manager",'Project Portfolio'!$Z$4:$Z$42,IF($B5="WMS Consultant",'Project Portfolio'!$AA$4:$AA$42,0))))))))/IF(INT(('Project Portfolio'!$J$4:$J$42-'Project Portfolio'!$I$4:$I$42)/7+1)>0,INT(('Project Portfolio'!$J$4:$J$42-'Project Portfolio'!$I$4:$I$42)/7+1),1)))/$D5,0)} -> 0 | K5: {=IFERROR(SUMPRODUCT(('Project Portfolio'!$F$4:$F$42<>"✅ COMPLETE")*(('Project Portfolio'!$M$4:$M$42=$A5)+('Project Portfolio'!$N$4:$N$42=$A5)+('Project Portfolio'!$O$4:$O$42=$A5)+('Project Portfolio'!$P$4:$P$42=$A5)>0)*('Project Portfolio'!$I$4:$I$42>0)*('Project Portfolio'!$J$4:$J$42>0)*('Project Portfolio'!$I$4:$I$42<=K$4+6)*('Project Portfolio'!$J$4:$J$42>=K$4)*('Project Portfolio'!$R$4:$R$42*IF($B5="Business Analyst",'Project Portfolio'!$T$4:$T$42,IF($B5="Functional",'Project Portfolio'!$U$4:$U$42,IF($B5="Technical",'Project Portfolio'!$V$4:$V$42,IF($B5="Developer",'Project Portfolio'!$W$4:$W$42,IF($B5="Infrastructure",'Project Portfolio'!$X$4:$X$42,IF($B5="DBA",'Project Portfolio'!$Y$4:$Y$42,IF($B5="Project Manager",'Project Portfolio'!$Z$4:$Z$42,IF($B5="WMS Consultant",'Project Portfolio'!$AA$4:$AA$42,0))))))))/IF(INT(('Project Portfolio'!$J$4:$J$42-'Project Portfolio'!$I$4:$I$42)/7+1)>0,INT(('Project Portfolio'!$J$4:$J$42-'Project Portfolio'!$I$4:$I$42)/7+1),1)))/$D5,0)} -> 0 | L5: {=IFERROR(SUMPRODUCT(('Project Portfolio'!$F$4:$F$42<>"✅ COMPLETE")*(('Project Portfolio'!$M$4:$M$42=$A5)+('Project Portfolio'!$N$4:$N$42=$A5)+('Project Portfolio'!$O$4:$O$42=$A5)+('Project Portfolio'!$P$4:$P$42=$A5)>0)*('Project Portfolio'!$I$4:$I$42>0)*('Project Portfolio'!$J$4:$J$42>0)*('Project Portfolio'!$I$4:$I$42<=L$4+6)*('Project Portfolio'!$J$4:$J$42>=L$4)*('Project Portfolio'!$R$4:$R$42*IF($B5="Business Analyst",'Project Portfolio'!$T$4:$T$42,IF($B5="Functional",'Project Portfolio'!$U$4:$U$42,IF($B5="Technical",'Project Portfolio'!$V$4:$V$42,IF($B5="Developer",'Project Portfolio'!$W$4:$W$42,IF($B5="Infrastructure",'Project Portfolio'!$X$4:$X$42,IF($B5="DBA",'Project Portfolio'!$Y$4:$Y$42,IF($B5="Project Manager",'Project Portfolio'!$Z$4:$Z$42,IF($B5="WMS Consultant",'Project Portfolio'!$AA$4:$AA$42,0))))))))/IF(INT(('Project Portfolio'!$J$4:$J$42-'Project Portfolio'!$I$4:$I$42)/7+1)>0,INT(('Project Portfolio'!$J$4:$J$42-'Project Portfolio'!$I$4:$I$42)/7+1),1)))/$D5,0)} -> 0.17857143 | ... AD5: {=IFERROR(SUMPRODUCT(('Project Portfolio'!$F$4:$F$42<>"✅ COMPLETE")*(('Project Portfolio'!$M$4:$M$42=$A5)+('Project Portfolio'!$N$4:$N$42=$A5)+('Project Portfolio'!$O$4:$O$42=$A5)+('Project Portfolio'!$P$4:$P$42=$A5)>0)*('Project Portfolio'!$I$4:$I$42>0)*('Project Portfolio'!$J$4:$J$42>0)*('Project Portfolio'!$I$4:$I$42<=AD$4+6)*('Project Portfolio'!$J$4:$J$42>=AD$4)*('Project Portfolio'!$R$4:$R$42*IF($B5="Business Analyst",'Project Portfolio'!$T$4:$T$42,IF($B5="Functional",'Project Portfolio'!$U$4:$U$42,IF($B5="Technical",'Project Portfolio'!$V$4:$V$42,IF($B5="Developer",'Project Portfolio'!$W$4:$W$42,IF($B5="Infrastructure",'Project Portfolio'!$X$4:$X$42,IF($B5="DBA",'Project Portfolio'!$Y$4:$Y$42,IF($B5="Project Manager",'Project Portfolio'!$Z$4:$Z$42,IF($B5="WMS Consultant",'Project Portfolio'!$AA$4:$AA$42,0))))))))/IF(INT(('Project Portfolio'!$J$4:$J$42-'Project Portfolio'!$I$4:$I$42)/7+1)>0,INT(('Project Portfolio'!$J$4:$J$42-'Project Portfolio'!$I$4:$I$42)/7+1),1)))/$D5,0)} -> 0
A6: Ravindra Reddy | B6: Technical | C6: Synnergie | D6: ='Team Roster'!K5 -> 21 | E6: {=IFERROR(SUMPRODUCT(('Project Portfolio'!$F$4:$F$42<>"✅ COMPLETE")*(('Project Portfolio'!$M$4:$M$42=$A6)+('Project Portfolio'!$N$4:$N$42=$A6)+('Project Portfolio'!$O$4:$O$42=$A6)+('Project Portfolio'!$P$4:$P$42=$A6)>0)*('Project Portfolio'!$I$4:$I$42>0)*('Project Portfolio'!$J$4:$J$42>0)*('Project Portfolio'!$I$4:$I$42<=E$4+6)*('Project Portfolio'!$J$4:$J$42>=E$4)*('Project Portfolio'!$R$4:$R$42*IF($B6="Business Analyst",'Project Portfolio'!$T$4:$T$42,IF($B6="Functional",'Project Portfolio'!$U$4:$U$42,IF($B6="Technical",'Project Portfolio'!$V$4:$V$42,IF($B6="Developer",'Project Portfolio'!$W$4:$W$42,IF($B6="Infrastructure",'Project Portfolio'!$X$4:$X$42,IF($B6="DBA",'Project Portfolio'!$Y$4:$Y$42,IF($B6="Project Manager",'Project Portfolio'!$Z$4:$Z$42,IF($B6="WMS Consultant",'Project Portfolio'!$AA$4:$AA$42,0))))))))/IF(INT(('Project Portfolio'!$J$4:$J$42-'Project Portfolio'!$I$4:$I$42)/7+1)>0,INT(('Project Portfolio'!$J$4:$J$42-'Project Portfolio'!$I$4:$I$42)/7+1),1)))/$D6,0)} -> 0 | F6: {=IFERROR(SUMPRODUCT(('Project Portfolio'!$F$4:$F$42<>"✅ COMPLETE")*(('Project Portfolio'!$M$4:$M$42=$A6)+('Project Portfolio'!$N$4:$N$42=$A6)+('Project Portfolio'!$O$4:$O$42=$A6)+('Project Portfolio'!$P$4:$P$42=$A6)>0)*('Project Portfolio'!$I$4:$I$42>0)*('Project Portfolio'!$J$4:$J$42>0)*('Project Portfolio'!$I$4:$I$42<=F$4+6)*('Project Portfolio'!$J$4:$J$42>=F$4)*('Project Portfolio'!$R$4:$R$42*IF($B6="Business Analyst",'Project Portfolio'!$T$4:$T$42,IF($B6="Functional",'Project Portfolio'!$U$4:$U$42,IF($B6="Technical",'Project Portfolio'!$V$4:$V$42,IF($B6="Developer",'Project Portfolio'!$W$4:$W$42,IF($B6="Infrastructure",'Project Portfolio'!$X$4:$X$42,IF($B6="DBA",'Project Portfolio'!$Y$4:$Y$42,IF($B6="Project Manager",'Project Portfolio'!$Z$4:$Z$42,IF($B6="WMS Consultant",'Project Portfolio'!$AA$4:$AA$42,0))))))))/IF(INT(('Project Portfolio'!$J$4:$J$42-'Project Portfolio'!$I$4:$I$42)/7+1)>0,INT(('Project Portfolio'!$J$4:$J$42-'Project Portfolio'!$I$4:$I$42)/7+1),1)))/$D6,0)} -> 0 | G6: {=IFERROR(SUMPRODUCT(('Project Portfolio'!$F$4:$F$42<>"✅ COMPLETE")*(('Project Portfolio'!$M$4:$M$42=$A6)+('Project Portfolio'!$N$4:$N$42=$A6)+('Project Portfolio'!$O$4:$O$42=$A6)+('Project Portfolio'!$P$4:$P$42=$A6)>0)*('Project Portfolio'!$I$4:$I$42>0)*('Project Portfolio'!$J$4:$J$42>0)*('Project Portfolio'!$I$4:$I$42<=G$4+6)*('Project Portfolio'!$J$4:$J$42>=G$4)*('Project Portfolio'!$R$4:$R$42*IF($B6="Business Analyst",'Project Portfolio'!$T$4:$T$42,IF($B6="Functional",'Project Portfolio'!$U$4:$U$42,IF($B6="Technical",'Project Portfolio'!$V$4:$V$42,IF($B6="Developer",'Project Portfolio'!$W$4:$W$42,IF($B6="Infrastructure",'Project Portfolio'!$X$4:$X$42,IF($B6="DBA",'Project Portfolio'!$Y$4:$Y$42,IF($B6="Project Manager",'Project Portfolio'!$Z$4:$Z$42,IF($B6="WMS Consultant",'Project Portfolio'!$AA$4:$AA$42,0))))))))/IF(INT(('Project Portfolio'!$J$4:$J$42-'Project Portfolio'!$I$4:$I$42)/7+1)>0,INT(('Project Portfolio'!$J$4:$J$42-'Project Portfolio'!$I$4:$I$42)/7+1),1)))/$D6,0)} -> 0 | H6: {=IFERROR(SUMPRODUCT(('Project Portfolio'!$F$4:$F$42<>"✅ COMPLETE")*(('Project Portfolio'!$M$4:$M$42=$A6)+('Project Portfolio'!$N$4:$N$42=$A6)+('Project Portfolio'!$O$4:$O$42=$A6)+('Project Portfolio'!$P$4:$P$42=$A6)>0)*('Project Portfolio'!$I$4:$I$42>0)*('Project Portfolio'!$J$4:$J$42>0)*('Project Portfolio'!$I$4:$I$42<=H$4+6)*('Project Portfolio'!$J$4:$J$42>=H$4)*('Project Portfolio'!$R$4:$R$42*IF($B6="Business Analyst",'Project Portfolio'!$T$4:$T$42,IF($B6="Functional",'Project Portfolio'!$U$4:$U$42,IF($B6="Technical",'Project Portfolio'!$V$4:$V$42,IF($B6="Developer",'Project Portfolio'!$W$4:$W$42,IF($B6="Infrastructure",'Project Portfolio'!$X$4:$X$42,IF($B6="DBA",'Project Portfolio'!$Y$4:$Y$42,IF($B6="Project Manager",'Project Portfolio'!$Z$4:$Z$42,IF($B6="WMS Consultant",'Project Portfolio'!$AA$4:$AA$42,0))))))))/IF(INT(('Project Portfolio'!$J$4:$J$42-'Project Portfolio'!$I$4:$I$42)/7+1)>0,INT(('Project Portfolio'!$J$4:$J$42-'Project Portfolio'!$I$4:$I$42)/7+1),1)))/$D6,0)} -> 0 | I6: {=IFERROR(SUMPRODUCT(('Project Portfolio'!$F$4:$F$42<>"✅ COMPLETE")*(('Project Portfolio'!$M$4:$M$42=$A6)+('Project Portfolio'!$N$4:$N$42=$A6)+('Project Portfolio'!$O$4:$O$42=$A6)+('Project Portfolio'!$P$4:$P$42=$A6)>0)*('Project Portfolio'!$I$4:$I$42>0)*('Project Portfolio'!$J$4:$J$42>0)*('Project Portfolio'!$I$4:$I$42<=I$4+6)*('Project Portfolio'!$J$4:$J$42>=I$4)*('Project Portfolio'!$R$4:$R$42*IF($B6="Business Analyst",'Project Portfolio'!$T$4:$T$42,IF($B6="Functional",'Project Portfolio'!$U$4:$U$42,IF($B6="Technical",'Project Portfolio'!$V$4:$V$42,IF($B6="Developer",'Project Portfolio'!$W$4:$W$42,IF($B6="Infrastructure",'Project Portfolio'!$X$4:$X$42,IF($B6="DBA",'Project Portfolio'!$Y$4:$Y$42,IF($B6="Project Manager",'Project Portfolio'!$Z$4:$Z$42,IF($B6="WMS Consultant",'Project Portfolio'!$AA$4:$AA$42,0))))))))/IF(INT(('Project Portfolio'!$J$4:$J$42-'Project Portfolio'!$I$4:$I$42)/7+1)>0,INT(('Project Portfolio'!$J$4:$J$42-'Project Portfolio'!$I$4:$I$42)/7+1),1)))/$D6,0)} -> 0 | J6: {=IFERROR(SUMPRODUCT(('Project Portfolio'!$F$4:$F$42<>"✅ COMPLETE")*(('Project Portfolio'!$M$4:$M$42=$A6)+('Project Portfolio'!$N$4:$N$42=$A6)+('Project Portfolio'!$O$4:$O$42=$A6)+('Project Portfolio'!$P$4:$P$42=$A6)>0)*('Project Portfolio'!$I$4:$I$42>0)*('Project Portfolio'!$J$4:$J$42>0)*('Project Portfolio'!$I$4:$I$42<=J$4+6)*('Project Portfolio'!$J$4:$J$42>=J$4)*('Project Portfolio'!$R$4:$R$42*IF($B6="Business Analyst",'Project Portfolio'!$T$4:$T$42,IF($B6="Functional",'Project Portfolio'!$U$4:$U$42,IF($B6="Technical",'Project Portfolio'!$V$4:$V$42,IF($B6="Developer",'Project Portfolio'!$W$4:$W$42,IF($B6="Infrastructure",'Project Portfolio'!$X$4:$X$42,IF($B6="DBA",'Project Portfolio'!$Y$4:$Y$42,IF($B6="Project Manager",'Project Portfolio'!$Z$4:$Z$42,IF($B6="WMS Consultant",'Project Portfolio'!$AA$4:$AA$42,0))))))))/IF(INT(('Project Portfolio'!$J$4:$J$42-'Project Portfolio'!$I$4:$I$42)/7+1)>0,INT(('Project Portfolio'!$J$4:$J$42-'Project Portfolio'!$I$4:$I$42)/7+1),1)))/$D6,0)} -> 0 | K6: {=IFERROR(SUMPRODUCT(('Project Portfolio'!$F$4:$F$42<>"✅ COMPLETE")*(('Project Portfolio'!$M$4:$M$42=$A6)+('Project Portfolio'!$N$4:$N$42=$A6)+('Project Portfolio'!$O$4:$O$42=$A6)+('Project Portfolio'!$P$4:$P$42=$A6)>0)*('Project Portfolio'!$I$4:$I$42>0)*('Project Portfolio'!$J$4:$J$42>0)*('Project Portfolio'!$I$4:$I$42<=K$4+6)*('Project Portfolio'!$J$4:$J$42>=K$4)*('Project Portfolio'!$R$4:$R$42*IF($B6="Business Analyst",'Project Portfolio'!$T$4:$T$42,IF($B6="Functional",'Project Portfolio'!$U$4:$U$42,IF($B6="Technical",'Project Portfolio'!$V$4:$V$42,IF($B6="Developer",'Project Portfolio'!$W$4:$W$42,IF($B6="Infrastructure",'Project Portfolio'!$X$4:$X$42,IF($B6="DBA",'Project Portfolio'!$Y$4:$Y$42,IF($B6="Project Manager",'Project Portfolio'!$Z$4:$Z$42,IF($B6="WMS Consultant",'Project Portfolio'!$AA$4:$AA$42,0))))))))/IF(INT(('Project Portfolio'!$J$4:$J$42-'Project Portfolio'!$I$4:$I$42)/7+1)>0,INT(('Project Portfolio'!$J$4:$J$42-'Project Portfolio'!$I$4:$I$42)/7+1),1)))/$D6,0)} -> 0 | L6: {=IFERROR(SUMPRODUCT(('Project Portfolio'!$F$4:$F$42<>"✅ COMPLETE")*(('Project Portfolio'!$M$4:$M$42=$A6)+('Project Portfolio'!$N$4:$N$42=$A6)+('Project Portfolio'!$O$4:$O$42=$A6)+('Project Portfolio'!$P$4:$P$42=$A6)>0)*('Project Portfolio'!$I$4:$I$42>0)*('Project Portfolio'!$J$4:$J$42>0)*('Project Portfolio'!$I$4:$I$42<=L$4+6)*('Project Portfolio'!$J$4:$J$42>=L$4)*('Project Portfolio'!$R$4:$R$42*IF($B6="Business Analyst",'Project Portfolio'!$T$4:$T$42,IF($B6="Functional",'Project Portfolio'!$U$4:$U$42,IF($B6="Technical",'Project Portfolio'!$V$4:$V$42,IF($B6="Developer",'Project Portfolio'!$W$4:$W$42,IF($B6="Infrastructure",'Project Portfolio'!$X$4:$X$42,IF($B6="DBA",'Project Portfolio'!$Y$4:$Y$42,IF($B6="Project Manager",'Project Portfolio'!$Z$4:$Z$42,IF($B6="WMS Consultant",'Project Portfolio'!$AA$4:$AA$42,0))))))))/IF(INT(('Project Portfolio'!$J$4:$J$42-'Project Portfolio'!$I$4:$I$42)/7+1)>0,INT(('Project Portfolio'!$J$4:$J$42-'Project Portfolio'!$I$4:$I$42)/7+1),1)))/$D6,0)} -> 0 | ... AD6: {=IFERROR(SUMPRODUCT(('Project Portfolio'!$F$4:$F$42<>"✅ COMPLETE")*(('Project Portfolio'!$M$4:$M$42=$A6)+('Project Portfolio'!$N$4:$N$42=$A6)+('Project Portfolio'!$O$4:$O$42=$A6)+('Project Portfolio'!$P$4:$P$42=$A6)>0)*('Project Portfolio'!$I$4:$I$42>0)*('Project Portfolio'!$J$4:$J$42>0)*('Project Portfolio'!$I$4:$I$42<=AD$4+6)*('Project Portfolio'!$J$4:$J$42>=AD$4)*('Project Portfolio'!$R$4:$R$42*IF($B6="Business Analyst",'Project Portfolio'!$T$4:$T$42,IF($B6="Functional",'Project Portfolio'!$U$4:$U$42,IF($B6="Technical",'Project Portfolio'!$V$4:$V$42,IF($B6="Developer",'Project Portfolio'!$W$4:$W$42,IF($B6="Infrastructure",'Project Portfolio'!$X$4:$X$42,IF($B6="DBA",'Project Portfolio'!$Y$4:$Y$42,IF($B6="Project Manager",'Project Portfolio'!$Z$4:$Z$42,IF($B6="WMS Consultant",'Project Portfolio'!$AA$4:$AA$42,0))))))))/IF(INT(('Project Portfolio'!$J$4:$J$42-'Project Portfolio'!$I$4:$I$42)/7+1)>0,INT(('Project Portfolio'!$J$4:$J$42-'Project Portfolio'!$I$4:$I$42)/7+1),1)))/$D6,0)} -> 0
A7: Vishnu Premen | B7: Technical | C7: Synnergie | D7: ='Team Roster'!K6 -> 21 | E7: {=IFERROR(SUMPRODUCT(('Project Portfolio'!$F$4:$F$42<>"✅ COMPLETE")*(('Project Portfolio'!$M$4:$M$42=$A7)+('Project Portfolio'!$N$4:$N$42=$A7)+('Project Portfolio'!$O$4:$O$42=$A7)+('Project Portfolio'!$P$4:$P$42=$A7)>0)*('Project Portfolio'!$I$4:$I$42>0)*('Project Portfolio'!$J$4:$J$42>0)*('Project Portfolio'!$I$4:$I$42<=E$4+6)*('Project Portfolio'!$J$4:$J$42>=E$4)*('Project Portfolio'!$R$4:$R$42*IF($B7="Business Analyst",'Project Portfolio'!$T$4:$T$42,IF($B7="Functional",'Project Portfolio'!$U$4:$U$42,IF($B7="Technical",'Project Portfolio'!$V$4:$V$42,IF($B7="Developer",'Project Portfolio'!$W$4:$W$42,IF($B7="Infrastructure",'Project Portfolio'!$X$4:$X$42,IF($B7="DBA",'Project Portfolio'!$Y$4:$Y$42,IF($B7="Project Manager",'Project Portfolio'!$Z$4:$Z$42,IF($B7="WMS Consultant",'Project Portfolio'!$AA$4:$AA$42,0))))))))/IF(INT(('Project Portfolio'!$J$4:$J$42-'Project Portfolio'!$I$4:$I$42)/7+1)>0,INT(('Project Portfolio'!$J$4:$J$42-'Project Portfolio'!$I$4:$I$42)/7+1),1)))/$D7,0)} -> 0 | F7: {=IFERROR(SUMPRODUCT(('Project Portfolio'!$F$4:$F$42<>"✅ COMPLETE")*(('Project Portfolio'!$M$4:$M$42=$A7)+('Project Portfolio'!$N$4:$N$42=$A7)+('Project Portfolio'!$O$4:$O$42=$A7)+('Project Portfolio'!$P$4:$P$42=$A7)>0)*('Project Portfolio'!$I$4:$I$42>0)*('Project Portfolio'!$J$4:$J$42>0)*('Project Portfolio'!$I$4:$I$42<=F$4+6)*('Project Portfolio'!$J$4:$J$42>=F$4)*('Project Portfolio'!$R$4:$R$42*IF($B7="Business Analyst",'Project Portfolio'!$T$4:$T$42,IF($B7="Functional",'Project Portfolio'!$U$4:$U$42,IF($B7="Technical",'Project Portfolio'!$V$4:$V$42,IF($B7="Developer",'Project Portfolio'!$W$4:$W$42,IF($B7="Infrastructure",'Project Portfolio'!$X$4:$X$42,IF($B7="DBA",'Project Portfolio'!$Y$4:$Y$42,IF($B7="Project Manager",'Project Portfolio'!$Z$4:$Z$42,IF($B7="WMS Consultant",'Project Portfolio'!$AA$4:$AA$42,0))))))))/IF(INT(('Project Portfolio'!$J$4:$J$42-'Project Portfolio'!$I$4:$I$42)/7+1)>0,INT(('Project Portfolio'!$J$4:$J$42-'Project Portfolio'!$I$4:$I$42)/7+1),1)))/$D7,0)} -> 0 | G7: {=IFERROR(SUMPRODUCT(('Project Portfolio'!$F$4:$F$42<>"✅ COMPLETE")*(('Project Portfolio'!$M$4:$M$42=$A7)+('Project Portfolio'!$N$4:$N$42=$A7)+('Project Portfolio'!$O$4:$O$42=$A7)+('Project Portfolio'!$P$4:$P$42=$A7)>0)*('Project Portfolio'!$I$4:$I$42>0)*('Project Portfolio'!$J$4:$J$42>0)*('Project Portfolio'!$I$4:$I$42<=G$4+6)*('Project Portfolio'!$J$4:$J$42>=G$4)*('Project Portfolio'!$R$4:$R$42*IF($B7="Business Analyst",'Project Portfolio'!$T$4:$T$42,IF($B7="Functional",'Project Portfolio'!$U$4:$U$42,IF($B7="Technical",'Project Portfolio'!$V$4:$V$42,IF($B7="Developer",'Project Portfolio'!$W$4:$W$42,IF($B7="Infrastructure",'Project Portfolio'!$X$4:$X$42,IF($B7="DBA",'Project Portfolio'!$Y$4:$Y$42,IF($B7="Project Manager",'Project Portfolio'!$Z$4:$Z$42,IF($B7="WMS Consultant",'Project Portfolio'!$AA$4:$AA$42,0))))))))/IF(INT(('Project Portfolio'!$J$4:$J$42-'Project Portfolio'!$I$4:$I$42)/7+1)>0,INT(('Project Portfolio'!$J$4:$J$42-'Project Portfolio'!$I$4:$I$42)/7+1),1)))/$D7,0)} -> 0 | H7: {=IFERROR(SUMPRODUCT(('Project Portfolio'!$F$4:$F$42<>"✅ COMPLETE")*(('Project Portfolio'!$M$4:$M$42=$A7)+('Project Portfolio'!$N$4:$N$42=$A7)+('Project Portfolio'!$O$4:$O$42=$A7)+('Project Portfolio'!$P$4:$P$42=$A7)>0)*('Project Portfolio'!$I$4:$I$42>0)*('Project Portfolio'!$J$4:$J$42>0)*('Project Portfolio'!$I$4:$I$42<=H$4+6)*('Project Portfolio'!$J$4:$J$42>=H$4)*('Project Portfolio'!$R$4:$R$42*IF($B7="Business Analyst",'Project Portfolio'!$T$4:$T$42,IF($B7="Functional",'Project Portfolio'!$U$4:$U$42,IF($B7="Technical",'Project Portfolio'!$V$4:$V$42,IF($B7="Developer",'Project Portfolio'!$W$4:$W$42,IF($B7="Infrastructure",'Project Portfolio'!$X$4:$X$42,IF($B7="DBA",'Project Portfolio'!$Y$4:$Y$42,IF($B7="Project Manager",'Project Portfolio'!$Z$4:$Z$42,IF($B7="WMS Consultant",'Project Portfolio'!$AA$4:$AA$42,0))))))))/IF(INT(('Project Portfolio'!$J$4:$J$42-'Project Portfolio'!$I$4:$I$42)/7+1)>0,INT(('Project Portfolio'!$J$4:$J$42-'Project Portfolio'!$I$4:$I$42)/7+1),1)))/$D7,0)} -> 0 | I7: {=IFERROR(SUMPRODUCT(('Project Portfolio'!$F$4:$F$42<>"✅ COMPLETE")*(('Project Portfolio'!$M$4:$M$42=$A7)+('Project Portfolio'!$N$4:$N$42=$A7)+('Project Portfolio'!$O$4:$O$42=$A7)+('Project Portfolio'!$P$4:$P$42=$A7)>0)*('Project Portfolio'!$I$4:$I$42>0)*('Project Portfolio'!$J$4:$J$42>0)*('Project Portfolio'!$I$4:$I$42<=I$4+6)*('Project Portfolio'!$J$4:$J$42>=I$4)*('Project Portfolio'!$R$4:$R$42*IF($B7="Business Analyst",'Project Portfolio'!$T$4:$T$42,IF($B7="Functional",'Project Portfolio'!$U$4:$U$42,IF($B7="Technical",'Project Portfolio'!$V$4:$V$42,IF($B7="Developer",'Project Portfolio'!$W$4:$W$42,IF($B7="Infrastructure",'Project Portfolio'!$X$4:$X$42,IF($B7="DBA",'Project Portfolio'!$Y$4:$Y$42,IF($B7="Project Manager",'Project Portfolio'!$Z$4:$Z$42,IF($B7="WMS Consultant",'Project Portfolio'!$AA$4:$AA$42,0))))))))/IF(INT(('Project Portfolio'!$J$4:$J$42-'Project Portfolio'!$I$4:$I$42)/7+1)>0,INT(('Project Portfolio'!$J$4:$J$42-'Project Portfolio'!$I$4:$I$42)/7+1),1)))/$D7,0)} -> 0 | J7: {=IFERROR(SUMPRODUCT(('Project Portfolio'!$F$4:$F$42<>"✅ COMPLETE")*(('Project Portfolio'!$M$4:$M$42=$A7)+('Project Portfolio'!$N$4:$N$42=$A7)+('Project Portfolio'!$O$4:$O$42=$A7)+('Project Portfolio'!$P$4:$P$42=$A7)>0)*('Project Portfolio'!$I$4:$I$42>0)*('Project Portfolio'!$J$4:$J$42>0)*('Project Portfolio'!$I$4:$I$42<=J$4+6)*('Project Portfolio'!$J$4:$J$42>=J$4)*('Project Portfolio'!$R$4:$R$42*IF($B7="Business Analyst",'Project Portfolio'!$T$4:$T$42,IF($B7="Functional",'Project Portfolio'!$U$4:$U$42,IF($B7="Technical",'Project Portfolio'!$V$4:$V$42,IF($B7="Developer",'Project Portfolio'!$W$4:$W$42,IF($B7="Infrastructure",'Project Portfolio'!$X$4:$X$42,IF($B7="DBA",'Project Portfolio'!$Y$4:$Y$42,IF($B7="Project Manager",'Project Portfolio'!$Z$4:$Z$42,IF($B7="WMS Consultant",'Project Portfolio'!$AA$4:$AA$42,0))))))))/IF(INT(('Project Portfolio'!$J$4:$J$42-'Project Portfolio'!$I$4:$I$42)/7+1)>0,INT(('Project Portfolio'!$J$4:$J$42-'Project Portfolio'!$I$4:$I$42)/7+1),1)))/$D7,0)} -> 0 | K7: {=IFERROR(SUMPRODUCT(('Project Portfolio'!$F$4:$F$42<>"✅ COMPLETE")*(('Project Portfolio'!$M$4:$M$42=$A7)+('Project Portfolio'!$N$4:$N$42=$A7)+('Project Portfolio'!$O$4:$O$42=$A7)+('Project Portfolio'!$P$4:$P$42=$A7)>0)*('Project Portfolio'!$I$4:$I$42>0)*('Project Portfolio'!$J$4:$J$42>0)*('Project Portfolio'!$I$4:$I$42<=K$4+6)*('Project Portfolio'!$J$4:$J$42>=K$4)*('Project Portfolio'!$R$4:$R$42*IF($B7="Business Analyst",'Project Portfolio'!$T$4:$T$42,IF($B7="Functional",'Project Portfolio'!$U$4:$U$42,IF($B7="Technical",'Project Portfolio'!$V$4:$V$42,IF($B7="Developer",'Project Portfolio'!$W$4:$W$42,IF($B7="Infrastructure",'Project Portfolio'!$X$4:$X$42,IF($B7="DBA",'Project Portfolio'!$Y$4:$Y$42,IF($B7="Project Manager",'Project Portfolio'!$Z$4:$Z$42,IF($B7="WMS Consultant",'Project Portfolio'!$AA$4:$AA$42,0))))))))/IF(INT(('Project Portfolio'!$J$4:$J$42-'Project Portfolio'!$I$4:$I$42)/7+1)>0,INT(('Project Portfolio'!$J$4:$J$42-'Project Portfolio'!$I$4:$I$42)/7+1),1)))/$D7,0)} -> 0 | L7: {=IFERROR(SUMPRODUCT(('Project Portfolio'!$F$4:$F$42<>"✅ COMPLETE")*(('Project Portfolio'!$M$4:$M$42=$A7)+('Project Portfolio'!$N$4:$N$42=$A7)+('Project Portfolio'!$O$4:$O$42=$A7)+('Project Portfolio'!$P$4:$P$42=$A7)>0)*('Project Portfolio'!$I$4:$I$42>0)*('Project Portfolio'!$J$4:$J$42>0)*('Project Portfolio'!$I$4:$I$42<=L$4+6)*('Project Portfolio'!$J$4:$J$42>=L$4)*('Project Portfolio'!$R$4:$R$42*IF($B7="Business Analyst",'Project Portfolio'!$T$4:$T$42,IF($B7="Functional",'Project Portfolio'!$U$4:$U$42,IF($B7="Technical",'Project Portfolio'!$V$4:$V$42,IF($B7="Developer",'Project Portfolio'!$W$4:$W$42,IF($B7="Infrastructure",'Project Portfolio'!$X$4:$X$42,IF($B7="DBA",'Project Portfolio'!$Y$4:$Y$42,IF($B7="Project Manager",'Project Portfolio'!$Z$4:$Z$42,IF($B7="WMS Consultant",'Project Portfolio'!$AA$4:$AA$42,0))))))))/IF(INT(('Project Portfolio'!$J$4:$J$42-'Project Portfolio'!$I$4:$I$42)/7+1)>0,INT(('Project Portfolio'!$J$4:$J$42-'Project Portfolio'!$I$4:$I$42)/7+1),1)))/$D7,0)} -> 0 | ... AD7: {=IFERROR(SUMPRODUCT(('Project Portfolio'!$F$4:$F$42<>"✅ COMPLETE")*(('Project Portfolio'!$M$4:$M$42=$A7)+('Project Portfolio'!$N$4:$N$42=$A7)+('Project Portfolio'!$O$4:$O$42=$A7)+('Project Portfolio'!$P$4:$P$42=$A7)>0)*('Project Portfolio'!$I$4:$I$42>0)*('Project Portfolio'!$J$4:$J$42>0)*('Project Portfolio'!$I$4:$I$42<=AD$4+6)*('Project Portfolio'!$J$4:$J$42>=AD$4)*('Project Portfolio'!$R$4:$R$42*IF($B7="Business Analyst",'Project Portfolio'!$T$4:$T$42,IF($B7="Functional",'Project Portfolio'!$U$4:$U$42,IF($B7="Technical",'Project Portfolio'!$V$4:$V$42,IF($B7="Developer",'Project Portfolio'!$W$4:$W$42,IF($B7="Infrastructure",'Project Portfolio'!$X$4:$X$42,IF($B7="DBA",'Project Portfolio'!$Y$4:$Y$42,IF($B7="Project Manager",'Project Portfolio'!$Z$4:$Z$42,IF($B7="WMS Consultant",'Project Portfolio'!$AA$4:$AA$42,0))))))))/IF(INT(('Project Portfolio'!$J$4:$J$42-'Project Portfolio'!$I$4:$I$42)/7+1)>0,INT(('Project Portfolio'!$J$4:$J$42-'Project Portfolio'!$I$4:$I$42)/7+1),1)))/$D7,0)} -> 0
A8: Deepak Gudwani | B8: Functional | C8: Synnergie | D8: ='Team Roster'!K7 -> 21 | E8: {=IFERROR(SUMPRODUCT(('Project Portfolio'!$F$4:$F$42<>"✅ COMPLETE")*(('Project Portfolio'!$M$4:$M$42=$A8)+('Project Portfolio'!$N$4:$N$42=$A8)+('Project Portfolio'!$O$4:$O$42=$A8)+('Project Portfolio'!$P$4:$P$42=$A8)>0)*('Project Portfolio'!$I$4:$I$42>0)*('Project Portfolio'!$J$4:$J$42>0)*('Project Portfolio'!$I$4:$I$42<=E$4+6)*('Project Portfolio'!$J$4:$J$42>=E$4)*('Project Portfolio'!$R$4:$R$42*IF($B8="Business Analyst",'Project Portfolio'!$T$4:$T$42,IF($B8="Functional",'Project Portfolio'!$U$4:$U$42,IF($B8="Technical",'Project Portfolio'!$V$4:$V$42,IF($B8="Developer",'Project Portfolio'!$W$4:$W$42,IF($B8="Infrastructure",'Project Portfolio'!$X$4:$X$42,IF($B8="DBA",'Project Portfolio'!$Y$4:$Y$42,IF($B8="Project Manager",'Project Portfolio'!$Z$4:$Z$42,IF($B8="WMS Consultant",'Project Portfolio'!$AA$4:$AA$42,0))))))))/IF(INT(('Project Portfolio'!$J$4:$J$42-'Project Portfolio'!$I$4:$I$42)/7+1)>0,INT(('Project Portfolio'!$J$4:$J$42-'Project Portfolio'!$I$4:$I$42)/7+1),1)))/$D8,0)} -> 0 | F8: {=IFERROR(SUMPRODUCT(('Project Portfolio'!$F$4:$F$42<>"✅ COMPLETE")*(('Project Portfolio'!$M$4:$M$42=$A8)+('Project Portfolio'!$N$4:$N$42=$A8)+('Project Portfolio'!$O$4:$O$42=$A8)+('Project Portfolio'!$P$4:$P$42=$A8)>0)*('Project Portfolio'!$I$4:$I$42>0)*('Project Portfolio'!$J$4:$J$42>0)*('Project Portfolio'!$I$4:$I$42<=F$4+6)*('Project Portfolio'!$J$4:$J$42>=F$4)*('Project Portfolio'!$R$4:$R$42*IF($B8="Business Analyst",'Project Portfolio'!$T$4:$T$42,IF($B8="Functional",'Project Portfolio'!$U$4:$U$42,IF($B8="Technical",'Project Portfolio'!$V$4:$V$42,IF($B8="Developer",'Project Portfolio'!$W$4:$W$42,IF($B8="Infrastructure",'Project Portfolio'!$X$4:$X$42,IF($B8="DBA",'Project Portfolio'!$Y$4:$Y$42,IF($B8="Project Manager",'Project Portfolio'!$Z$4:$Z$42,IF($B8="WMS Consultant",'Project Portfolio'!$AA$4:$AA$42,0))))))))/IF(INT(('Project Portfolio'!$J$4:$J$42-'Project Portfolio'!$I$4:$I$42)/7+1)>0,INT(('Project Portfolio'!$J$4:$J$42-'Project Portfolio'!$I$4:$I$42)/7+1),1)))/$D8,0)} -> 0 | G8: {=IFERROR(SUMPRODUCT(('Project Portfolio'!$F$4:$F$42<>"✅ COMPLETE")*(('Project Portfolio'!$M$4:$M$42=$A8)+('Project Portfolio'!$N$4:$N$42=$A8)+('Project Portfolio'!$O$4:$O$42=$A8)+('Project Portfolio'!$P$4:$P$42=$A8)>0)*('Project Portfolio'!$I$4:$I$42>0)*('Project Portfolio'!$J$4:$J$42>0)*('Project Portfolio'!$I$4:$I$42<=G$4+6)*('Project Portfolio'!$J$4:$J$42>=G$4)*('Project Portfolio'!$R$4:$R$42*IF($B8="Business Analyst",'Project Portfolio'!$T$4:$T$42,IF($B8="Functional",'Project Portfolio'!$U$4:$U$42,IF($B8="Technical",'Project Portfolio'!$V$4:$V$42,IF($B8="Developer",'Project Portfolio'!$W$4:$W$42,IF($B8="Infrastructure",'Project Portfolio'!$X$4:$X$42,IF($B8="DBA",'Project Portfolio'!$Y$4:$Y$42,IF($B8="Project Manager",'Project Portfolio'!$Z$4:$Z$42,IF($B8="WMS Consultant",'Project Portfolio'!$AA$4:$AA$42,0))))))))/IF(INT(('Project Portfolio'!$J$4:$J$42-'Project Portfolio'!$I$4:$I$42)/7+1)>0,INT(('Project Portfolio'!$J$4:$J$42-'Project Portfolio'!$I$4:$I$42)/7+1),1)))/$D8,0)} -> 0 | H8: {=IFERROR(SUMPRODUCT(('Project Portfolio'!$F$4:$F$42<>"✅ COMPLETE")*(('Project Portfolio'!$M$4:$M$42=$A8)+('Project Portfolio'!$N$4:$N$42=$A8)+('Project Portfolio'!$O$4:$O$42=$A8)+('Project Portfolio'!$P$4:$P$42=$A8)>0)*('Project Portfolio'!$I$4:$I$42>0)*('Project Portfolio'!$J$4:$J$42>0)*('Project Portfolio'!$I$4:$I$42<=H$4+6)*('Project Portfolio'!$J$4:$J$42>=H$4)*('Project Portfolio'!$R$4:$R$42*IF($B8="Business Analyst",'Project Portfolio'!$T$4:$T$42,IF($B8="Functional",'Project Portfolio'!$U$4:$U$42,IF($B8="Technical",'Project Portfolio'!$V$4:$V$42,IF($B8="Developer",'Project Portfolio'!$W$4:$W$42,IF($B8="Infrastructure",'Project Portfolio'!$X$4:$X$42,IF($B8="DBA",'Project Portfolio'!$Y$4:$Y$42,IF($B8="Project Manager",'Project Portfolio'!$Z$4:$Z$42,IF($B8="WMS Consultant",'Project Portfolio'!$AA$4:$AA$42,0))))))))/IF(INT(('Project Portfolio'!$J$4:$J$42-'Project Portfolio'!$I$4:$I$42)/7+1)>0,INT(('Project Portfolio'!$J$4:$J$42-'Project Portfolio'!$I$4:$I$42)/7+1),1)))/$D8,0)} -> 0 | I8: {=IFERROR(SUMPRODUCT(('Project Portfolio'!$F$4:$F$42<>"✅ COMPLETE")*(('Project Portfolio'!$M$4:$M$42=$A8)+('Project Portfolio'!$N$4:$N$42=$A8)+('Project Portfolio'!$O$4:$O$42=$A8)+('Project Portfolio'!$P$4:$P$42=$A8)>0)*('Project Portfolio'!$I$4:$I$42>0)*('Project Portfolio'!$J$4:$J$42>0)*('Project Portfolio'!$I$4:$I$42<=I$4+6)*('Project Portfolio'!$J$4:$J$42>=I$4)*('Project Portfolio'!$R$4:$R$42*IF($B8="Business Analyst",'Project Portfolio'!$T$4:$T$42,IF($B8="Functional",'Project Portfolio'!$U$4:$U$42,IF($B8="Technical",'Project Portfolio'!$V$4:$V$42,IF($B8="Developer",'Project Portfolio'!$W$4:$W$42,IF($B8="Infrastructure",'Project Portfolio'!$X$4:$X$42,IF($B8="DBA",'Project Portfolio'!$Y$4:$Y$42,IF($B8="Project Manager",'Project Portfolio'!$Z$4:$Z$42,IF($B8="WMS Consultant",'Project Portfolio'!$AA$4:$AA$42,0))))))))/IF(INT(('Project Portfolio'!$J$4:$J$42-'Project Portfolio'!$I$4:$I$42)/7+1)>0,INT(('Project Portfolio'!$J$4:$J$42-'Project Portfolio'!$I$4:$I$42)/7+1),1)))/$D8,0)} -> 0 | J8: {=IFERROR(SUMPRODUCT(('Project Portfolio'!$F$4:$F$42<>"✅ COMPLETE")*(('Project Portfolio'!$M$4:$M$42=$A8)+('Project Portfolio'!$N$4:$N$42=$A8)+('Project Portfolio'!$O$4:$O$42=$A8)+('Project Portfolio'!$P$4:$P$42=$A8)>0)*('Project Portfolio'!$I$4:$I$42>0)*('Project Portfolio'!$J$4:$J$42>0)*('Project Portfolio'!$I$4:$I$42<=J$4+6)*('Project Portfolio'!$J$4:$J$42>=J$4)*('Project Portfolio'!$R$4:$R$42*IF($B8="Business Analyst",'Project Portfolio'!$T$4:$T$42,IF($B8="Functional",'Project Portfolio'!$U$4:$U$42,IF($B8="Technical",'Project Portfolio'!$V$4:$V$42,IF($B8="Developer",'Project Portfolio'!$W$4:$W$42,IF($B8="Infrastructure",'Project Portfolio'!$X$4:$X$42,IF($B8="DBA",'Project Portfolio'!$Y$4:$Y$42,IF($B8="Project Manager",'Project Portfolio'!$Z$4:$Z$42,IF($B8="WMS Consultant",'Project Portfolio'!$AA$4:$AA$42,0))))))))/IF(INT(('Project Portfolio'!$J$4:$J$42-'Project Portfolio'!$I$4:$I$42)/7+1)>0,INT(('Project Portfolio'!$J$4:$J$42-'Project Portfolio'!$I$4:$I$42)/7+1),1)))/$D8,0)} -> 0 | K8: {=IFERROR(SUMPRODUCT(('Project Portfolio'!$F$4:$F$42<>"✅ COMPLETE")*(('Project Portfolio'!$M$4:$M$42=$A8)+('Project Portfolio'!$N$4:$N$42=$A8)+('Project Portfolio'!$O$4:$O$42=$A8)+('Project Portfolio'!$P$4:$P$42=$A8)>0)*('Project Portfolio'!$I$4:$I$42>0)*('Project Portfolio'!$J$4:$J$42>0)*('Project Portfolio'!$I$4:$I$42<=K$4+6)*('Project Portfolio'!$J$4:$J$42>=K$4)*('Project Portfolio'!$R$4:$R$42*IF($B8="Business Analyst",'Project Portfolio'!$T$4:$T$42,IF($B8="Functional",'Project Portfolio'!$U$4:$U$42,IF($B8="Technical",'Project Portfolio'!$V$4:$V$42,IF($B8="Developer",'Project Portfolio'!$W$4:$W$42,IF($B8="Infrastructure",'Project Portfolio'!$X$4:$X$42,IF($B8="DBA",'Project Portfolio'!$Y$4:$Y$42,IF($B8="Project Manager",'Project Portfolio'!$Z$4:$Z$42,IF($B8="WMS Consultant",'Project Portfolio'!$AA$4:$AA$42,0))))))))/IF(INT(('Project Portfolio'!$J$4:$J$42-'Project Portfolio'!$I$4:$I$42)/7+1)>0,INT(('Project Portfolio'!$J$4:$J$42-'Project Portfolio'!$I$4:$I$42)/7+1),1)))/$D8,0)} -> 0 | L8: {=IFERROR(SUMPRODUCT(('Project Portfolio'!$F$4:$F$42<>"✅ COMPLETE")*(('Project Portfolio'!$M$4:$M$42=$A8)+('Project Portfolio'!$N$4:$N$42=$A8)+('Project Portfolio'!$O$4:$O$42=$A8)+('Project Portfolio'!$P$4:$P$42=$A8)>0)*('Project Portfolio'!$I$4:$I$42>0)*('Project Portfolio'!$J$4:$J$42>0)*('Project Portfolio'!$I$4:$I$42<=L$4+6)*('Project Portfolio'!$J$4:$J$42>=L$4)*('Project Portfolio'!$R$4:$R$42*IF($B8="Business Analyst",'Project Portfolio'!$T$4:$T$42,IF($B8="Functional",'Project Portfolio'!$U$4:$U$42,IF($B8="Technical",'Project Portfolio'!$V$4:$V$42,IF($B8="Developer",'Project Portfolio'!$W$4:$W$42,IF($B8="Infrastructure",'Project Portfolio'!$X$4:$X$42,IF($B8="DBA",'Project Portfolio'!$Y$4:$Y$42,IF($B8="Project Manager",'Project Portfolio'!$Z$4:$Z$42,IF($B8="WMS Consultant",'Project Portfolio'!$AA$4:$AA$42,0))))))))/IF(INT(('Project Portfolio'!$J$4:$J$42-'Project Portfolio'!$I$4:$I$42)/7+1)>0,INT(('Project Portfolio'!$J$4:$J$42-'Project Portfolio'!$I$4:$I$42)/7+1),1)))/$D8,0)} -> 0 | ... AD8: {=IFERROR(SUMPRODUCT(('Project Portfolio'!$F$4:$F$42<>"✅ COMPLETE")*(('Project Portfolio'!$M$4:$M$42=$A8)+('Project Portfolio'!$N$4:$N$42=$A8)+('Project Portfolio'!$O$4:$O$42=$A8)+('Project Portfolio'!$P$4:$P$42=$A8)>0)*('Project Portfolio'!$I$4:$I$42>0)*('Project Portfolio'!$J$4:$J$42>0)*('Project Portfolio'!$I$4:$I$42<=AD$4+6)*('Project Portfolio'!$J$4:$J$42>=AD$4)*('Project Portfolio'!$R$4:$R$42*IF($B8="Business Analyst",'Project Portfolio'!$T$4:$T$42,IF($B8="Functional",'Project Portfolio'!$U$4:$U$42,IF($B8="Technical",'Project Portfolio'!$V$4:$V$42,IF($B8="Developer",'Project Portfolio'!$W$4:$W$42,IF($B8="Infrastructure",'Project Portfolio'!$X$4:$X$42,IF($B8="DBA",'Project Portfolio'!$Y$4:$Y$42,IF($B8="Project Manager",'Project Portfolio'!$Z$4:$Z$42,IF($B8="WMS Consultant",'Project Portfolio'!$AA$4:$AA$42,0))))))))/IF(INT(('Project Portfolio'!$J$4:$J$42-'Project Portfolio'!$I$4:$I$42)/7+1)>0,INT(('Project Portfolio'!$J$4:$J$42-'Project Portfolio'!$I$4:$I$42)/7+1),1)))/$D8,0)} -> 0
A9: Sangamesh Koti | B9: Technical | C9: Synnergie | D9: ='Team Roster'!K8 -> 35 | E9: {=IFERROR(SUMPRODUCT(('Project Portfolio'!$F$4:$F$42<>"✅ COMPLETE")*(('Project Portfolio'!$M$4:$M$42=$A9)+('Project Portfolio'!$N$4:$N$42=$A9)+('Project Portfolio'!$O$4:$O$42=$A9)+('Project Portfolio'!$P$4:$P$42=$A9)>0)*('Project Portfolio'!$I$4:$I$42>0)*('Project Portfolio'!$J$4:$J$42>0)*('Project Portfolio'!$I$4:$I$42<=E$4+6)*('Project Portfolio'!$J$4:$J$42>=E$4)*('Project Portfolio'!$R$4:$R$42*IF($B9="Business Analyst",'Project Portfolio'!$T$4:$T$42,IF($B9="Functional",'Project Portfolio'!$U$4:$U$42,IF($B9="Technical",'Project Portfolio'!$V$4:$V$42,IF($B9="Developer",'Project Portfolio'!$W$4:$W$42,IF($B9="Infrastructure",'Project Portfolio'!$X$4:$X$42,IF($B9="DBA",'Project Portfolio'!$Y$4:$Y$42,IF($B9="Project Manager",'Project Portfolio'!$Z$4:$Z$42,IF($B9="WMS Consultant",'Project Portfolio'!$AA$4:$AA$42,0))))))))/IF(INT(('Project Portfolio'!$J$4:$J$42-'Project Portfolio'!$I$4:$I$42)/7+1)>0,INT(('Project Portfolio'!$J$4:$J$42-'Project Portfolio'!$I$4:$I$42)/7+1),1)))/$D9,0)} -> 0 | F9: {=IFERROR(SUMPRODUCT(('Project Portfolio'!$F$4:$F$42<>"✅ COMPLETE")*(('Project Portfolio'!$M$4:$M$42=$A9)+('Project Portfolio'!$N$4:$N$42=$A9)+('Project Portfolio'!$O$4:$O$42=$A9)+('Project Portfolio'!$P$4:$P$42=$A9)>0)*('Project Portfolio'!$I$4:$I$42>0)*('Project Portfolio'!$J$4:$J$42>0)*('Project Portfolio'!$I$4:$I$42<=F$4+6)*('Project Portfolio'!$J$4:$J$42>=F$4)*('Project Portfolio'!$R$4:$R$42*IF($B9="Business Analyst",'Project Portfolio'!$T$4:$T$42,IF($B9="Functional",'Project Portfolio'!$U$4:$U$42,IF($B9="Technical",'Project Portfolio'!$V$4:$V$42,IF($B9="Developer",'Project Portfolio'!$W$4:$W$42,IF($B9="Infrastructure",'Project Portfolio'!$X$4:$X$42,IF($B9="DBA",'Project Portfolio'!$Y$4:$Y$42,IF($B9="Project Manager",'Project Portfolio'!$Z$4:$Z$42,IF($B9="WMS Consultant",'Project Portfolio'!$AA$4:$AA$42,0))))))))/IF(INT(('Project Portfolio'!$J$4:$J$42-'Project Portfolio'!$I$4:$I$42)/7+1)>0,INT(('Project Portfolio'!$J$4:$J$42-'Project Portfolio'!$I$4:$I$42)/7+1),1)))/$D9,0)} -> 0 | G9: {=IFERROR(SUMPRODUCT(('Project Portfolio'!$F$4:$F$42<>"✅ COMPLETE")*(('Project Portfolio'!$M$4:$M$42=$A9)+('Project Portfolio'!$N$4:$N$42=$A9)+('Project Portfolio'!$O$4:$O$42=$A9)+('Project Portfolio'!$P$4:$P$42=$A9)>0)*('Project Portfolio'!$I$4:$I$42>0)*('Project Portfolio'!$J$4:$J$42>0)*('Project Portfolio'!$I$4:$I$42<=G$4+6)*('Project Portfolio'!$J$4:$J$42>=G$4)*('Project Portfolio'!$R$4:$R$42*IF($B9="Business Analyst",'Project Portfolio'!$T$4:$T$42,IF($B9="Functional",'Project Portfolio'!$U$4:$U$42,IF($B9="Technical",'Project Portfolio'!$V$4:$V$42,IF($B9="Developer",'Project Portfolio'!$W$4:$W$42,IF($B9="Infrastructure",'Project Portfolio'!$X$4:$X$42,IF($B9="DBA",'Project Portfolio'!$Y$4:$Y$42,IF($B9="Project Manager",'Project Portfolio'!$Z$4:$Z$42,IF($B9="WMS Consultant",'Project Portfolio'!$AA$4:$AA$42,0))))))))/IF(INT(('Project Portfolio'!$J$4:$J$42-'Project Portfolio'!$I$4:$I$42)/7+1)>0,INT(('Project Portfolio'!$J$4:$J$42-'Project Portfolio'!$I$4:$I$42)/7+1),1)))/$D9,0)} -> 0 | H9: {=IFERROR(SUMPRODUCT(('Project Portfolio'!$F$4:$F$42<>"✅ COMPLETE")*(('Project Portfolio'!$M$4:$M$42=$A9)+('Project Portfolio'!$N$4:$N$42=$A9)+('Project Portfolio'!$O$4:$O$42=$A9)+('Project Portfolio'!$P$4:$P$42=$A9)>0)*('Project Portfolio'!$I$4:$I$42>0)*('Project Portfolio'!$J$4:$J$42>0)*('Project Portfolio'!$I$4:$I$42<=H$4+6)*('Project Portfolio'!$J$4:$J$42>=H$4)*('Project Portfolio'!$R$4:$R$42*IF($B9="Business Analyst",'Project Portfolio'!$T$4:$T$42,IF($B9="Functional",'Project Portfolio'!$U$4:$U$42,IF($B9="Technical",'Project Portfolio'!$V$4:$V$42,IF($B9="Developer",'Project Portfolio'!$W$4:$W$42,IF($B9="Infrastructure",'Project Portfolio'!$X$4:$X$42,IF($B9="DBA",'Project Portfolio'!$Y$4:$Y$42,IF($B9="Project Manager",'Project Portfolio'!$Z$4:$Z$42,IF($B9="WMS Consultant",'Project Portfolio'!$AA$4:$AA$42,0))))))))/IF(INT(('Project Portfolio'!$J$4:$J$42-'Project Portfolio'!$I$4:$I$42)/7+1)>0,INT(('Project Portfolio'!$J$4:$J$42-'Project Portfolio'!$I$4:$I$42)/7+1),1)))/$D9,0)} -> 0 | I9: {=IFERROR(SUMPRODUCT(('Project Portfolio'!$F$4:$F$42<>"✅ COMPLETE")*(('Project Portfolio'!$M$4:$M$42=$A9)+('Project Portfolio'!$N$4:$N$42=$A9)+('Project Portfolio'!$O$4:$O$42=$A9)+('Project Portfolio'!$P$4:$P$42=$A9)>0)*('Project Portfolio'!$I$4:$I$42>0)*('Project Portfolio'!$J$4:$J$42>0)*('Project Portfolio'!$I$4:$I$42<=I$4+6)*('Project Portfolio'!$J$4:$J$42>=I$4)*('Project Portfolio'!$R$4:$R$42*IF($B9="Business Analyst",'Project Portfolio'!$T$4:$T$42,IF($B9="Functional",'Project Portfolio'!$U$4:$U$42,IF($B9="Technical",'Project Portfolio'!$V$4:$V$42,IF($B9="Developer",'Project Portfolio'!$W$4:$W$42,IF($B9="Infrastructure",'Project Portfolio'!$X$4:$X$42,IF($B9="DBA",'Project Portfolio'!$Y$4:$Y$42,IF($B9="Project Manager",'Project Portfolio'!$Z$4:$Z$42,IF($B9="WMS Consultant",'Project Portfolio'!$AA$4:$AA$42,0))))))))/IF(INT(('Project Portfolio'!$J$4:$J$42-'Project Portfolio'!$I$4:$I$42)/7+1)>0,INT(('Project Portfolio'!$J$4:$J$42-'Project Portfolio'!$I$4:$I$42)/7+1),1)))/$D9,0)} -> 0 | J9: {=IFERROR(SUMPRODUCT(('Project Portfolio'!$F$4:$F$42<>"✅ COMPLETE")*(('Project Portfolio'!$M$4:$M$42=$A9)+('Project Portfolio'!$N$4:$N$42=$A9)+('Project Portfolio'!$O$4:$O$42=$A9)+('Project Portfolio'!$P$4:$P$42=$A9)>0)*('Project Portfolio'!$I$4:$I$42>0)*('Project Portfolio'!$J$4:$J$42>0)*('Project Portfolio'!$I$4:$I$42<=J$4+6)*('Project Portfolio'!$J$4:$J$42>=J$4)*('Project Portfolio'!$R$4:$R$42*IF($B9="Business Analyst",'Project Portfolio'!$T$4:$T$42,IF($B9="Functional",'Project Portfolio'!$U$4:$U$42,IF($B9="Technical",'Project Portfolio'!$V$4:$V$42,IF($B9="Developer",'Project Portfolio'!$W$4:$W$42,IF($B9="Infrastructure",'Project Portfolio'!$X$4:$X$42,IF($B9="DBA",'Project Portfolio'!$Y$4:$Y$42,IF($B9="Project Manager",'Project Portfolio'!$Z$4:$Z$42,IF($B9="WMS Consultant",'Project Portfolio'!$AA$4:$AA$42,0))))))))/IF(INT(('Project Portfolio'!$J$4:$J$42-'Project Portfolio'!$I$4:$I$42)/7+1)>0,INT(('Project Portfolio'!$J$4:$J$42-'Project Portfolio'!$I$4:$I$42)/7+1),1)))/$D9,0)} -> 0 | K9: {=IFERROR(SUMPRODUCT(('Project Portfolio'!$F$4:$F$42<>"✅ COMPLETE")*(('Project Portfolio'!$M$4:$M$42=$A9)+('Project Portfolio'!$N$4:$N$42=$A9)+('Project Portfolio'!$O$4:$O$42=$A9)+('Project Portfolio'!$P$4:$P$42=$A9)>0)*('Project Portfolio'!$I$4:$I$42>0)*('Project Portfolio'!$J$4:$J$42>0)*('Project Portfolio'!$I$4:$I$42<=K$4+6)*('Project Portfolio'!$J$4:$J$42>=K$4)*('Project Portfolio'!$R$4:$R$42*IF($B9="Business Analyst",'Project Portfolio'!$T$4:$T$42,IF($B9="Functional",'Project Portfolio'!$U$4:$U$42,IF($B9="Technical",'Project Portfolio'!$V$4:$V$42,IF($B9="Developer",'Project Portfolio'!$W$4:$W$42,IF($B9="Infrastructure",'Project Portfolio'!$X$4:$X$42,IF($B9="DBA",'Project Portfolio'!$Y$4:$Y$42,IF($B9="Project Manager",'Project Portfolio'!$Z$4:$Z$42,IF($B9="WMS Consultant",'Project Portfolio'!$AA$4:$AA$42,0))))))))/IF(INT(('Project Portfolio'!$J$4:$J$42-'Project Portfolio'!$I$4:$I$42)/7+1)>0,INT(('Project Portfolio'!$J$4:$J$42-'Project Portfolio'!$I$4:$I$42)/7+1),1)))/$D9,0)} -> 0 | L9: {=IFERROR(SUMPRODUCT(('Project Portfolio'!$F$4:$F$42<>"✅ COMPLETE")*(('Project Portfolio'!$M$4:$M$42=$A9)+('Project Portfolio'!$N$4:$N$42=$A9)+('Project Portfolio'!$O$4:$O$42=$A9)+('Project Portfolio'!$P$4:$P$42=$A9)>0)*('Project Portfolio'!$I$4:$I$42>0)*('Project Portfolio'!$J$4:$J$42>0)*('Project Portfolio'!$I$4:$I$42<=L$4+6)*('Project Portfolio'!$J$4:$J$42>=L$4)*('Project Portfolio'!$R$4:$R$42*IF($B9="Business Analyst",'Project Portfolio'!$T$4:$T$42,IF($B9="Functional",'Project Portfolio'!$U$4:$U$42,IF($B9="Technical",'Project Portfolio'!$V$4:$V$42,IF($B9="Developer",'Project Portfolio'!$W$4:$W$42,IF($B9="Infrastructure",'Project Portfolio'!$X$4:$X$42,IF($B9="DBA",'Project Portfolio'!$Y$4:$Y$42,IF($B9="Project Manager",'Project Portfolio'!$Z$4:$Z$42,IF($B9="WMS Consultant",'Project Portfolio'!$AA$4:$AA$42,0))))))))/IF(INT(('Project Portfolio'!$J$4:$J$42-'Project Portfolio'!$I$4:$I$42)/7+1)>0,INT(('Project Portfolio'!$J$4:$J$42-'Project Portfolio'!$I$4:$I$42)/7+1),1)))/$D9,0)} -> 0 | ... AD9: {=IFERROR(SUMPRODUCT(('Project Portfolio'!$F$4:$F$42<>"✅ COMPLETE")*(('Project Portfolio'!$M$4:$M$42=$A9)+('Project Portfolio'!$N$4:$N$42=$A9)+('Project Portfolio'!$O$4:$O$42=$A9)+('Project Portfolio'!$P$4:$P$42=$A9)>0)*('Project Portfolio'!$I$4:$I$42>0)*('Project Portfolio'!$J$4:$J$42>0)*('Project Portfolio'!$I$4:$I$42<=AD$4+6)*('Project Portfolio'!$J$4:$J$42>=AD$4)*('Project Portfolio'!$R$4:$R$42*IF($B9="Business Analyst",'Project Portfolio'!$T$4:$T$42,IF($B9="Functional",'Project Portfolio'!$U$4:$U$42,IF($B9="Technical",'Project Portfolio'!$V$4:$V$42,IF($B9="Developer",'Project Portfolio'!$W$4:$W$42,IF($B9="Infrastructure",'Project Portfolio'!$X$4:$X$42,IF($B9="DBA",'Project Portfolio'!$Y$4:$Y$42,IF($B9="Project Manager",'Project Portfolio'!$Z$4:$Z$42,IF($B9="WMS Consultant",'Project Portfolio'!$AA$4:$AA$42,0))))))))/IF(INT(('Project Portfolio'!$J$4:$J$42-'Project Portfolio'!$I$4:$I$42)/7+1)>0,INT(('Project Portfolio'!$J$4:$J$42-'Project Portfolio'!$I$4:$I$42)/7+1),1)))/$D9,0)} -> 0
